Workbook

Sheet Character
A1: WARHAMMER FANTASY ROLEPLAY 5E — CHARACTER
A2: White cells: enter values · Grey cells: calculated · Yellow: starting (free) advances · Dropdowns accept custom text (a warning is shown).
A3: Name | F3: Species | M3: Career
A4: Career level | F4: Career title | H4: =IF(OR($O$3="",$B$4=""),"",IFERROR(INDEX(Data_Careers!$E:$E,MATCH($O$3&"|"&$B$4,Data_Careers!$A:$A,0)),"")) | M4: Class | O4: =IF($O$3="","",IFERROR(INDEX(Data_Careers!$D:$D,MATCH($O$3&"|1",Data_Careers!$A:$A,0)),""))
A5: Status | B5: =IF(OR($O$3="",$B$4=""),"",IFERROR(INDEX(Data_Careers!$F:$F,MATCH($O$3&"|"&$B$4,Data_Careers!$A:$A,0)),"")) | F5: Income skill | H5: =IF($O$3="","",IFERROR(INDEX(Data_Careers!$M:$M,MATCH($O$3&"|1",Data_Careers!$A:$A,0)),"")) | M5: Age
A6: Height | F6: Eyes | M6: Hair
A7: Ambition | M7: Party ambition
A9: CHARACTERISTICS | M9: ATTRIBUTES
B10: WS | C10: BS | D10: S | E10: T | F10: I | G10: Ag | H10: Dex | I10: Int | J10: WP | K10: Fel | O10: Current | P10: Max | Q10: How it is calculated
A11: Initial (species + roll + career pts) | M11: Wounds | P11: =$D$17+$J$17+2*$E$17+$E$17*SUMIF($M$27:$M$77,"Hardy",$U$27:$U$77) | Q11: SB + WPB + 2×TB (+TB per Hardy)
A12: Advances (+5 each) | B12: 0 | C12: 0 | D12: 0 | E12: 0 | F12: 0 | G12: 0 | H12: 0 | I12: 0 | J12: 0 | K12: 0 | M12: Fate | P12: =IF($H$3="","",IFERROR(INDEX(Data_Lists!$B$2:$B$6,MATCH($H$3,Data_Lists!$A$2:$A$6,0)),"")) | Q12: Species Fate (+1 if you kept all first rolls)
A13: …of which non-career | B13: 0 | C13: 0 | D13: 0 | E13: 0 | F13: 0 | G13: 0 | H13: 0 | I13: 0 | J13: 0 | K13: 0 | M13: Fortune | P13: =IF($H$3="","",IFERROR(INDEX(Data_Lists!$C$2:$C$6,MATCH($H$3,Data_Lists!$A$2:$A$6,0)),"")+MIN(3,SUMIF($M$27:$M$77,"Luck",$U$27:$U$77))) | Q13: Species Fortune (+1 if you kept the species roll) + Luck
A14: Talent bonus (auto) | B14: =5*SUMIF($T$27:$T$77,B$10,$U$27:$U$77) | C14: =5*SUMIF($T$27:$T$77,C$10,$U$27:$U$77) | D14: =5*SUMIF($T$27:$T$77,D$10,$U$27:$U$77) | E14: =5*SUMIF($T$27:$T$77,E$10,$U$27:$U$77) | F14: =5*SUMIF($T$27:$T$77,F$10,$U$27:$U$77) | G14: =5*SUMIF($T$27:$T$77,G$10,$U$27:$U$77) | H14: =5*SUMIF($T$27:$T$77,H$10,$U$27:$U$77) | I14: =5*SUMIF($T$27:$T$77,I$10,$U$27:$U$77) | ... K14: =5*SUMIF($T$27:$T$77,K$10,$U$27:$U$77) | M14: Movement | O14: =IF($H$3="","",IFERROR(INDEX(Data_Lists!$D$2:$D$6,MATCH($H$3,Data_Lists!$A$2:$A$6,0)),"")+IF(SUMIF($M$27:$M$77,"Fleet-footed",$U$27:$U$77)>0,1,0)) | Q14: Species Move (+1 Fleet-footed)
A15: Other modifier | B15: 0 | C15: 0 | D15: 0 | E15: 0 | F15: 0 | G15: 0 | H15: 0 | I15: 0 | J15: 0 | K15: 0 | M15: Walk / Run | O15: =IF(O14="","",O14*2&" / "&O14*4) | Q15: Walk = 2×M, Run = 4×M (yards per round)
A16: CURRENT | B16: =N(B11)+N(B12)+N(B14)+N(B15) | C16: =N(C11)+N(C12)+N(C14)+N(C15) | D16: =N(D11)+N(D12)+N(D14)+N(D15) | E16: =N(E11)+N(E12)+N(E14)+N(E15) | F16: =N(F11)+N(F12)+N(F14)+N(F15) | G16: =N(G11)+N(G12)+N(G14)+N(G15) | H16: =N(H11)+N(H12)+N(H14)+N(H15) | I16: =N(I11)+N(I12)+N(I14)+N(I15) | ... K16: =N(K11)+N(K12)+N(K14)+N(K15) | M16: Encumbrance | O16: =Equipment!$B$90 | P16: =$D$17*IF(SUMIF($M$27:$M$77,"Sturdy",$U$27:$U$77)>0,2,1)+$E$17+IF(SUMIF($M$27:$M$77,"Strong Back",$U$27:$U$77)>=2,3,SUMIF($M$27:$M$77,"Strong Back",$U$27:$U$77))+N(O17) | Q16: Carried (Equipment tab) / max SB + TB (SB×2 Sturdy, +Strong Back)
A17: Bonus | B17: =INT(B16/10) | C17: =INT(C16/10) | D17: =INT(D16/10) | E17: =INT(E16/10) | F17: =INT(F16/10) | G17: =INT(G16/10) | H17: =INT(H16/10) | I17: =INT(I16/10) | ... K17: =INT(K16/10) | M17: Max Enc adjust | O17: 0 | Q17: GM rulings, Dwarf house rule etc.
A18: Career characteristic (★ now, Ln = opens at level n) | B18: =IF($O$3="","",IFERROR(IF(INDEX(Data_Careers!$P:$P,MATCH($O$3&"|1",Data_Careers!$A:$A,0))="","",IF(INDEX(Data_Careers!$P:$P,MATCH($O$3&"|1",Data_Careers!$A:$A,0))<=N($B$4),"★","L"&INDEX(Data_Careers!$P:$P,MATCH($O$3&"|1",Data_Careers!$A:$A,0)))),"")) | C18: =IF($O$3="","",IFERROR(IF(INDEX(Data_Careers!$Q:$Q,MATCH($O$3&"|1",Data_Careers!$A:$A,0))="","",IF(INDEX(Data_Careers!$Q:$Q,MATCH($O$3&"|1",Data_Careers!$A:$A,0))<=N($B$4),"★","L"&INDEX(Data_Careers!$Q:$Q,MATCH($O$3&"|1",Data_Careers!$A:$A,0)))),"")) | D18: =IF($O$3="","",IFERROR(IF(INDEX(Data_Careers!$R:$R,MATCH($O$3&"|1",Data_Careers!$A:$A,0))="","",IF(INDEX(Data_Careers!$R:$R,MATCH($O$3&"|1",Data_Careers!$A:$A,0))<=N($B$4),"★","L"&INDEX(Data_Careers!$R:$R,MATCH($O$3&"|1",Data_Careers!$A:$A,0)))),"")) | E18: =IF($O$3="","",IFERROR(IF(INDEX(Data_Careers!$S:$S,MATCH($O$3&"|1",Data_Careers!$A:$A,0))="","",IF(INDEX(Data_Careers!$S:$S,MATCH($O$3&"|1",Data_Careers!$A:$A,0))<=N($B$4),"★","L"&INDEX(Data_Careers!$S:$S,MATCH($O$3&"|1",Data_Careers!$A:$A,0)))),"")) | F18: =IF($O$3="","",IFERROR(IF(INDEX(Data_Careers!$T:$T,MATCH($O$3&"|1",Data_Careers!$A:$A,0))="","",IF(INDEX(Data_Careers!$T:$T,MATCH($O$3&"|1",Data_Careers!$A:$A,0))<=N($B$4),"★","L"&INDEX(Data_Careers!$T:$T,MATCH($O$3&"|1",Data_Careers!$A:$A,0)))),"")) | G18: =IF($O$3="","",IFERROR(IF(INDEX(Data_Careers!$U:$U,MATCH($O$3&"|1",Data_Careers!$A:$A,0))="","",IF(INDEX(Data_Careers!$U:$U,MATCH($O$3&"|1",Data_Careers!$A:$A,0))<=N($B$4),"★","L"&INDEX(Data_Careers!$U:$U,MATCH($O$3&"|1",Data_Careers!$A:$A,0)))),"")) | H18: =IF($O$3="","",IFERROR(IF(INDEX(Data_Careers!$V:$V,MATCH($O$3&"|1",Data_Careers!$A:$A,0))="","",IF(INDEX(Data_Careers!$V:$V,MATCH($O$3&"|1",Data_Careers!$A:$A,0))<=N($B$4),"★","L"&INDEX(Data_Careers!$V:$V,MATCH($O$3&"|1",Data_Careers!$A:$A,0)))),"")) | I18: =IF($O$3="","",IFERROR(IF(INDEX(Data_Careers!$W:$W,MATCH($O$3&"|1",Data_Careers!$A:$A,0))="","",IF(INDEX(Data_Careers!$W:$W,MATCH($O$3&"|1",Data_Careers!$A:$A,0))<=N($B$4),"★","L"&INDEX(Data_Careers!$W:$W,MATCH($O$3&"|1",Data_Careers!$A:$A,0)))),"")) | J18: =IF($O$3="","",IFERROR(IF(INDEX(Data_Careers!$X:$X,MATCH($O$3&"|1",Data_Careers!$A:$A,0))="","",IF(INDEX(Data_Careers!$X:$X,MATCH($O$3&"|1",Data_Careers!$A:$A,0))<=N($B$4),"★","L"&INDEX(Data_Careers!$X:$X,MATCH($O$3&"|1",Data_Careers!$A:$A,0)))),"")) | K18: =IF($O$3="","",IFERROR(IF(INDEX(Data_Careers!$Y:$Y,MATCH($O$3&"|1",Data_Careers!$A:$A,0))="","",IF(INDEX(Data_Careers!$Y:$Y,MATCH($O$3&"|1",Data_Careers!$A:$A,0))<=N($B$4),"★","L"&INDEX(Data_Careers!$Y:$Y,MATCH($O$3&"|1",Data_Careers!$A:$A,0)))),"")) | M18: Career ticks | P18: =IF(N($B$4)>=4,"top",IF(N($B$4)=0,"",CHOOSE($B$4,10,12,14))) | Q18: Ticks needed to reach the next level
A19: XP spent | B19: =IFERROR(2*INDEX(Data_Lists!$AF$2:$AF$17,N(B12)/5+1)-INDEX(Data_Lists!$AF$2:$AF$17,(N(B12)-N(B13))/5+1),"?") | C19: =IFERROR(2*INDEX(Data_Lists!$AF$2:$AF$17,N(C12)/5+1)-INDEX(Data_Lists!$AF$2:$AF$17,(N(C12)-N(C13))/5+1),"?") | D19: =IFERROR(2*INDEX(Data_Lists!$AF$2:$AF$17,N(D12)/5+1)-INDEX(Data_Lists!$AF$2:$AF$17,(N(D12)-N(D13))/5+1),"?") | E19: =IFERROR(2*INDEX(Data_Lists!$AF$2:$AF$17,N(E12)/5+1)-INDEX(Data_Lists!$AF$2:$AF$17,(N(E12)-N(E13))/5+1),"?") | F19: =IFERROR(2*INDEX(Data_Lists!$AF$2:$AF$17,N(F12)/5+1)-INDEX(Data_Lists!$AF$2:$AF$17,(N(F12)-N(F13))/5+1),"?") | G19: =IFERROR(2*INDEX(Data_Lists!$AF$2:$AF$17,N(G12)/5+1)-INDEX(Data_Lists!$AF$2:$AF$17,(N(G12)-N(G13))/5+1),"?") | H19: =IFERROR(2*INDEX(Data_Lists!$AF$2:$AF$17,N(H12)/5+1)-INDEX(Data_Lists!$AF$2:$AF$17,(N(H12)-N(H13))/5+1),"?") | I19: =IFERROR(2*INDEX(Data_Lists!$AF$2:$AF$17,N(I12)/5+1)-INDEX(Data_Lists!$AF$2:$AF$17,(N(I12)-N(I13))/5+1),"?") | ... K19: =IFERROR(2*INDEX(Data_Lists!$AF$2:$AF$17,N(K12)/5+1)-INDEX(Data_Lists!$AF$2:$AF$17,(N(K12)-N(K13))/5+1),"?")
A21: EXPERIENCE
A22: XP earned | C22: XP spent | E22: =B23+E23+H23+K23+O23+N(R22) | F22: XP available | H22: =N(B22)-E22 | M22: Other XP spent (endeavours, training…) | R22: 0
A23: Characteristics | B23: =SUM(B19:K19) | C23: Skills | E23: =SUM(H27:H77) | F23: Talents | H23: =SUM(R27:R77) | I23: Careers | K23: =SUM(I81:I86) | M23: Spells & Prayers | O23: ='Spells & Prayers'!$B$4
A25: SKILLS | M25: TALENTS
A26: Skill | B26: Char | C26: Char value | D26: Starting adv (free) | E26: Total adv | F26: …non-career | G26: Skill value | H26: XP cost | I26: Career skill | M26: Talent | P26: Times taken | Q26: Bought with XP? | R26: XP cost | S26: Career talent
A27: Art | B27: =IF(A27="","",IFERROR(IFERROR(INDEX(Data_Skills!$C:$C,MATCH(A27,Data_Skills!$A:$A,0))&"",INDEX(Data_Skills!$C:$C,MATCH(TRIM(IFERROR(LEFT(A27,FIND("(",A27)-1),A27)),Data_Skills!$B:$B,0))&""),"")) | C27: =IF(B27="","",INDEX($B$16:$K$16,MATCH(B27,$B$10:$K$10,0))) | D27: 0 | E27: 0 | F27: 0 | G27: =IF(OR(A27="",C27=""),"",C27+N(E27)) | H27: =IF(A27="","",IFERROR(MAX(0,2*INDEX(Data_Lists!$AG$2:$AG$17,N(E27)/5+1)-INDEX(Data_Lists!$AG$2:$AG$17,N(D27)/5+1)-INDEX(Data_Lists!$AG$2:$AG$17,(N(E27)-N(F27))/5+1)),"?")) | I27: =IF(OR(A27="",$O$3=""),"",IF(OR(ISNUMBER(SEARCH("|"&A27&"|",IFERROR(INDEX(Data_Careers!$J:$J,MATCH($O$3&"|"&$B$4,Data_Careers!$A:$A,0)),""))),ISNUMBER(SEARCH("|"&TRIM(IFERROR(LEFT(A27,FIND("(",A27)-1),A27))&" (any)|",IFERROR(INDEX(Data_Careers!$J:$J,MATCH($O$3&"|"&$B$4,Data_Careers!$A:$A,0)),"")))),"★","")) | R27: =IF(M27="","",IF(Q27="Yes",100*U27,0)) | S27: =IF(OR(M27="",$O$3=""),"",IF(OR(ISNUMBER(SEARCH("|"&M27&"|",IFERROR(INDEX(Data_Careers!$K:$K,MATCH($O$3&"|"&$B$4,Data_Careers!$A:$A,0)),""))),ISNUMBER(SEARCH("|"&TRIM(IFERROR(LEFT(M27,FIND("(",M27)-1),M27))&" (any)|",IFERROR(INDEX(Data_Careers!$K:$K,MATCH($O$3&"|"&$B$4,Data_Careers!$A:$A,0)),"")))),"★","")) | T27: =IF(M27="","",IFERROR(IFERROR(INDEX(Data_Talents!$D:$D,MATCH(M27,Data_Talents!$A:$A,0))&"",INDEX(Data_Talents!$D:$D,MATCH(TRIM(IFERROR(LEFT(M27,FIND("(",M27)-1),M27)),Data_Talents!$B:$B,0))&""),"")) | U27: =IF(M27="",0,IF(N(P27)=0,1,N(P27)))
A28: Athletics | B28: =IF(A28="","",IFERROR(IFERROR(INDEX(Data_Skills!$C:$C,MATCH(A28,Data_Skills!$A:$A,0))&"",INDEX(Data_Skills!$C:$C,MATCH(TRIM(IFERROR(LEFT(A28,FIND("(",A28)-1),A28)),Data_Skills!$B:$B,0))&""),"")) | C28: =IF(B28="","",INDEX($B$16:$K$16,MATCH(B28,$B$10:$K$10,0))) | D28: 0 | E28: 0 | F28: 0 | G28: =IF(OR(A28="",C28=""),"",C28+N(E28)) | H28: =IF(A28="","",IFERROR(MAX(0,2*INDEX(Data_Lists!$AG$2:$AG$17,N(E28)/5+1)-INDEX(Data_Lists!$AG$2:$AG$17,N(D28)/5+1)-INDEX(Data_Lists!$AG$2:$AG$17,(N(E28)-N(F28))/5+1)),"?")) | I28: =IF(OR(A28="",$O$3=""),"",IF(OR(ISNUMBER(SEARCH("|"&A28&"|",IFERROR(INDEX(Data_Careers!$J:$J,MATCH($O$3&"|"&$B$4,Data_Careers!$A:$A,0)),""))),ISNUMBER(SEARCH("|"&TRIM(IFERROR(LEFT(A28,FIND("(",A28)-1),A28))&" (any)|",IFERROR(INDEX(Data_Careers!$J:$J,MATCH($O$3&"|"&$B$4,Data_Careers!$A:$A,0)),"")))),"★","")) | R28: =IF(M28="","",IF(Q28="Yes",100*U28,0)) | S28: =IF(OR(M28="",$O$3=""),"",IF(OR(ISNUMBER(SEARCH("|"&M28&"|",IFERROR(INDEX(Data_Careers!$K:$K,MATCH($O$3&"|"&$B$4,Data_Careers!$A:$A,0)),""))),ISNUMBER(SEARCH("|"&TRIM(IFERROR(LEFT(M28,FIND("(",M28)-1),M28))&" (any)|",IFERROR(INDEX(Data_Careers!$K:$K,MATCH($O$3&"|"&$B$4,Data_Careers!$A:$A,0)),"")))),"★","")) | T28: =IF(M28="","",IFERROR(IFERROR(INDEX(Data_Talents!$D:$D,MATCH(M28,Data_Talents!$A:$A,0))&"",INDEX(Data_Talents!$D:$D,MATCH(TRIM(IFERROR(LEFT(M28,FIND("(",M28)-1),M28)),Data_Talents!$B:$B,0))&""),"")) | U28: =IF(M28="",0,IF(N(P28)=0,1,N(P28)))
A29: Bribery | B29: =IF(A29="","",IFERROR(IFERROR(INDEX(Data_Skills!$C:$C,MATCH(A29,Data_Skills!$A:$A,0))&"",INDEX(Data_Skills!$C:$C,MATCH(TRIM(IFERROR(LEFT(A29,FIND("(",A29)-1),A29)),Data_Skills!$B:$B,0))&""),"")) | C29: =IF(B29="","",INDEX($B$16:$K$16,MATCH(B29,$B$10:$K$10,0))) | D29: 0 | E29: 0 | F29: 0 | G29: =IF(OR(A29="",C29=""),"",C29+N(E29)) | H29: =IF(A29="","",IFERROR(MAX(0,2*INDEX(Data_Lists!$AG$2:$AG$17,N(E29)/5+1)-INDEX(Data_Lists!$AG$2:$AG$17,N(D29)/5+1)-INDEX(Data_Lists!$AG$2:$AG$17,(N(E29)-N(F29))/5+1)),"?")) | I29: =IF(OR(A29="",$O$3=""),"",IF(OR(ISNUMBER(SEARCH("|"&A29&"|",IFERROR(INDEX(Data_Careers!$J:$J,MATCH($O$3&"|"&$B$4,Data_Careers!$A:$A,0)),""))),ISNUMBER(SEARCH("|"&TRIM(IFERROR(LEFT(A29,FIND("(",A29)-1),A29))&" (any)|",IFERROR(INDEX(Data_Careers!$J:$J,MATCH($O$3&"|"&$B$4,Data_Careers!$A:$A,0)),"")))),"★","")) | R29: =IF(M29="","",IF(Q29="Yes",100*U29,0)) | S29: =IF(OR(M29="",$O$3=""),"",IF(OR(ISNUMBER(SEARCH("|"&M29&"|",IFERROR(INDEX(Data_Careers!$K:$K,MATCH($O$3&"|"&$B$4,Data_Careers!$A:$A,0)),""))),ISNUMBER(SEARCH("|"&TRIM(IFERROR(LEFT(M29,FIND("(",M29)-1),M29))&" (any)|",IFERROR(INDEX(Data_Careers!$K:$K,MATCH($O$3&"|"&$B$4,Data_Careers!$A:$A,0)),"")))),"★","")) | T29: =IF(M29="","",IFERROR(IFERROR(INDEX(Data_Talents!$D:$D,MATCH(M29,Data_Talents!$A:$A,0))&"",INDEX(Data_Talents!$D:$D,MATCH(TRIM(IFERROR(LEFT(M29,FIND("(",M29)-1),M29)),Data_Talents!$B:$B,0))&""),"")) | U29: =IF(M29="",0,IF(N(P29)=0,1,N(P29)))
A30: Charm | B30: =IF(A30="","",IFERROR(IFERROR(INDEX(Data_Skills!$C:$C,MATCH(A30,Data_Skills!$A:$A,0))&"",INDEX(Data_Skills!$C:$C,MATCH(TRIM(IFERROR(LEFT(A30,FIND("(",A30)-1),A30)),Data_Skills!$B:$B,0))&""),"")) | C30: =IF(B30="","",INDEX($B$16:$K$16,MATCH(B30,$B$10:$K$10,0))) | D30: 0 | E30: 0 | F30: 0 | G30: =IF(OR(A30="",C30=""),"",C30+N(E30)) | H30: =IF(A30="","",IFERROR(MAX(0,2*INDEX(Data_Lists!$AG$2:$AG$17,N(E30)/5+1)-INDEX(Data_Lists!$AG$2:$AG$17,N(D30)/5+1)-INDEX(Data_Lists!$AG$2:$AG$17,(N(E30)-N(F30))/5+1)),"?")) | I30: =IF(OR(A30="",$O$3=""),"",IF(OR(ISNUMBER(SEARCH("|"&A30&"|",IFERROR(INDEX(Data_Careers!$J:$J,MATCH($O$3&"|"&$B$4,Data_Careers!$A:$A,0)),""))),ISNUMBER(SEARCH("|"&TRIM(IFERROR(LEFT(A30,FIND("(",A30)-1),A30))&" (any)|",IFERROR(INDEX(Data_Careers!$J:$J,MATCH($O$3&"|"&$B$4,Data_Careers!$A:$A,0)),"")))),"★","")) | R30: =IF(M30="","",IF(Q30="Yes",100*U30,0)) | S30: =IF(OR(M30="",$O$3=""),"",IF(OR(ISNUMBER(SEARCH("|"&M30&"|",IFERROR(INDEX(Data_Careers!$K:$K,MATCH($O$3&"|"&$B$4,Data_Careers!$A:$A,0)),""))),ISNUMBER(SEARCH("|"&TRIM(IFERROR(LEFT(M30,FIND("(",M30)-1),M30))&" (any)|",IFERROR(INDEX(Data_Careers!$K:$K,MATCH($O$3&"|"&$B$4,Data_Careers!$A:$A,0)),"")))),"★","")) | T30: =IF(M30="","",IFERROR(IFERROR(INDEX(Data_Talents!$D:$D,MATCH(M30,Data_Talents!$A:$A,0))&"",INDEX(Data_Talents!$D:$D,MATCH(TRIM(IFERROR(LEFT(M30,FIND("(",M30)-1),M30)),Data_Talents!$B:$B,0))&""),"")) | U30: =IF(M30="",0,IF(N(P30)=0,1,N(P30)))
A31: Charm Animal | B31: =IF(A31="","",IFERROR(IFERROR(INDEX(Data_Skills!$C:$C,MATCH(A31,Data_Skills!$A:$A,0))&"",INDEX(Data_Skills!$C:$C,MATCH(TRIM(IFERROR(LEFT(A31,FIND("(",A31)-1),A31)),Data_Skills!$B:$B,0))&""),"")) | C31: =IF(B31="","",INDEX($B$16:$K$16,MATCH(B31,$B$10:$K$10,0))) | D31: 0 | E31: 0 | F31: 0 | G31: =IF(OR(A31="",C31=""),"",C31+N(E31)) | H31: =IF(A31="","",IFERROR(MAX(0,2*INDEX(Data_Lists!$AG$2:$AG$17,N(E31)/5+1)-INDEX(Data_Lists!$AG$2:$AG$17,N(D31)/5+1)-INDEX(Data_Lists!$AG$2:$AG$17,(N(E31)-N(F31))/5+1)),"?")) | I31: =IF(OR(A31="",$O$3=""),"",IF(OR(ISNUMBER(SEARCH("|"&A31&"|",IFERROR(INDEX(Data_Careers!$J:$J,MATCH($O$3&"|"&$B$4,Data_Careers!$A:$A,0)),""))),ISNUMBER(SEARCH("|"&TRIM(IFERROR(LEFT(A31,FIND("(",A31)-1),A31))&" (any)|",IFERROR(INDEX(Data_Careers!$J:$J,MATCH($O$3&"|"&$B$4,Data_Careers!$A:$A,0)),"")))),"★","")) | R31: =IF(M31="","",IF(Q31="Yes",100*U31,0)) | S31: =IF(OR(M31="",$O$3=""),"",IF(OR(ISNUMBER(SEARCH("|"&M31&"|",IFERROR(INDEX(Data_Careers!$K:$K,MATCH($O$3&"|"&$B$4,Data_Careers!$A:$A,0)),""))),ISNUMBER(SEARCH("|"&TRIM(IFERROR(LEFT(M31,FIND("(",M31)-1),M31))&" (any)|",IFERROR(INDEX(Data_Careers!$K:$K,MATCH($O$3&"|"&$B$4,Data_Careers!$A:$A,0)),"")))),"★","")) | T31: =IF(M31="","",IFERROR(IFERROR(INDEX(Data_Talents!$D:$D,MATCH(M31,Data_Talents!$A:$A,0))&"",INDEX(Data_Talents!$D:$D,MATCH(TRIM(IFERROR(LEFT(M31,FIND("(",M31)-1),M31)),Data_Talents!$B:$B,0))&""),"")) | U31: =IF(M31="",0,IF(N(P31)=0,1,N(P31)))
A32: Climb | B32: =IF(A32="","",IFERROR(IFERROR(INDEX(Data_Skills!$C:$C,MATCH(A32,Data_Skills!$A:$A,0))&"",INDEX(Data_Skills!$C:$C,MATCH(TRIM(IFERROR(LEFT(A32,FIND("(",A32)-1),A32)),Data_Skills!$B:$B,0))&""),"")) | C32: =IF(B32="","",INDEX($B$16:$K$16,MATCH(B32,$B$10:$K$10,0))) | D32: 0 | E32: 0 | F32: 0 | G32: =IF(OR(A32="",C32=""),"",C32+N(E32)) | H32: =IF(A32="","",IFERROR(MAX(0,2*INDEX(Data_Lists!$AG$2:$AG$17,N(E32)/5+1)-INDEX(Data_Lists!$AG$2:$AG$17,N(D32)/5+1)-INDEX(Data_Lists!$AG$2:$AG$17,(N(E32)-N(F32))/5+1)),"?")) | I32: =IF(OR(A32="",$O$3=""),"",IF(OR(ISNUMBER(SEARCH("|"&A32&"|",IFERROR(INDEX(Data_Careers!$J:$J,MATCH($O$3&"|"&$B$4,Data_Careers!$A:$A,0)),""))),ISNUMBER(SEARCH("|"&TRIM(IFERROR(LEFT(A32,FIND("(",A32)-1),A32))&" (any)|",IFERROR(INDEX(Data_Careers!$J:$J,MATCH($O$3&"|"&$B$4,Data_Careers!$A:$A,0)),"")))),"★","")) | R32: =IF(M32="","",IF(Q32="Yes",100*U32,0)) | S32: =IF(OR(M32="",$O$3=""),"",IF(OR(ISNUMBER(SEARCH("|"&M32&"|",IFERROR(INDEX(Data_Careers!$K:$K,MATCH($O$3&"|"&$B$4,Data_Careers!$A:$A,0)),""))),ISNUMBER(SEARCH("|"&TRIM(IFERROR(LEFT(M32,FIND("(",M32)-1),M32))&" (any)|",IFERROR(INDEX(Data_Careers!$K:$K,MATCH($O$3&"|"&$B$4,Data_Careers!$A:$A,0)),"")))),"★","")) | T32: =IF(M32="","",IFERROR(IFERROR(INDEX(Data_Talents!$D:$D,MATCH(M32,Data_Talents!$A:$A,0))&"",INDEX(Data_Talents!$D:$D,MATCH(TRIM(IFERROR(LEFT(M32,FIND("(",M32)-1),M32)),Data_Talents!$B:$B,0))&""),"")) | U32: =IF(M32="",0,IF(N(P32)=0,1,N(P32)))
A33: Consume Alcohol | B33: =IF(A33="","",IFERROR(IFERROR(INDEX(Data_Skills!$C:$C,MATCH(A33,Data_Skills!$A:$A,0))&"",INDEX(Data_Skills!$C:$C,MATCH(TRIM(IFERROR(LEFT(A33,FIND("(",A33)-1),A33)),Data_Skills!$B:$B,0))&""),"")) | C33: =IF(B33="","",INDEX($B$16:$K$16,MATCH(B33,$B$10:$K$10,0))) | D33: 0 | E33: 0 | F33: 0 | G33: =IF(OR(A33="",C33=""),"",C33+N(E33)) | H33: =IF(A33="","",IFERROR(MAX(0,2*INDEX(Data_Lists!$AG$2:$AG$17,N(E33)/5+1)-INDEX(Data_Lists!$AG$2:$AG$17,N(D33)/5+1)-INDEX(Data_Lists!$AG$2:$AG$17,(N(E33)-N(F33))/5+1)),"?")) | I33: =IF(OR(A33="",$O$3=""),"",IF(OR(ISNUMBER(SEARCH("|"&A33&"|",IFERROR(INDEX(Data_Careers!$J:$J,MATCH($O$3&"|"&$B$4,Data_Careers!$A:$A,0)),""))),ISNUMBER(SEARCH("|"&TRIM(IFERROR(LEFT(A33,FIND("(",A33)-1),A33))&" (any)|",IFERROR(INDEX(Data_Careers!$J:$J,MATCH($O$3&"|"&$B$4,Data_Careers!$A:$A,0)),"")))),"★","")) | R33: =IF(M33="","",IF(Q33="Yes",100*U33,0)) | S33: =IF(OR(M33="",$O$3=""),"",IF(OR(ISNUMBER(SEARCH("|"&M33&"|",IFERROR(INDEX(Data_Careers!$K:$K,MATCH($O$3&"|"&$B$4,Data_Careers!$A:$A,0)),""))),ISNUMBER(SEARCH("|"&TRIM(IFERROR(LEFT(M33,FIND("(",M33)-1),M33))&" (any)|",IFERROR(INDEX(Data_Careers!$K:$K,MATCH($O$3&"|"&$B$4,Data_Careers!$A:$A,0)),"")))),"★","")) | T33: =IF(M33="","",IFERROR(IFERROR(INDEX(Data_Talents!$D:$D,MATCH(M33,Data_Talents!$A:$A,0))&"",INDEX(Data_Talents!$D:$D,MATCH(TRIM(IFERROR(LEFT(M33,FIND("(",M33)-1),M33)),Data_Talents!$B:$B,0))&""),"")) | U33: =IF(M33="",0,IF(N(P33)=0,1,N(P33)))
A34: Cool | B34: =IF(A34="","",IFERROR(IFERROR(INDEX(Data_Skills!$C:$C,MATCH(A34,Data_Skills!$A:$A,0))&"",INDEX(Data_Skills!$C:$C,MATCH(TRIM(IFERROR(LEFT(A34,FIND("(",A34)-1),A34)),Data_Skills!$B:$B,0))&""),"")) | C34: =IF(B34="","",INDEX($B$16:$K$16,MATCH(B34,$B$10:$K$10,0))) | D34: 0 | E34: 0 | F34: 0 | G34: =IF(OR(A34="",C34=""),"",C34+N(E34)) | H34: =IF(A34="","",IFERROR(MAX(0,2*INDEX(Data_Lists!$AG$2:$AG$17,N(E34)/5+1)-INDEX(Data_Lists!$AG$2:$AG$17,N(D34)/5+1)-INDEX(Data_Lists!$AG$2:$AG$17,(N(E34)-N(F34))/5+1)),"?")) | I34: =IF(OR(A34="",$O$3=""),"",IF(OR(ISNUMBER(SEARCH("|"&A34&"|",IFERROR(INDEX(Data_Careers!$J:$J,MATCH($O$3&"|"&$B$4,Data_Careers!$A:$A,0)),""))),ISNUMBER(SEARCH("|"&TRIM(IFERROR(LEFT(A34,FIND("(",A34)-1),A34))&" (any)|",IFERROR(INDEX(Data_Careers!$J:$J,MATCH($O$3&"|"&$B$4,Data_Careers!$A:$A,0)),"")))),"★","")) | R34: =IF(M34="","",IF(Q34="Yes",100*U34,0)) | S34: =IF(OR(M34="",$O$3=""),"",IF(OR(ISNUMBER(SEARCH("|"&M34&"|",IFERROR(INDEX(Data_Careers!$K:$K,MATCH($O$3&"|"&$B$4,Data_Careers!$A:$A,0)),""))),ISNUMBER(SEARCH("|"&TRIM(IFERROR(LEFT(M34,FIND("(",M34)-1),M34))&" (any)|",IFERROR(INDEX(Data_Careers!$K:$K,MATCH($O$3&"|"&$B$4,Data_Careers!$A:$A,0)),"")))),"★","")) | T34: =IF(M34="","",IFERROR(IFERROR(INDEX(Data_Talents!$D:$D,MATCH(M34,Data_Talents!$A:$A,0))&"",INDEX(Data_Talents!$D:$D,MATCH(TRIM(IFERROR(LEFT(M34,FIND("(",M34)-1),M34)),Data_Talents!$B:$B,0))&""),"")) | U34: =IF(M34="",0,IF(N(P34)=0,1,N(P34)))
A35: Dodge | B35: =IF(A35="","",IFERROR(IFERROR(INDEX(Data_Skills!$C:$C,MATCH(A35,Data_Skills!$A:$A,0))&"",INDEX(Data_Skills!$C:$C,MATCH(TRIM(IFERROR(LEFT(A35,FIND("(",A35)-1),A35)),Data_Skills!$B:$B,0))&""),"")) | C35: =IF(B35="","",INDEX($B$16:$K$16,MATCH(B35,$B$10:$K$10,0))) | D35: 0 | E35: 0 | F35: 0 | G35: =IF(OR(A35="",C35=""),"",C35+N(E35)) | H35: =IF(A35="","",IFERROR(MAX(0,2*INDEX(Data_Lists!$AG$2:$AG$17,N(E35)/5+1)-INDEX(Data_Lists!$AG$2:$AG$17,N(D35)/5+1)-INDEX(Data_Lists!$AG$2:$AG$17,(N(E35)-N(F35))/5+1)),"?")) | I35: =IF(OR(A35="",$O$3=""),"",IF(OR(ISNUMBER(SEARCH("|"&A35&"|",IFERROR(INDEX(Data_Careers!$J:$J,MATCH($O$3&"|"&$B$4,Data_Careers!$A:$A,0)),""))),ISNUMBER(SEARCH("|"&TRIM(IFERROR(LEFT(A35,FIND("(",A35)-1),A35))&" (any)|",IFERROR(INDEX(Data_Careers!$J:$J,MATCH($O$3&"|"&$B$4,Data_Careers!$A:$A,0)),"")))),"★","")) | R35: =IF(M35="","",IF(Q35="Yes",100*U35,0)) | S35: =IF(OR(M35="",$O$3=""),"",IF(OR(ISNUMBER(SEARCH("|"&M35&"|",IFERROR(INDEX(Data_Careers!$K:$K,MATCH($O$3&"|"&$B$4,Data_Careers!$A:$A,0)),""))),ISNUMBER(SEARCH("|"&TRIM(IFERROR(LEFT(M35,FIND("(",M35)-1),M35))&" (any)|",IFERROR(INDEX(Data_Careers!$K:$K,MATCH($O$3&"|"&$B$4,Data_Careers!$A:$A,0)),"")))),"★","")) | T35: =IF(M35="","",IFERROR(IFERROR(INDEX(Data_Talents!$D:$D,MATCH(M35,Data_Talents!$A:$A,0))&"",INDEX(Data_Talents!$D:$D,MATCH(TRIM(IFERROR(LEFT(M35,FIND("(",M35)-1),M35)),Data_Talents!$B:$B,0))&""),"")) | U35: =IF(M35="",0,IF(N(P35)=0,1,N(P35)))
A36: Drive | B36: =IF(A36="","",IFERROR(IFERROR(INDEX(Data_Skills!$C:$C,MATCH(A36,Data_Skills!$A:$A,0))&"",INDEX(Data_Skills!$C:$C,MATCH(TRIM(IFERROR(LEFT(A36,FIND("(",A36)-1),A36)),Data_Skills!$B:$B,0))&""),"")) | C36: =IF(B36="","",INDEX($B$16:$K$16,MATCH(B36,$B$10:$K$10,0))) | D36: 0 | E36: 0 | F36: 0 | G36: =IF(OR(A36="",C36=""),"",C36+N(E36)) | H36: =IF(A36="","",IFERROR(MAX(0,2*INDEX(Data_Lists!$AG$2:$AG$17,N(E36)/5+1)-INDEX(Data_Lists!$AG$2:$AG$17,N(D36)/5+1)-INDEX(Data_Lists!$AG$2:$AG$17,(N(E36)-N(F36))/5+1)),"?")) | I36: =IF(OR(A36="",$O$3=""),"",IF(OR(ISNUMBER(SEARCH("|"&A36&"|",IFERROR(INDEX(Data_Careers!$J:$J,MATCH($O$3&"|"&$B$4,Data_Careers!$A:$A,0)),""))),ISNUMBER(SEARCH("|"&TRIM(IFERROR(LEFT(A36,FIND("(",A36)-1),A36))&" (any)|",IFERROR(INDEX(Data_Careers!$J:$J,MATCH($O$3&"|"&$B$4,Data_Careers!$A:$A,0)),"")))),"★","")) | R36: =IF(M36="","",IF(Q36="Yes",100*U36,0)) | S36: =IF(OR(M36="",$O$3=""),"",IF(OR(ISNUMBER(SEARCH("|"&M36&"|",IFERROR(INDEX(Data_Careers!$K:$K,MATCH($O$3&"|"&$B$4,Data_Careers!$A:$A,0)),""))),ISNUMBER(SEARCH("|"&TRIM(IFERROR(LEFT(M36,FIND("(",M36)-1),M36))&" (any)|",IFERROR(INDEX(Data_Careers!$K:$K,MATCH($O$3&"|"&$B$4,Data_Careers!$A:$A,0)),"")))),"★","")) | T36: =IF(M36="","",IFERROR(IFERROR(INDEX(Data_Talents!$D:$D,MATCH(M36,Data_Talents!$A:$A,0))&"",INDEX(Data_Talents!$D:$D,MATCH(TRIM(IFERROR(LEFT(M36,FIND("(",M36)-1),M36)),Data_Talents!$B:$B,0))&""),"")) | U36: =IF(M36="",0,IF(N(P36)=0,1,N(P36)))
A37: Endurance | B37: =IF(A37="","",IFERROR(IFERROR(INDEX(Data_Skills!$C:$C,MATCH(A37,Data_Skills!$A:$A,0))&"",INDEX(Data_Skills!$C:$C,MATCH(TRIM(IFERROR(LEFT(A37,FIND("(",A37)-1),A37)),Data_Skills!$B:$B,0))&""),"")) | C37: =IF(B37="","",INDEX($B$16:$K$16,MATCH(B37,$B$10:$K$10,0))) | D37: 0 | E37: 0 | F37: 0 | G37: =IF(OR(A37="",C37=""),"",C37+N(E37)) | H37: =IF(A37="","",IFERROR(MAX(0,2*INDEX(Data_Lists!$AG$2:$AG$17,N(E37)/5+1)-INDEX(Data_Lists!$AG$2:$AG$17,N(D37)/5+1)-INDEX(Data_Lists!$AG$2:$AG$17,(N(E37)-N(F37))/5+1)),"?")) | I37: =IF(OR(A37="",$O$3=""),"",IF(OR(ISNUMBER(SEARCH("|"&A37&"|",IFERROR(INDEX(Data_Careers!$J:$J,MATCH($O$3&"|"&$B$4,Data_Careers!$A:$A,0)),""))),ISNUMBER(SEARCH("|"&TRIM(IFERROR(LEFT(A37,FIND("(",A37)-1),A37))&" (any)|",IFERROR(INDEX(Data_Careers!$J:$J,MATCH($O$3&"|"&$B$4,Data_Careers!$A:$A,0)),"")))),"★","")) | R37: =IF(M37="","",IF(Q37="Yes",100*U37,0)) | S37: =IF(OR(M37="",$O$3=""),"",IF(OR(ISNUMBER(SEARCH("|"&M37&"|",IFERROR(INDEX(Data_Careers!$K:$K,MATCH($O$3&"|"&$B$4,Data_Careers!$A:$A,0)),""))),ISNUMBER(SEARCH("|"&TRIM(IFERROR(LEFT(M37,FIND("(",M37)-1),M37))&" (any)|",IFERROR(INDEX(Data_Careers!$K:$K,MATCH($O$3&"|"&$B$4,Data_Careers!$A:$A,0)),"")))),"★","")) | T37: =IF(M37="","",IFERROR(IFERROR(INDEX(Data_Talents!$D:$D,MATCH(M37,Data_Talents!$A:$A,0))&"",INDEX(Data_Talents!$D:$D,MATCH(TRIM(IFERROR(LEFT(M37,FIND("(",M37)-1),M37)),Data_Talents!$B:$B,0))&""),"")) | U37: =IF(M37="",0,IF(N(P37)=0,1,N(P37)))
A38: Entertain | B38: =IF(A38="","",IFERROR(IFERROR(INDEX(Data_Skills!$C:$C,MATCH(A38,Data_Skills!$A:$A,0))&"",INDEX(Data_Skills!$C:$C,MATCH(TRIM(IFERROR(LEFT(A38,FIND("(",A38)-1),A38)),Data_Skills!$B:$B,0))&""),"")) | C38: =IF(B38="","",INDEX($B$16:$K$16,MATCH(B38,$B$10:$K$10,0))) | D38: 0 | E38: 0 | F38: 0 | G38: =IF(OR(A38="",C38=""),"",C38+N(E38)) | H38: =IF(A38="","",IFERROR(MAX(0,2*INDEX(Data_Lists!$AG$2:$AG$17,N(E38)/5+1)-INDEX(Data_Lists!$AG$2:$AG$17,N(D38)/5+1)-INDEX(Data_Lists!$AG$2:$AG$17,(N(E38)-N(F38))/5+1)),"?")) | I38: =IF(OR(A38="",$O$3=""),"",IF(OR(ISNUMBER(SEARCH("|"&A38&"|",IFERROR(INDEX(Data_Careers!$J:$J,MATCH($O$3&"|"&$B$4,Data_Careers!$A:$A,0)),""))),ISNUMBER(SEARCH("|"&TRIM(IFERROR(LEFT(A38,FIND("(",A38)-1),A38))&" (any)|",IFERROR(INDEX(Data_Careers!$J:$J,MATCH($O$3&"|"&$B$4,Data_Careers!$A:$A,0)),"")))),"★","")) | R38: =IF(M38="","",IF(Q38="Yes",100*U38,0)) | S38: =IF(OR(M38="",$O$3=""),"",IF(OR(ISNUMBER(SEARCH("|"&M38&"|",IFERROR(INDEX(Data_Careers!$K:$K,MATCH($O$3&"|"&$B$4,Data_Careers!$A:$A,0)),""))),ISNUMBER(SEARCH("|"&TRIM(IFERROR(LEFT(M38,FIND("(",M38)-1),M38))&" (any)|",IFERROR(INDEX(Data_Careers!$K:$K,MATCH($O$3&"|"&$B$4,Data_Careers!$A:$A,0)),"")))),"★","")) | T38: =IF(M38="","",IFERROR(IFERROR(INDEX(Data_Talents!$D:$D,MATCH(M38,Data_Talents!$A:$A,0))&"",INDEX(Data_Talents!$D:$D,MATCH(TRIM(IFERROR(LEFT(M38,FIND("(",M38)-1),M38)),Data_Talents!$B:$B,0))&""),"")) | U38: =IF(M38="",0,IF(N(P38)=0,1,N(P38)))
... A52: Stealth | B52: =IF(A52="","",IFERROR(IFERROR(INDEX(Data_Skills!$C:$C,MATCH(A52,Data_Skills!$A:$A,0))&"",INDEX(Data_Skills!$C:$C,MATCH(TRIM(IFERROR(LEFT(A52,FIND("(",A52)-1),A52)),Data_Skills!$B:$B,0))&""),"")) | C52: =IF(B52="","",INDEX($B$16:$K$16,MATCH(B52,$B$10:$K$10,0))) | D52: 0 | E52: 0 | F52: 0 | G52: =IF(OR(A52="",C52=""),"",C52+N(E52)) | H52: =IF(A52="","",IFERROR(MAX(0,2*INDEX(Data_Lists!$AG$2:$AG$17,N(E52)/5+1)-INDEX(Data_Lists!$AG$2:$AG$17,N(D52)/5+1)-INDEX(Data_Lists!$AG$2:$AG$17,(N(E52)-N(F52))/5+1)),"?")) | I52: =IF(OR(A52="",$O$3=""),"",IF(OR(ISNUMBER(SEARCH("|"&A52&"|",IFERROR(INDEX(Data_Careers!$J:$J,MATCH($O$3&"|"&$B$4,Data_Careers!$A:$A,0)),""))),ISNUMBER(SEARCH("|"&TRIM(IFERROR(LEFT(A52,FIND("(",A52)-1),A52))&" (any)|",IFERROR(INDEX(Data_Careers!$J:$J,MATCH($O$3&"|"&$B$4,Data_Careers!$A:$A,0)),"")))),"★","")) | R52: =IF(M52="","",IF(Q52="Yes",100*U52,0)) | S52: =IF(OR(M52="",$O$3=""),"",IF(OR(ISNUMBER(SEARCH("|"&M52&"|",IFERROR(INDEX(Data_Careers!$K:$K,MATCH($O$3&"|"&$B$4,Data_Careers!$A:$A,0)),""))),ISNUMBER(SEARCH("|"&TRIM(IFERROR(LEFT(M52,FIND("(",M52)-1),M52))&" (any)|",IFERROR(INDEX(Data_Careers!$K:$K,MATCH($O$3&"|"&$B$4,Data_Careers!$A:$A,0)),"")))),"★","")) | T52: =IF(M52="","",IFERROR(IFERROR(INDEX(Data_Talents!$D:$D,MATCH(M52,Data_Talents!$A:$A,0))&"",INDEX(Data_Talents!$D:$D,MATCH(TRIM(IFERROR(LEFT(M52,FIND("(",M52)-1),M52)),Data_Talents!$B:$B,0))&""),"")) | U52: =IF(M52="",0,IF(N(P52)=0,1,N(P52)))
A53: Advanced & grouped skills — pick from the list (e.g. Language (Reikspiel), Lore (Law)) | R53: =IF(M53="","",IF(Q53="Yes",100*U53,0)) | S53: =IF(OR(M53="",$O$3=""),"",IF(OR(ISNUMBER(SEARCH("|"&M53&"|",IFERROR(INDEX(Data_Careers!$K:$K,MATCH($O$3&"|"&$B$4,Data_Careers!$A:$A,0)),""))),ISNUMBER(SEARCH("|"&TRIM(IFERROR(LEFT(M53,FIND("(",M53)-1),M53))&" (any)|",IFERROR(INDEX(Data_Careers!$K:$K,MATCH($O$3&"|"&$B$4,Data_Careers!$A:$A,0)),"")))),"★","")) | T53: =IF(M53="","",IFERROR(IFERROR(INDEX(Data_Talents!$D:$D,MATCH(M53,Data_Talents!$A:$A,0))&"",INDEX(Data_Talents!$D:$D,MATCH(TRIM(IFERROR(LEFT(M53,FIND("(",M53)-1),M53)),Data_Talents!$B:$B,0))&""),"")) | U53: =IF(M53="",0,IF(N(P53)=0,1,N(P53)))
B54: =IF(A54="","",IFERROR(IFERROR(INDEX(Data_Skills!$C:$C,MATCH(A54,Data_Skills!$A:$A,0))&"",INDEX(Data_Skills!$C:$C,MATCH(TRIM(IFERROR(LEFT(A54,FIND("(",A54)-1),A54)),Data_Skills!$B:$B,0))&""),"")) | C54: =IF(B54="","",INDEX($B$16:$K$16,MATCH(B54,$B$10:$K$10,0))) | G54: =IF(OR(A54="",C54=""),"",C54+N(E54)) | H54: =IF(A54="","",IFERROR(MAX(0,2*INDEX(Data_Lists!$AG$2:$AG$17,N(E54)/5+1)-INDEX(Data_Lists!$AG$2:$AG$17,N(D54)/5+1)-INDEX(Data_Lists!$AG$2:$AG$17,(N(E54)-N(F54))/5+1)),"?")) | I54: =IF(OR(A54="",$O$3=""),"",IF(OR(ISNUMBER(SEARCH("|"&A54&"|",IFERROR(INDEX(Data_Careers!$J:$J,MATCH($O$3&"|"&$B$4,Data_Careers!$A:$A,0)),""))),ISNUMBER(SEARCH("|"&TRIM(IFERROR(LEFT(A54,FIND("(",A54)-1),A54))&" (any)|",IFERROR(INDEX(Data_Careers!$J:$J,MATCH($O$3&"|"&$B$4,Data_Careers!$A:$A,0)),"")))),"★","")) | R54: =IF(M54="","",IF(Q54="Yes",100*U54,0)) | S54: =IF(OR(M54="",$O$3=""),"",IF(OR(ISNUMBER(SEARCH("|"&M54&"|",IFERROR(INDEX(Data_Careers!$K:$K,MATCH($O$3&"|"&$B$4,Data_Careers!$A:$A,0)),""))),ISNUMBER(SEARCH("|"&TRIM(IFERROR(LEFT(M54,FIND("(",M54)-1),M54))&" (any)|",IFERROR(INDEX(Data_Careers!$K:$K,MATCH($O$3&"|"&$B$4,Data_Careers!$A:$A,0)),"")))),"★","")) | T54: =IF(M54="","",IFERROR(IFERROR(INDEX(Data_Talents!$D:$D,MATCH(M54,Data_Talents!$A:$A,0))&"",INDEX(Data_Talents!$D:$D,MATCH(TRIM(IFERROR(LEFT(M54,FIND("(",M54)-1),M54)),Data_Talents!$B:$B,0))&""),"")) | U54: =IF(M54="",0,IF(N(P54)=0,1,N(P54)))
B55: =IF(A55="","",IFERROR(IFERROR(INDEX(Data_Skills!$C:$C,MATCH(A55,Data_Skills!$A:$A,0))&"",INDEX(Data_Skills!$C:$C,MATCH(TRIM(IFERROR(LEFT(A55,FIND("(",A55)-1),A55)),Data_Skills!$B:$B,0))&""),"")) | C55: =IF(B55="","",INDEX($B$16:$K$16,MATCH(B55,$B$10:$K$10,0))) | G55: =IF(OR(A55="",C55=""),"",C55+N(E55)) | H55: =IF(A55="","",IFERROR(MAX(0,2*INDEX(Data_Lists!$AG$2:$AG$17,N(E55)/5+1)-INDEX(Data_Lists!$AG$2:$AG$17,N(D55)/5+1)-INDEX(Data_Lists!$AG$2:$AG$17,(N(E55)-N(F55))/5+1)),"?")) | I55: =IF(OR(A55="",$O$3=""),"",IF(OR(ISNUMBER(SEARCH("|"&A55&"|",IFERROR(INDEX(Data_Careers!$J:$J,MATCH($O$3&"|"&$B$4,Data_Careers!$A:$A,0)),""))),ISNUMBER(SEARCH("|"&TRIM(IFERROR(LEFT(A55,FIND("(",A55)-1),A55))&" (any)|",IFERROR(INDEX(Data_Careers!$J:$J,MATCH($O$3&"|"&$B$4,Data_Careers!$A:$A,0)),"")))),"★","")) | R55: =IF(M55="","",IF(Q55="Yes",100*U55,0)) | S55: =IF(OR(M55="",$O$3=""),"",IF(OR(ISNUMBER(SEARCH("|"&M55&"|",IFERROR(INDEX(Data_Careers!$K:$K,MATCH($O$3&"|"&$B$4,Data_Careers!$A:$A,0)),""))),ISNUMBER(SEARCH("|"&TRIM(IFERROR(LEFT(M55,FIND("(",M55)-1),M55))&" (any)|",IFERROR(INDEX(Data_Careers!$K:$K,MATCH($O$3&"|"&$B$4,Data_Careers!$A:$A,0)),"")))),"★","")) | T55: =IF(M55="","",IFERROR(IFERROR(INDEX(Data_Talents!$D:$D,MATCH(M55,Data_Talents!$A:$A,0))&"",INDEX(Data_Talents!$D:$D,MATCH(TRIM(IFERROR(LEFT(M55,FIND("(",M55)-1),M55)),Data_Talents!$B:$B,0))&""),"")) | U55: =IF(M55="",0,IF(N(P55)=0,1,N(P55)))
B56: =IF(A56="","",IFERROR(IFERROR(INDEX(Data_Skills!$C:$C,MATCH(A56,Data_Skills!$A:$A,0))&"",INDEX(Data_Skills!$C:$C,MATCH(TRIM(IFERROR(LEFT(A56,FIND("(",A56)-1),A56)),Data_Skills!$B:$B,0))&""),"")) | C56: =IF(B56="","",INDEX($B$16:$K$16,MATCH(B56,$B$10:$K$10,0))) | G56: =IF(OR(A56="",C56=""),"",C56+N(E56)) | H56: =IF(A56="","",IFERROR(MAX(0,2*INDEX(Data_Lists!$AG$2:$AG$17,N(E56)/5+1)-INDEX(Data_Lists!$AG$2:$AG$17,N(D56)/5+1)-INDEX(Data_Lists!$AG$2:$AG$17,(N(E56)-N(F56))/5+1)),"?")) | I56: =IF(OR(A56="",$O$3=""),"",IF(OR(ISNUMBER(SEARCH("|"&A56&"|",IFERROR(INDEX(Data_Careers!$J:$J,MATCH($O$3&"|"&$B$4,Data_Careers!$A:$A,0)),""))),ISNUMBER(SEARCH("|"&TRIM(IFERROR(LEFT(A56,FIND("(",A56)-1),A56))&" (any)|",IFERROR(INDEX(Data_Careers!$J:$J,MATCH($O$3&"|"&$B$4,Data_Careers!$A:$A,0)),"")))),"★","")) | R56: =IF(M56="","",IF(Q56="Yes",100*U56,0)) | S56: =IF(OR(M56="",$O$3=""),"",IF(OR(ISNUMBER(SEARCH("|"&M56&"|",IFERROR(INDEX(Data_Careers!$K:$K,MATCH($O$3&"|"&$B$4,Data_Careers!$A:$A,0)),""))),ISNUMBER(SEARCH("|"&TRIM(IFERROR(LEFT(M56,FIND("(",M56)-1),M56))&" (any)|",IFERROR(INDEX(Data_Careers!$K:$K,MATCH($O$3&"|"&$B$4,Data_Careers!$A:$A,0)),"")))),"★","")) | T56: =IF(M56="","",IFERROR(IFERROR(INDEX(Data_Talents!$D:$D,MATCH(M56,Data_Talents!$A:$A,0))&"",INDEX(Data_Talents!$D:$D,MATCH(TRIM(IFERROR(LEFT(M56,FIND("(",M56)-1),M56)),Data_Talents!$B:$B,0))&""),"")) | U56: =IF(M56="",0,IF(N(P56)=0,1,N(P56)))
B57: =IF(A57="","",IFERROR(IFERROR(INDEX(Data_Skills!$C:$C,MATCH(A57,Data_Skills!$A:$A,0))&"",INDEX(Data_Skills!$C:$C,MATCH(TRIM(IFERROR(LEFT(A57,FIND("(",A57)-1),A57)),Data_Skills!$B:$B,0))&""),"")) | C57: =IF(B57="","",INDEX($B$16:$K$16,MATCH(B57,$B$10:$K$10,0))) | G57: =IF(OR(A57="",C57=""),"",C57+N(E57)) | H57: =IF(A57="","",IFERROR(MAX(0,2*INDEX(Data_Lists!$AG$2:$AG$17,N(E57)/5+1)-INDEX(Data_Lists!$AG$2:$AG$17,N(D57)/5+1)-INDEX(Data_Lists!$AG$2:$AG$17,(N(E57)-N(F57))/5+1)),"?")) | I57: =IF(OR(A57="",$O$3=""),"",IF(OR(ISNUMBER(SEARCH("|"&A57&"|",IFERROR(INDEX(Data_Careers!$J:$J,MATCH($O$3&"|"&$B$4,Data_Careers!$A:$A,0)),""))),ISNUMBER(SEARCH("|"&TRIM(IFERROR(LEFT(A57,FIND("(",A57)-1),A57))&" (any)|",IFERROR(INDEX(Data_Careers!$J:$J,MATCH($O$3&"|"&$B$4,Data_Careers!$A:$A,0)),"")))),"★","")) | R57: =IF(M57="","",IF(Q57="Yes",100*U57,0)) | S57: =IF(OR(M57="",$O$3=""),"",IF(OR(ISNUMBER(SEARCH("|"&M57&"|",IFERROR(INDEX(Data_Careers!$K:$K,MATCH($O$3&"|"&$B$4,Data_Careers!$A:$A,0)),""))),ISNUMBER(SEARCH("|"&TRIM(IFERROR(LEFT(M57,FIND("(",M57)-1),M57))&" (any)|",IFERROR(INDEX(Data_Careers!$K:$K,MATCH($O$3&"|"&$B$4,Data_Careers!$A:$A,0)),"")))),"★","")) | T57: =IF(M57="","",IFERROR(IFERROR(INDEX(Data_Talents!$D:$D,MATCH(M57,Data_Talents!$A:$A,0))&"",INDEX(Data_Talents!$D:$D,MATCH(TRIM(IFERROR(LEFT(M57,FIND("(",M57)-1),M57)),Data_Talents!$B:$B,0))&""),"")) | U57: =IF(M57="",0,IF(N(P57)=0,1,N(P57)))
B58: =IF(A58="","",IFERROR(IFERROR(INDEX(Data_Skills!$C:$C,MATCH(A58,Data_Skills!$A:$A,0))&"",INDEX(Data_Skills!$C:$C,MATCH(TRIM(IFERROR(LEFT(A58,FIND("(",A58)-1),A58)),Data_Skills!$B:$B,0))&""),"")) | C58: =IF(B58="","",INDEX($B$16:$K$16,MATCH(B58,$B$10:$K$10,0))) | G58: =IF(OR(A58="",C58=""),"",C58+N(E58)) | H58: =IF(A58="","",IFERROR(MAX(0,2*INDEX(Data_Lists!$AG$2:$AG$17,N(E58)/5+1)-INDEX(Data_Lists!$AG$2:$AG$17,N(D58)/5+1)-INDEX(Data_Lists!$AG$2:$AG$17,(N(E58)-N(F58))/5+1)),"?")) | I58: =IF(OR(A58="",$O$3=""),"",IF(OR(ISNUMBER(SEARCH("|"&A58&"|",IFERROR(INDEX(Data_Careers!$J:$J,MATCH($O$3&"|"&$B$4,Data_Careers!$A:$A,0)),""))),ISNUMBER(SEARCH("|"&TRIM(IFERROR(LEFT(A58,FIND("(",A58)-1),A58))&" (any)|",IFERROR(INDEX(Data_Careers!$J:$J,MATCH($O$3&"|"&$B$4,Data_Careers!$A:$A,0)),"")))),"★","")) | R58: =IF(M58="","",IF(Q58="Yes",100*U58,0)) | S58: =IF(OR(M58="",$O$3=""),"",IF(OR(ISNUMBER(SEARCH("|"&M58&"|",IFERROR(INDEX(Data_Careers!$K:$K,MATCH($O$3&"|"&$B$4,Data_Careers!$A:$A,0)),""))),ISNUMBER(SEARCH("|"&TRIM(IFERROR(LEFT(M58,FIND("(",M58)-1),M58))&" (any)|",IFERROR(INDEX(Data_Careers!$K:$K,MATCH($O$3&"|"&$B$4,Data_Careers!$A:$A,0)),"")))),"★","")) | T58: =IF(M58="","",IFERROR(IFERROR(INDEX(Data_Talents!$D:$D,MATCH(M58,Data_Talents!$A:$A,0))&"",INDEX(Data_Talents!$D:$D,MATCH(TRIM(IFERROR(LEFT(M58,FIND("(",M58)-1),M58)),Data_Talents!$B:$B,0))&""),"")) | U58: =IF(M58="",0,IF(N(P58)=0,1,N(P58)))
B59: =IF(A59="","",IFERROR(IFERROR(INDEX(Data_Skills!$C:$C,MATCH(A59,Data_Skills!$A:$A,0))&"",INDEX(Data_Skills!$C:$C,MATCH(TRIM(IFERROR(LEFT(A59,FIND("(",A59)-1),A59)),Data_Skills!$B:$B,0))&""),"")) | C59: =IF(B59="","",INDEX($B$16:$K$16,MATCH(B59,$B$10:$K$10,0))) | G59: =IF(OR(A59="",C59=""),"",C59+N(E59)) | H59: =IF(A59="","",IFERROR(MAX(0,2*INDEX(Data_Lists!$AG$2:$AG$17,N(E59)/5+1)-INDEX(Data_Lists!$AG$2:$AG$17,N(D59)/5+1)-INDEX(Data_Lists!$AG$2:$AG$17,(N(E59)-N(F59))/5+1)),"?")) | I59: =IF(OR(A59="",$O$3=""),"",IF(OR(ISNUMBER(SEARCH("|"&A59&"|",IFERROR(INDEX(Data_Careers!$J:$J,MATCH($O$3&"|"&$B$4,Data_Careers!$A:$A,0)),""))),ISNUMBER(SEARCH("|"&TRIM(IFERROR(LEFT(A59,FIND("(",A59)-1),A59))&" (any)|",IFERROR(INDEX(Data_Careers!$J:$J,MATCH($O$3&"|"&$B$4,Data_Careers!$A:$A,0)),"")))),"★","")) | R59: =IF(M59="","",IF(Q59="Yes",100*U59,0)) | S59: =IF(OR(M59="",$O$3=""),"",IF(OR(ISNUMBER(SEARCH("|"&M59&"|",IFERROR(INDEX(Data_Careers!$K:$K,MATCH($O$3&"|"&$B$4,Data_Careers!$A:$A,0)),""))),ISNUMBER(SEARCH("|"&TRIM(IFERROR(LEFT(M59,FIND("(",M59)-1),M59))&" (any)|",IFERROR(INDEX(Data_Careers!$K:$K,MATCH($O$3&"|"&$B$4,Data_Careers!$A:$A,0)),"")))),"★","")) | T59: =IF(M59="","",IFERROR(IFERROR(INDEX(Data_Talents!$D:$D,MATCH(M59,Data_Talents!$A:$A,0))&"",INDEX(Data_Talents!$D:$D,MATCH(TRIM(IFERROR(LEFT(M59,FIND("(",M59)-1),M59)),Data_Talents!$B:$B,0))&""),"")) | U59: =IF(M59="",0,IF(N(P59)=0,1,N(P59)))
B60: =IF(A60="","",IFERROR(IFERROR(INDEX(Data_Skills!$C:$C,MATCH(A60,Data_Skills!$A:$A,0))&"",INDEX(Data_Skills!$C:$C,MATCH(TRIM(IFERROR(LEFT(A60,FIND("(",A60)-1),A60)),Data_Skills!$B:$B,0))&""),"")) | C60: =IF(B60="","",INDEX($B$16:$K$16,MATCH(B60,$B$10:$K$10,0))) | G60: =IF(OR(A60="",C60=""),"",C60+N(E60)) | H60: =IF(A60="","",IFERROR(MAX(0,2*INDEX(Data_Lists!$AG$2:$AG$17,N(E60)/5+1)-INDEX(Data_Lists!$AG$2:$AG$17,N(D60)/5+1)-INDEX(Data_Lists!$AG$2:$AG$17,(N(E60)-N(F60))/5+1)),"?")) | I60: =IF(OR(A60="",$O$3=""),"",IF(OR(ISNUMBER(SEARCH("|"&A60&"|",IFERROR(INDEX(Data_Careers!$J:$J,MATCH($O$3&"|"&$B$4,Data_Careers!$A:$A,0)),""))),ISNUMBER(SEARCH("|"&TRIM(IFERROR(LEFT(A60,FIND("(",A60)-1),A60))&" (any)|",IFERROR(INDEX(Data_Careers!$J:$J,MATCH($O$3&"|"&$B$4,Data_Careers!$A:$A,0)),"")))),"★","")) | R60: =IF(M60="","",IF(Q60="Yes",100*U60,0)) | S60: =IF(OR(M60="",$O$3=""),"",IF(OR(ISNUMBER(SEARCH("|"&M60&"|",IFERROR(INDEX(Data_Careers!$K:$K,MATCH($O$3&"|"&$B$4,Data_Careers!$A:$A,0)),""))),ISNUMBER(SEARCH("|"&TRIM(IFERROR(LEFT(M60,FIND("(",M60)-1),M60))&" (any)|",IFERROR(INDEX(Data_Careers!$K:$K,MATCH($O$3&"|"&$B$4,Data_Careers!$A:$A,0)),"")))),"★","")) | T60: =IF(M60="","",IFERROR(IFERROR(INDEX(Data_Talents!$D:$D,MATCH(M60,Data_Talents!$A:$A,0))&"",INDEX(Data_Talents!$D:$D,MATCH(TRIM(IFERROR(LEFT(M60,FIND("(",M60)-1),M60)),Data_Talents!$B:$B,0))&""),"")) | U60: =IF(M60="",0,IF(N(P60)=0,1,N(P60)))
B61: =IF(A61="","",IFERROR(IFERROR(INDEX(Data_Skills!$C:$C,MATCH(A61,Data_Skills!$A:$A,0))&"",INDEX(Data_Skills!$C:$C,MATCH(TRIM(IFERROR(LEFT(A61,FIND("(",A61)-1),A61)),Data_Skills!$B:$B,0))&""),"")) | C61: =IF(B61="","",INDEX($B$16:$K$16,MATCH(B61,$B$10:$K$10,0))) | G61: =IF(OR(A61="",C61=""),"",C61+N(E61)) | H61: =IF(A61="","",IFERROR(MAX(0,2*INDEX(Data_Lists!$AG$2:$AG$17,N(E61)/5+1)-INDEX(Data_Lists!$AG$2:$AG$17,N(D61)/5+1)-INDEX(Data_Lists!$AG$2:$AG$17,(N(E61)-N(F61))/5+1)),"?")) | I61: =IF(OR(A61="",$O$3=""),"",IF(OR(ISNUMBER(SEARCH("|"&A61&"|",IFERROR(INDEX(Data_Careers!$J:$J,MATCH($O$3&"|"&$B$4,Data_Careers!$A:$A,0)),""))),ISNUMBER(SEARCH("|"&TRIM(IFERROR(LEFT(A61,FIND("(",A61)-1),A61))&" (any)|",IFERROR(INDEX(Data_Careers!$J:$J,MATCH($O$3&"|"&$B$4,Data_Careers!$A:$A,0)),"")))),"★","")) | R61: =IF(M61="","",IF(Q61="Yes",100*U61,0)) | S61: =IF(OR(M61="",$O$3=""),"",IF(OR(ISNUMBER(SEARCH("|"&M61&"|",IFERROR(INDEX(Data_Careers!$K:$K,MATCH($O$3&"|"&$B$4,Data_Careers!$A:$A,0)),""))),ISNUMBER(SEARCH("|"&TRIM(IFERROR(LEFT(M61,FIND("(",M61)-1),M61))&" (any)|",IFERROR(INDEX(Data_Careers!$K:$K,MATCH($O$3&"|"&$B$4,Data_Careers!$A:$A,0)),"")))),"★","")) | T61: =IF(M61="","",IFERROR(IFERROR(INDEX(Data_Talents!$D:$D,MATCH(M61,Data_Talents!$A:$A,0))&"",INDEX(Data_Talents!$D:$D,MATCH(TRIM(IFERROR(LEFT(M61,FIND("(",M61)-1),M61)),Data_Talents!$B:$B,0))&""),"")) | U61: =IF(M61="",0,IF(N(P61)=0,1,N(P61)))
B62: =IF(A62="","",IFERROR(IFERROR(INDEX(Data_Skills!$C:$C,MATCH(A62,Data_Skills!$A:$A,0))&"",INDEX(Data_Skills!$C:$C,MATCH(TRIM(IFERROR(LEFT(A62,FIND("(",A62)-1),A62)),Data_Skills!$B:$B,0))&""),"")) | C62: =IF(B62="","",INDEX($B$16:$K$16,MATCH(B62,$B$10:$K$10,0))) | G62: =IF(OR(A62="",C62=""),"",C62+N(E62)) | H62: =IF(A62="","",IFERROR(MAX(0,2*INDEX(Data_Lists!$AG$2:$AG$17,N(E62)/5+1)-INDEX(Data_Lists!$AG$2:$AG$17,N(D62)/5+1)-INDEX(Data_Lists!$AG$2:$AG$17,(N(E62)-N(F62))/5+1)),"?")) | I62: =IF(OR(A62="",$O$3=""),"",IF(OR(ISNUMBER(SEARCH("|"&A62&"|",IFERROR(INDEX(Data_Careers!$J:$J,MATCH($O$3&"|"&$B$4,Data_Careers!$A:$A,0)),""))),ISNUMBER(SEARCH("|"&TRIM(IFERROR(LEFT(A62,FIND("(",A62)-1),A62))&" (any)|",IFERROR(INDEX(Data_Careers!$J:$J,MATCH($O$3&"|"&$B$4,Data_Careers!$A:$A,0)),"")))),"★","")) | R62: =IF(M62="","",IF(Q62="Yes",100*U62,0)) | S62: =IF(OR(M62="",$O$3=""),"",IF(OR(ISNUMBER(SEARCH("|"&M62&"|",IFERROR(INDEX(Data_Careers!$K:$K,MATCH($O$3&"|"&$B$4,Data_Careers!$A:$A,0)),""))),ISNUMBER(SEARCH("|"&TRIM(IFERROR(LEFT(M62,FIND("(",M62)-1),M62))&" (any)|",IFERROR(INDEX(Data_Careers!$K:$K,MATCH($O$3&"|"&$B$4,Data_Careers!$A:$A,0)),"")))),"★","")) | T62: =IF(M62="","",IFERROR(IFERROR(INDEX(Data_Talents!$D:$D,MATCH(M62,Data_Talents!$A:$A,0))&"",INDEX(Data_Talents!$D:$D,MATCH(TRIM(IFERROR(LEFT(M62,FIND("(",M62)-1),M62)),Data_Talents!$B:$B,0))&""),"")) | U62: =IF(M62="",0,IF(N(P62)=0,1,N(P62)))
B63: =IF(A63="","",IFERROR(IFERROR(INDEX(Data_Skills!$C:$C,MATCH(A63,Data_Skills!$A:$A,0))&"",INDEX(Data_Skills!$C:$C,MATCH(TRIM(IFERROR(LEFT(A63,FIND("(",A63)-1),A63)),Data_Skills!$B:$B,0))&""),"")) | C63: =IF(B63="","",INDEX($B$16:$K$16,MATCH(B63,$B$10:$K$10,0))) | G63: =IF(OR(A63="",C63=""),"",C63+N(E63)) | H63: =IF(A63="","",IFERROR(MAX(0,2*INDEX(Data_Lists!$AG$2:$AG$17,N(E63)/5+1)-INDEX(Data_Lists!$AG$2:$AG$17,N(D63)/5+1)-INDEX(Data_Lists!$AG$2:$AG$17,(N(E63)-N(F63))/5+1)),"?")) | I63: =IF(OR(A63="",$O$3=""),"",IF(OR(ISNUMBER(SEARCH("|"&A63&"|",IFERROR(INDEX(Data_Careers!$J:$J,MATCH($O$3&"|"&$B$4,Data_Careers!$A:$A,0)),""))),ISNUMBER(SEARCH("|"&TRIM(IFERROR(LEFT(A63,FIND("(",A63)-1),A63))&" (any)|",IFERROR(INDEX(Data_Careers!$J:$J,MATCH($O$3&"|"&$B$4,Data_Careers!$A:$A,0)),"")))),"★","")) | R63: =IF(M63="","",IF(Q63="Yes",100*U63,0)) | S63: =IF(OR(M63="",$O$3=""),"",IF(OR(ISNUMBER(SEARCH("|"&M63&"|",IFERROR(INDEX(Data_Careers!$K:$K,MATCH($O$3&"|"&$B$4,Data_Careers!$A:$A,0)),""))),ISNUMBER(SEARCH("|"&TRIM(IFERROR(LEFT(M63,FIND("(",M63)-1),M63))&" (any)|",IFERROR(INDEX(Data_Careers!$K:$K,MATCH($O$3&"|"&$B$4,Data_Careers!$A:$A,0)),"")))),"★","")) | T63: =IF(M63="","",IFERROR(IFERROR(INDEX(Data_Talents!$D:$D,MATCH(M63,Data_Talents!$A:$A,0))&"",INDEX(Data_Talents!$D:$D,MATCH(TRIM(IFERROR(LEFT(M63,FIND("(",M63)-1),M63)),Data_Talents!$B:$B,0))&""),"")) | U63: =IF(M63="",0,IF(N(P63)=0,1,N(P63)))
B64: =IF(A64="","",IFERROR(IFERROR(INDEX(Data_Skills!$C:$C,MATCH(A64,Data_Skills!$A:$A,0))&"",INDEX(Data_Skills!$C:$C,MATCH(TRIM(IFERROR(LEFT(A64,FIND("(",A64)-1),A64)),Data_Skills!$B:$B,0))&""),"")) | C64: =IF(B64="","",INDEX($B$16:$K$16,MATCH(B64,$B$10:$K$10,0))) | G64: =IF(OR(A64="",C64=""),"",C64+N(E64)) | H64: =IF(A64="","",IFERROR(MAX(0,2*INDEX(Data_Lists!$AG$2:$AG$17,N(E64)/5+1)-INDEX(Data_Lists!$AG$2:$AG$17,N(D64)/5+1)-INDEX(Data_Lists!$AG$2:$AG$17,(N(E64)-N(F64))/5+1)),"?")) | I64: =IF(OR(A64="",$O$3=""),"",IF(OR(ISNUMBER(SEARCH("|"&A64&"|",IFERROR(INDEX(Data_Careers!$J:$J,MATCH($O$3&"|"&$B$4,Data_Careers!$A:$A,0)),""))),ISNUMBER(SEARCH("|"&TRIM(IFERROR(LEFT(A64,FIND("(",A64)-1),A64))&" (any)|",IFERROR(INDEX(Data_Careers!$J:$J,MATCH($O$3&"|"&$B$4,Data_Careers!$A:$A,0)),"")))),"★","")) | R64: =IF(M64="","",IF(Q64="Yes",100*U64,0)) | S64: =IF(OR(M64="",$O$3=""),"",IF(OR(ISNUMBER(SEARCH("|"&M64&"|",IFERROR(INDEX(Data_Careers!$K:$K,MATCH($O$3&"|"&$B$4,Data_Careers!$A:$A,0)),""))),ISNUMBER(SEARCH("|"&TRIM(IFERROR(LEFT(M64,FIND("(",M64)-1),M64))&" (any)|",IFERROR(INDEX(Data_Careers!$K:$K,MATCH($O$3&"|"&$B$4,Data_Careers!$A:$A,0)),"")))),"★","")) | T64: =IF(M64="","",IFERROR(IFERROR(INDEX(Data_Talents!$D:$D,MATCH(M64,Data_Talents!$A:$A,0))&"",INDEX(Data_Talents!$D:$D,MATCH(TRIM(IFERROR(LEFT(M64,FIND("(",M64)-1),M64)),Data_Talents!$B:$B,0))&""),"")) | U64: =IF(M64="",0,IF(N(P64)=0,1,N(P64)))
B65: =IF(A65="","",IFERROR(IFERROR(INDEX(Data_Skills!$C:$C,MATCH(A65,Data_Skills!$A:$A,0))&"",INDEX(Data_Skills!$C:$C,MATCH(TRIM(IFERROR(LEFT(A65,FIND("(",A65)-1),A65)),Data_Skills!$B:$B,0))&""),"")) | C65: =IF(B65="","",INDEX($B$16:$K$16,MATCH(B65,$B$10:$K$10,0))) | G65: =IF(OR(A65="",C65=""),"",C65+N(E65)) | H65: =IF(A65="","",IFERROR(MAX(0,2*INDEX(Data_Lists!$AG$2:$AG$17,N(E65)/5+1)-INDEX(Data_Lists!$AG$2:$AG$17,N(D65)/5+1)-INDEX(Data_Lists!$AG$2:$AG$17,(N(E65)-N(F65))/5+1)),"?")) | I65: =IF(OR(A65="",$O$3=""),"",IF(OR(ISNUMBER(SEARCH("|"&A65&"|",IFERROR(INDEX(Data_Careers!$J:$J,MATCH($O$3&"|"&$B$4,Data_Careers!$A:$A,0)),""))),ISNUMBER(SEARCH("|"&TRIM(IFERROR(LEFT(A65,FIND("(",A65)-1),A65))&" (any)|",IFERROR(INDEX(Data_Careers!$J:$J,MATCH($O$3&"|"&$B$4,Data_Careers!$A:$A,0)),"")))),"★","")) | R65: =IF(M65="","",IF(Q65="Yes",100*U65,0)) | S65: =IF(OR(M65="",$O$3=""),"",IF(OR(ISNUMBER(SEARCH("|"&M65&"|",IFERROR(INDEX(Data_Careers!$K:$K,MATCH($O$3&"|"&$B$4,Data_Careers!$A:$A,0)),""))),ISNUMBER(SEARCH("|"&TRIM(IFERROR(LEFT(M65,FIND("(",M65)-1),M65))&" (any)|",IFERROR(INDEX(Data_Careers!$K:$K,MATCH($O$3&"|"&$B$4,Data_Careers!$A:$A,0)),"")))),"★","")) | T65: =IF(M65="","",IFERROR(IFERROR(INDEX(Data_Talents!$D:$D,MATCH(M65,Data_Talents!$A:$A,0))&"",INDEX(Data_Talents!$D:$D,MATCH(TRIM(IFERROR(LEFT(M65,FIND("(",M65)-1),M65)),Data_Talents!$B:$B,0))&""),"")) | U65: =IF(M65="",0,IF(N(P65)=0,1,N(P65)))
... B77: =IF(A77="","",IFERROR(IFERROR(INDEX(Data_Skills!$C:$C,MATCH(A77,Data_Skills!$A:$A,0))&"",INDEX(Data_Skills!$C:$C,MATCH(TRIM(IFERROR(LEFT(A77,FIND("(",A77)-1),A77)),Data_Skills!$B:$B,0))&""),"")) | C77: =IF(B77="","",INDEX($B$16:$K$16,MATCH(B77,$B$10:$K$10,0))) | G77: =IF(OR(A77="",C77=""),"",C77+N(E77)) | H77: =IF(A77="","",IFERROR(MAX(0,2*INDEX(Data_Lists!$AG$2:$AG$17,N(E77)/5+1)-INDEX(Data_Lists!$AG$2:$AG$17,N(D77)/5+1)-INDEX(Data_Lists!$AG$2:$AG$17,(N(E77)-N(F77))/5+1)),"?")) | I77: =IF(OR(A77="",$O$3=""),"",IF(OR(ISNUMBER(SEARCH("|"&A77&"|",IFERROR(INDEX(Data_Careers!$J:$J,MATCH($O$3&"|"&$B$4,Data_Careers!$A:$A,0)),""))),ISNUMBER(SEARCH("|"&TRIM(IFERROR(LEFT(A77,FIND("(",A77)-1),A77))&" (any)|",IFERROR(INDEX(Data_Careers!$J:$J,MATCH($O$3&"|"&$B$4,Data_Careers!$A:$A,0)),"")))),"★","")) | R77: =IF(M77="","",IF(Q77="Yes",100*U77,0)) | S77: =IF(OR(M77="",$O$3=""),"",IF(OR(ISNUMBER(SEARCH("|"&M77&"|",IFERROR(INDEX(Data_Careers!$K:$K,MATCH($O$3&"|"&$B$4,Data_Careers!$A:$A,0)),""))),ISNUMBER(SEARCH("|"&TRIM(IFERROR(LEFT(M77,FIND("(",M77)-1),M77))&" (any)|",IFERROR(INDEX(Data_Careers!$K:$K,MATCH($O$3&"|"&$B$4,Data_Careers!$A:$A,0)),"")))),"★","")) | T77: =IF(M77="","",IFERROR(IFERROR(INDEX(Data_Talents!$D:$D,MATCH(M77,Data_Talents!$A:$A,0))&"",INDEX(Data_Talents!$D:$D,MATCH(TRIM(IFERROR(LEFT(M77,FIND("(",M77)-1),M77)),Data_Talents!$B:$B,0))&""),"")) | U77: =IF(M77="",0,IF(N(P77)=0,1,N(P77)))
M78: Times taken: leave blank for 1. Talent bonuses such as Savvy (+5 Int) are added to characteristics automatically.
A79: CAREER PATH (XP for levels and career changes)
A80: Career | B80: Class | D80: Highest level | E80: Entered as | G80: Change XP | H80: Level XP | I80: Total XP | J80: Notes
B81: =IF(A81="","",IFERROR(INDEX(Data_Careers!$D:$D,MATCH(A81&"|1",Data_Careers!$A:$A,0)),"")) | G81: =IF(A81="","",IFERROR(INDEX(Data_Lists!$W$2:$W$4,MATCH(E81,Data_Lists!$V$2:$V$4,0)),0)) | H81: =IF(A81="","",100*MAX(0,N(D81)-1)) | I81: =IF(A81="","",N(G81)+N(H81))
B82: =IF(A82="","",IFERROR(INDEX(Data_Careers!$D:$D,MATCH(A82&"|1",Data_Careers!$A:$A,0)),"")) | G82: =IF(A82="","",IFERROR(INDEX(Data_Lists!$W$2:$W$4,MATCH(E82,Data_Lists!$V$2:$V$4,0)),0)) | H82: =IF(A82="","",100*MAX(0,N(D82)-1)) | I82: =IF(A82="","",N(G82)+N(H82))
B83: =IF(A83="","",IFERROR(INDEX(Data_Careers!$D:$D,MATCH(A83&"|1",Data_Careers!$A:$A,0)),"")) | G83: =IF(A83="","",IFERROR(INDEX(Data_Lists!$W$2:$W$4,MATCH(E83,Data_Lists!$V$2:$V$4,0)),0)) | H83: =IF(A83="","",100*MAX(0,N(D83)-1)) | I83: =IF(A83="","",N(G83)+N(H83))
B84: =IF(A84="","",IFERROR(INDEX(Data_Careers!$D:$D,MATCH(A84&"|1",Data_Careers!$A:$A,0)),"")) | G84: =IF(A84="","",IFERROR(INDEX(Data_Lists!$W$2:$W$4,MATCH(E84,Data_Lists!$V$2:$V$4,0)),0)) | H84: =IF(A84="","",100*MAX(0,N(D84)-1)) | I84: =IF(A84="","",N(G84)+N(H84))
B85: =IF(A85="","",IFERROR(INDEX(Data_Careers!$D:$D,MATCH(A85&"|1",Data_Careers!$A:$A,0)),"")) | G85: =IF(A85="","",IFERROR(INDEX(Data_Lists!$W$2:$W$4,MATCH(E85,Data_Lists!$V$2:$V$4,0)),0)) | H85: =IF(A85="","",100*MAX(0,N(D85)-1)) | I85: =IF(A85="","",N(G85)+N(H85))
B86: =IF(A86="","",IFERROR(INDEX(Data_Careers!$D:$D,MATCH(A86&"|1",Data_Careers!$A:$A,0)),"")) | G86: =IF(A86="","",IFERROR(INDEX(Data_Lists!$W$2:$W$4,MATCH(E86,Data_Lists!$V$2:$V$4,0)),0)) | H86: =IF(A86="","",100*MAX(0,N(D86)-1)) | I86: =IF(A86="","",N(G86)+N(H86))
A88: TALENT DETAILS (filled automatically from the Talents list)
A89: Talent | B89: Description | S89: Page
A90: =IF(M27="","",M27) | B90: =IF(M27="","",IFERROR(IFERROR(INDEX(Data_Talents!$E:$E,MATCH(M27,Data_Talents!$A:$A,0))&"",INDEX(Data_Talents!$E:$E,MATCH(TRIM(IFERROR(LEFT(M27,FIND("(",M27)-1),M27)),Data_Talents!$B:$B,0))&""),"")) | S90: =IF(M27="","",IFERROR(IFERROR(INDEX(Data_Talents!$F:$F,MATCH(M27,Data_Talents!$A:$A,0))&"",INDEX(Data_Talents!$F:$F,MATCH(TRIM(IFERROR(LEFT(M27,FIND("(",M27)-1),M27)),Data_Talents!$B:$B,0))&""),""))
A91: =IF(M28="","",M28) | B91: =IF(M28="","",IFERROR(IFERROR(INDEX(Data_Talents!$E:$E,MATCH(M28,Data_Talents!$A:$A,0))&"",INDEX(Data_Talents!$E:$E,MATCH(TRIM(IFERROR(LEFT(M28,FIND("(",M28)-1),M28)),Data_Talents!$B:$B,0))&""),"")) | S91: =IF(M28="","",IFERROR(IFERROR(INDEX(Data_Talents!$F:$F,MATCH(M28,Data_Talents!$A:$A,0))&"",INDEX(Data_Talents!$F:$F,MATCH(TRIM(IFERROR(LEFT(M28,FIND("(",M28)-1),M28)),Data_Talents!$B:$B,0))&""),""))
A92: =IF(M29="","",M29) | B92: =IF(M29="","",IFERROR(IFERROR(INDEX(Data_Talents!$E:$E,MATCH(M29,Data_Talents!$A:$A,0))&"",INDEX(Data_Talents!$E:$E,MATCH(TRIM(IFERROR(LEFT(M29,FIND("(",M29)-1),M29)),Data_Talents!$B:$B,0))&""),"")) | S92: =IF(M29="","",IFERROR(IFERROR(INDEX(Data_Talents!$F:$F,MATCH(M29,Data_Talents!$A:$A,0))&"",INDEX(Data_Talents!$F:$F,MATCH(TRIM(IFERROR(LEFT(M29,FIND("(",M29)-1),M29)),Data_Talents!$B:$B,0))&""),""))
A93: =IF(M30="","",M30) | B93: =IF(M30="","",IFERROR(IFERROR(INDEX(Data_Talents!$E:$E,MATCH(M30,Data_Talents!$A:$A,0))&"",INDEX(Data_Talents!$E:$E,MATCH(TRIM(IFERROR(LEFT(M30,FIND("(",M30)-1),M30)),Data_Talents!$B:$B,0))&""),"")) | S93: =IF(M30="","",IFERROR(IFERROR(INDEX(Data_Talents!$F:$F,MATCH(M30,Data_Talents!$A:$A,0))&"",INDEX(Data_Talents!$F:$F,MATCH(TRIM(IFERROR(LEFT(M30,FIND("(",M30)-1),M30)),Data_Talents!$B:$B,0))&""),""))
A94: =IF(M31="","",M31) | B94: =IF(M31="","",IFERROR(IFERROR(INDEX(Data_Talents!$E:$E,MATCH(M31,Data_Talents!$A:$A,0))&"",INDEX(Data_Talents!$E:$E,MATCH(TRIM(IFERROR(LEFT(M31,FIND("(",M31)-1),M31)),Data_Talents!$B:$B,0))&""),"")) | S94: =IF(M31="","",IFERROR(IFERROR(INDEX(Data_Talents!$F:$F,MATCH(M31,Data_Talents!$A:$A,0))&"",INDEX(Data_Talents!$F:$F,MATCH(TRIM(IFERROR(LEFT(M31,FIND("(",M31)-1),M31)),Data_Talents!$B:$B,0))&""),""))
A95: =IF(M32="","",M32) | B95: =IF(M32="","",IFERROR(IFERROR(INDEX(Data_Talents!$E:$E,MATCH(M32,Data_Talents!$A:$A,0))&"",INDEX(Data_Talents!$E:$E,MATCH(TRIM(IFERROR(LEFT(M32,FIND("(",M32)-1),M32)),Data_Talents!$B:$B,0))&""),"")) | S95: =IF(M32="","",IFERROR(IFERROR(INDEX(Data_Talents!$F:$F,MATCH(M32,Data_Talents!$A:$A,0))&"",INDEX(Data_Talents!$F:$F,MATCH(TRIM(IFERROR(LEFT(M32,FIND("(",M32)-1),M32)),Data_Talents!$B:$B,0))&""),""))
A96: =IF(M33="","",M33) | B96: =IF(M33="","",IFERROR(IFERROR(INDEX(Data_Talents!$E:$E,MATCH(M33,Data_Talents!$A:$A,0))&"",INDEX(Data_Talents!$E:$E,MATCH(TRIM(IFERROR(LEFT(M33,FIND("(",M33)-1),M33)),Data_Talents!$B:$B,0))&""),"")) | S96: =IF(M33="","",IFERROR(IFERROR(INDEX(Data_Talents!$F:$F,MATCH(M33,Data_Talents!$A:$A,0))&"",INDEX(Data_Talents!$F:$F,MATCH(TRIM(IFERROR(LEFT(M33,FIND("(",M33)-1),M33)),Data_Talents!$B:$B,0))&""),""))
A97: =IF(M34="","",M34) | B97: =IF(M34="","",IFERROR(IFERROR(INDEX(Data_Talents!$E:$E,MATCH(M34,Data_Talents!$A:$A,0))&"",INDEX(Data_Talents!$E:$E,MATCH(TRIM(IFERROR(LEFT(M34,FIND("(",M34)-1),M34)),Data_Talents!$B:$B,0))&""),"")) | S97: =IF(M34="","",IFERROR(IFERROR(INDEX(Data_Talents!$F:$F,MATCH(M34,Data_Talents!$A:$A,0))&"",INDEX(Data_Talents!$F:$F,MATCH(TRIM(IFERROR(LEFT(M34,FIND("(",M34)-1),M34)),Data_Talents!$B:$B,0))&""),""))
A98: =IF(M35="","",M35) | B98: =IF(M35="","",IFERROR(IFERROR(INDEX(Data_Talents!$E:$E,MATCH(M35,Data_Talents!$A:$A,0))&"",INDEX(Data_Talents!$E:$E,MATCH(TRIM(IFERROR(LEFT(M35,FIND("(",M35)-1),M35)),Data_Talents!$B:$B,0))&""),"")) | S98: =IF(M35="","",IFERROR(IFERROR(INDEX(Data_Talents!$F:$F,MATCH(M35,Data_Talents!$A:$A,0))&"",INDEX(Data_Talents!$F:$F,MATCH(TRIM(IFERROR(LEFT(M35,FIND("(",M35)-1),M35)),Data_Talents!$B:$B,0))&""),""))
A99: =IF(M36="","",M36) | B99: =IF(M36="","",IFERROR(IFERROR(INDEX(Data_Talents!$E:$E,MATCH(M36,Data_Talents!$A:$A,0))&"",INDEX(Data_Talents!$E:$E,MATCH(TRIM(IFERROR(LEFT(M36,FIND("(",M36)-1),M36)),Data_Talents!$B:$B,0))&""),"")) | S99: =IF(M36="","",IFERROR(IFERROR(INDEX(Data_Talents!$F:$F,MATCH(M36,Data_Talents!$A:$A,0))&"",INDEX(Data_Talents!$F:$F,MATCH(TRIM(IFERROR(LEFT(M36,FIND("(",M36)-1),M36)),Data_Talents!$B:$B,0))&""),""))
A100: =IF(M37="","",M37) | B100: =IF(M37="","",IFERROR(IFERROR(INDEX(Data_Talents!$E:$E,MATCH(M37,Data_Talents!$A:$A,0))&"",INDEX(Data_Talents!$E:$E,MATCH(TRIM(IFERROR(LEFT(M37,FIND("(",M37)-1),M37)),Data_Talents!$B:$B,0))&""),"")) | S100: =IF(M37="","",IFERROR(IFERROR(INDEX(Data_Talents!$F:$F,MATCH(M37,Data_Talents!$A:$A,0))&"",INDEX(Data_Talents!$F:$F,MATCH(TRIM(IFERROR(LEFT(M37,FIND("(",M37)-1),M37)),Data_Talents!$B:$B,0))&""),""))
A101: =IF(M38="","",M38) | B101: =IF(M38="","",IFERROR(IFERROR(INDEX(Data_Talents!$E:$E,MATCH(M38,Data_Talents!$A:$A,0))&"",INDEX(Data_Talents!$E:$E,MATCH(TRIM(IFERROR(LEFT(M38,FIND("(",M38)-1),M38)),Data_Talents!$B:$B,0))&""),"")) | S101: =IF(M38="","",IFERROR(IFERROR(INDEX(Data_Talents!$F:$F,MATCH(M38,Data_Talents!$A:$A,0))&"",INDEX(Data_Talents!$F:$F,MATCH(TRIM(IFERROR(LEFT(M38,FIND("(",M38)-1),M38)),Data_Talents!$B:$B,0))&""),""))
... A140: =IF(M77="","",M77) | B140: =IF(M77="","",IFERROR(IFERROR(INDEX(Data_Talents!$E:$E,MATCH(M77,Data_Talents!$A:$A,0))&"",INDEX(Data_Talents!$E:$E,MATCH(TRIM(IFERROR(LEFT(M77,FIND("(",M77)-1),M77)),Data_Talents!$B:$B,0))&""),"")) | S140: =IF(M77="","",IFERROR(IFERROR(INDEX(Data_Talents!$F:$F,MATCH(M77,Data_Talents!$A:$A,0))&"",INDEX(Data_Talents!$F:$F,MATCH(TRIM(IFERROR(LEFT(M77,FIND("(",M77)-1),M77)),Data_Talents!$B:$B,0))&""),""))

Sheet Career
A1: CAREER
A3: Career | B3: =IF(Character!$O$3="","(choose a career on the Character tab)",Character!$O$3) | D3: =N(Character!$B$4) | E3: ← current level (from Character tab)
A4: Class | B4: =IF(Character!$O$3="","",IFERROR(INDEX(Data_Careers!$D:$D,MATCH(Character!$O$3&"|1",Data_Careers!$A:$A,0))&"",""))
A5: Summary | B5: =IF(Character!$O$3="","",IFERROR(INDEX(Data_Careers!$L:$L,MATCH(Character!$O$3&"|1",Data_Careers!$A:$A,0))&"",""))
A6: Income | B6: =IF(Character!$O$3="","",IFERROR(INDEX(Data_Careers!$M:$M,MATCH(Character!$O$3&"|1",Data_Careers!$A:$A,0))&"","")) | D6: Species: | E6: =IF(Character!$O$3="","",IFERROR(INDEX(Data_Careers!$N:$N,MATCH(Character!$O$3&"|1",Data_Careers!$A:$A,0))&"",""))
A7: Page | B7: =IF(Character!$O$3="","",IFERROR(INDEX(Data_Careers!$O:$O,MATCH(Character!$O$3&"|1",Data_Careers!$A:$A,0))&"",""))
A9: CAREER LEVELS
A10: Level | B10: Title | C10: Status | D10: Skills | E10: Talents | F10: Trappings
A11: 1 | B11: =IF(Character!$O$3="","",IFERROR(INDEX(Data_Careers!$E:$E,MATCH(Character!$O$3&"|1",Data_Careers!$A:$A,0))&"","")) | C11: =IF(Character!$O$3="","",IFERROR(INDEX(Data_Careers!$F:$F,MATCH(Character!$O$3&"|1",Data_Careers!$A:$A,0))&"","")) | D11: =IF(Character!$O$3="","",IFERROR(INDEX(Data_Careers!$G:$G,MATCH(Character!$O$3&"|1",Data_Careers!$A:$A,0))&"","")) | E11: =IF(Character!$O$3="","",IFERROR(INDEX(Data_Careers!$H:$H,MATCH(Character!$O$3&"|1",Data_Careers!$A:$A,0))&"","")) | F11: =IF(Character!$O$3="","",IFERROR(INDEX(Data_Careers!$I:$I,MATCH(Character!$O$3&"|1",Data_Careers!$A:$A,0))&"",""))
A12: 2 | B12: =IF(Character!$O$3="","",IFERROR(INDEX(Data_Careers!$E:$E,MATCH(Character!$O$3&"|2",Data_Careers!$A:$A,0))&"","")) | C12: =IF(Character!$O$3="","",IFERROR(INDEX(Data_Careers!$F:$F,MATCH(Character!$O$3&"|2",Data_Careers!$A:$A,0))&"","")) | D12: =IF(Character!$O$3="","",IFERROR(INDEX(Data_Careers!$G:$G,MATCH(Character!$O$3&"|2",Data_Careers!$A:$A,0))&"","")) | E12: =IF(Character!$O$3="","",IFERROR(INDEX(Data_Careers!$H:$H,MATCH(Character!$O$3&"|2",Data_Careers!$A:$A,0))&"","")) | F12: =IF(Character!$O$3="","",IFERROR(INDEX(Data_Careers!$I:$I,MATCH(Character!$O$3&"|2",Data_Careers!$A:$A,0))&"",""))
A13: 3 | B13: =IF(Character!$O$3="","",IFERROR(INDEX(Data_Careers!$E:$E,MATCH(Character!$O$3&"|3",Data_Careers!$A:$A,0))&"","")) | C13: =IF(Character!$O$3="","",IFERROR(INDEX(Data_Careers!$F:$F,MATCH(Character!$O$3&"|3",Data_Careers!$A:$A,0))&"","")) | D13: =IF(Character!$O$3="","",IFERROR(INDEX(Data_Careers!$G:$G,MATCH(Character!$O$3&"|3",Data_Careers!$A:$A,0))&"","")) | E13: =IF(Character!$O$3="","",IFERROR(INDEX(Data_Careers!$H:$H,MATCH(Character!$O$3&"|3",Data_Careers!$A:$A,0))&"","")) | F13: =IF(Character!$O$3="","",IFERROR(INDEX(Data_Careers!$I:$I,MATCH(Character!$O$3&"|3",Data_Careers!$A:$A,0))&"",""))
A14: 4 | B14: =IF(Character!$O$3="","",IFERROR(INDEX(Data_Careers!$E:$E,MATCH(Character!$O$3&"|4",Data_Careers!$A:$A,0))&"","")) | C14: =IF(Character!$O$3="","",IFERROR(INDEX(Data_Careers!$F:$F,MATCH(Character!$O$3&"|4",Data_Careers!$A:$A,0))&"","")) | D14: =IF(Character!$O$3="","",IFERROR(INDEX(Data_Careers!$G:$G,MATCH(Character!$O$3&"|4",Data_Careers!$A:$A,0))&"","")) | E14: =IF(Character!$O$3="","",IFERROR(INDEX(Data_Careers!$H:$H,MATCH(Character!$O$3&"|4",Data_Careers!$A:$A,0))&"","")) | F14: =IF(Character!$O$3="","",IFERROR(INDEX(Data_Careers!$I:$I,MATCH(Character!$O$3&"|4",Data_Careers!$A:$A,0))&"",""))
A16: STARTING TRAPPINGS
A17: All | B17: Clothing, Dagger, Pouch
A18: Class | B18: =IF(B4="","",IFERROR(INDEX(Data_Lists!$M$2:$M$9,MATCH(B4,Data_Lists!$L$2:$L$9,0)),""))
A19: Career | B19: =F11
A20: Keeping the first career roll grants 2 Trappings from level 2 (1 if you picked from three rolls); each bonus Trapping ticks your Career Advancement tracker.
A22: CHARACTERISTIC ADVANCE SCHEME
A23: Char | B23: Characteristic | C23: Opens at level | D23: Advanceable now
A24: WS | B24: Weapon Skill | C24: =IF(Character!$O$3="","",IFERROR(IF(INDEX(Data_Careers!$P:$P,MATCH(Character!$O$3&"|1",Data_Careers!$A:$A,0))="","",INDEX(Data_Careers!$P:$P,MATCH(Character!$O$3&"|1",Data_Careers!$A:$A,0))),"")) | D24: =IF(C24="","",IF(N(C24)<=$D$3,"★ yes",""))
A25: BS | B25: Ballistic Skill | C25: =IF(Character!$O$3="","",IFERROR(IF(INDEX(Data_Careers!$Q:$Q,MATCH(Character!$O$3&"|1",Data_Careers!$A:$A,0))="","",INDEX(Data_Careers!$Q:$Q,MATCH(Character!$O$3&"|1",Data_Careers!$A:$A,0))),"")) | D25: =IF(C25="","",IF(N(C25)<=$D$3,"★ yes",""))
A26: S | B26: Strength | C26: =IF(Character!$O$3="","",IFERROR(IF(INDEX(Data_Careers!$R:$R,MATCH(Character!$O$3&"|1",Data_Careers!$A:$A,0))="","",INDEX(Data_Careers!$R:$R,MATCH(Character!$O$3&"|1",Data_Careers!$A:$A,0))),"")) | D26: =IF(C26="","",IF(N(C26)<=$D$3,"★ yes",""))
A27: T | B27: Toughness | C27: =IF(Character!$O$3="","",IFERROR(IF(INDEX(Data_Careers!$S:$S,MATCH(Character!$O$3&"|1",Data_Careers!$A:$A,0))="","",INDEX(Data_Careers!$S:$S,MATCH(Character!$O$3&"|1",Data_Careers!$A:$A,0))),"")) | D27: =IF(C27="","",IF(N(C27)<=$D$3,"★ yes",""))
A28: I | B28: Initiative | C28: =IF(Character!$O$3="","",IFERROR(IF(INDEX(Data_Careers!$T:$T,MATCH(Character!$O$3&"|1",Data_Careers!$A:$A,0))="","",INDEX(Data_Careers!$T:$T,MATCH(Character!$O$3&"|1",Data_Careers!$A:$A,0))),"")) | D28: =IF(C28="","",IF(N(C28)<=$D$3,"★ yes",""))
A29: Ag | B29: Agility | C29: =IF(Character!$O$3="","",IFERROR(IF(INDEX(Data_Careers!$U:$U,MATCH(Character!$O$3&"|1",Data_Careers!$A:$A,0))="","",INDEX(Data_Careers!$U:$U,MATCH(Character!$O$3&"|1",Data_Careers!$A:$A,0))),"")) | D29: =IF(C29="","",IF(N(C29)<=$D$3,"★ yes",""))
A30: Dex | B30: Dexterity | C30: =IF(Character!$O$3="","",IFERROR(IF(INDEX(Data_Careers!$V:$V,MATCH(Character!$O$3&"|1",Data_Careers!$A:$A,0))="","",INDEX(Data_Careers!$V:$V,MATCH(Character!$O$3&"|1",Data_Careers!$A:$A,0))),"")) | D30: =IF(C30="","",IF(N(C30)<=$D$3,"★ yes",""))
A31: Int | B31: Intelligence | C31: =IF(Character!$O$3="","",IFERROR(IF(INDEX(Data_Careers!$W:$W,MATCH(Character!$O$3&"|1",Data_Careers!$A:$A,0))="","",INDEX(Data_Careers!$W:$W,MATCH(Character!$O$3&"|1",Data_Careers!$A:$A,0))),"")) | D31: =IF(C31="","",IF(N(C31)<=$D$3,"★ yes",""))
A32: WP | B32: Willpower | C32: =IF(Character!$O$3="","",IFERROR(IF(INDEX(Data_Careers!$X:$X,MATCH(Character!$O$3&"|1",Data_Careers!$A:$A,0))="","",INDEX(Data_Careers!$X:$X,MATCH(Character!$O$3&"|1",Data_Careers!$A:$A,0))),"")) | D32: =IF(C32="","",IF(N(C32)<=$D$3,"★ yes",""))
A33: Fel | B33: Fellowship | C33: =IF(Character!$O$3="","",IFERROR(IF(INDEX(Data_Careers!$Y:$Y,MATCH(Character!$O$3&"|1",Data_Careers!$A:$A,0))="","",INDEX(Data_Careers!$Y:$Y,MATCH(Character!$O$3&"|1",Data_Careers!$A:$A,0))),"")) | D33: =IF(C33="","",IF(N(C33)<=$D$3,"★ yes",""))

Sheet Equipment
A1: EQUIPMENT
A2: Pick items from the dropdowns; stats fill in automatically. Worn items count 1 Enc less. Items inside a container count towards that container's capacity, not your own (only the container's Enc does).
A4: WEAPONS
A5: Weapon | B5: Group | C5: Hands | D5: Reach / Range | E5: Damage | F5: Damage total | G5: Qualities & Flaws | H5: Enc | I5: Location | J5: Skill value | K5: Price | L5: Notes
B6: =IF(A6="","",IFERROR(INDEX(Data_Gear!$C:$C,MATCH(A6,Data_Gear!$A:$A,0))&"","")) | C6: =IF(A6="","",IFERROR(INDEX(Data_Gear!$D:$D,MATCH(A6,Data_Gear!$A:$A,0))&"","")) | D6: =IF(A6="","",IFERROR(INDEX(Data_Gear!$J:$J,MATCH(A6,Data_Gear!$A:$A,0))&"","")) | E6: =IF(A6="","",IFERROR(INDEX(Data_Gear!$K:$K,MATCH(A6,Data_Gear!$A:$A,0))&"","")) | F6: =IF(E6="","",IFERROR(IF(ISNUMBER(SEARCH("SB",E6)),Character!$D$17,0)+VALUE(SUBSTITUTE(SUBSTITUTE(SUBSTITUTE(SUBSTITUTE(SUBSTITUTE(E6,"+SB",""),"SB","")," ",""),"+",""),"–","-")),IF(ISNUMBER(SEARCH("SB",E6)),Character!$D$17,""))) | G6: =IF(A6="","",IFERROR(INDEX(Data_Gear!$L:$L,MATCH(A6,Data_Gear!$A:$A,0))&"","")) | H6: =IF(A6="","",IFERROR(INDEX(Data_Gear!$G:$G,MATCH(A6,Data_Gear!$A:$A,0)),"")) | J6: =IF(A6="","",IFERROR(INDEX(Character!$G$27:$G$77,MATCH(IF(M6="Melee weapon","Melee (","Ranged (")&B6&")",Character!$A$27:$A$77,0)),IF(M6="Melee weapon",Character!$B$16,Character!$C$16))) | K6: =IF(A6="","",IFERROR(INDEX(Data_Gear!$E:$E,MATCH(A6,Data_Gear!$A:$A,0))&"","")) | M6: =IF(A6="","",IFERROR(INDEX(Data_Gear!$B:$B,MATCH(A6,Data_Gear!$A:$A,0))&"","")) | N6: =IF(A6="",0,MAX(0,N(H6)-IF(I6="Worn",1,0)))
B7: =IF(A7="","",IFERROR(INDEX(Data_Gear!$C:$C,MATCH(A7,Data_Gear!$A:$A,0))&"","")) | C7: =IF(A7="","",IFERROR(INDEX(Data_Gear!$D:$D,MATCH(A7,Data_Gear!$A:$A,0))&"","")) | D7: =IF(A7="","",IFERROR(INDEX(Data_Gear!$J:$J,MATCH(A7,Data_Gear!$A:$A,0))&"","")) | E7: =IF(A7="","",IFERROR(INDEX(Data_Gear!$K:$K,MATCH(A7,Data_Gear!$A:$A,0))&"","")) | F7: =IF(E7="","",IFERROR(IF(ISNUMBER(SEARCH("SB",E7)),Character!$D$17,0)+VALUE(SUBSTITUTE(SUBSTITUTE(SUBSTITUTE(SUBSTITUTE(SUBSTITUTE(E7,"+SB",""),"SB","")," ",""),"+",""),"–","-")),IF(ISNUMBER(SEARCH("SB",E7)),Character!$D$17,""))) | G7: =IF(A7="","",IFERROR(INDEX(Data_Gear!$L:$L,MATCH(A7,Data_Gear!$A:$A,0))&"","")) | H7: =IF(A7="","",IFERROR(INDEX(Data_Gear!$G:$G,MATCH(A7,Data_Gear!$A:$A,0)),"")) | J7: =IF(A7="","",IFERROR(INDEX(Character!$G$27:$G$77,MATCH(IF(M7="Melee weapon","Melee (","Ranged (")&B7&")",Character!$A$27:$A$77,0)),IF(M7="Melee weapon",Character!$B$16,Character!$C$16))) | K7: =IF(A7="","",IFERROR(INDEX(Data_Gear!$E:$E,MATCH(A7,Data_Gear!$A:$A,0))&"","")) | M7: =IF(A7="","",IFERROR(INDEX(Data_Gear!$B:$B,MATCH(A7,Data_Gear!$A:$A,0))&"","")) | N7: =IF(A7="",0,MAX(0,N(H7)-IF(I7="Worn",1,0)))
B8: =IF(A8="","",IFERROR(INDEX(Data_Gear!$C:$C,MATCH(A8,Data_Gear!$A:$A,0))&"","")) | C8: =IF(A8="","",IFERROR(INDEX(Data_Gear!$D:$D,MATCH(A8,Data_Gear!$A:$A,0))&"","")) | D8: =IF(A8="","",IFERROR(INDEX(Data_Gear!$J:$J,MATCH(A8,Data_Gear!$A:$A,0))&"","")) | E8: =IF(A8="","",IFERROR(INDEX(Data_Gear!$K:$K,MATCH(A8,Data_Gear!$A:$A,0))&"","")) | F8: =IF(E8="","",IFERROR(IF(ISNUMBER(SEARCH("SB",E8)),Character!$D$17,0)+VALUE(SUBSTITUTE(SUBSTITUTE(SUBSTITUTE(SUBSTITUTE(SUBSTITUTE(E8,"+SB",""),"SB","")," ",""),"+",""),"–","-")),IF(ISNUMBER(SEARCH("SB",E8)),Character!$D$17,""))) | G8: =IF(A8="","",IFERROR(INDEX(Data_Gear!$L:$L,MATCH(A8,Data_Gear!$A:$A,0))&"","")) | H8: =IF(A8="","",IFERROR(INDEX(Data_Gear!$G:$G,MATCH(A8,Data_Gear!$A:$A,0)),"")) | J8: =IF(A8="","",IFERROR(INDEX(Character!$G$27:$G$77,MATCH(IF(M8="Melee weapon","Melee (","Ranged (")&B8&")",Character!$A$27:$A$77,0)),IF(M8="Melee weapon",Character!$B$16,Character!$C$16))) | K8: =IF(A8="","",IFERROR(INDEX(Data_Gear!$E:$E,MATCH(A8,Data_Gear!$A:$A,0))&"","")) | M8: =IF(A8="","",IFERROR(INDEX(Data_Gear!$B:$B,MATCH(A8,Data_Gear!$A:$A,0))&"","")) | N8: =IF(A8="",0,MAX(0,N(H8)-IF(I8="Worn",1,0)))
B9: =IF(A9="","",IFERROR(INDEX(Data_Gear!$C:$C,MATCH(A9,Data_Gear!$A:$A,0))&"","")) | C9: =IF(A9="","",IFERROR(INDEX(Data_Gear!$D:$D,MATCH(A9,Data_Gear!$A:$A,0))&"","")) | D9: =IF(A9="","",IFERROR(INDEX(Data_Gear!$J:$J,MATCH(A9,Data_Gear!$A:$A,0))&"","")) | E9: =IF(A9="","",IFERROR(INDEX(Data_Gear!$K:$K,MATCH(A9,Data_Gear!$A:$A,0))&"","")) | F9: =IF(E9="","",IFERROR(IF(ISNUMBER(SEARCH("SB",E9)),Character!$D$17,0)+VALUE(SUBSTITUTE(SUBSTITUTE(SUBSTITUTE(SUBSTITUTE(SUBSTITUTE(E9,"+SB",""),"SB","")," ",""),"+",""),"–","-")),IF(ISNUMBER(SEARCH("SB",E9)),Character!$D$17,""))) | G9: =IF(A9="","",IFERROR(INDEX(Data_Gear!$L:$L,MATCH(A9,Data_Gear!$A:$A,0))&"","")) | H9: =IF(A9="","",IFERROR(INDEX(Data_Gear!$G:$G,MATCH(A9,Data_Gear!$A:$A,0)),"")) | J9: =IF(A9="","",IFERROR(INDEX(Character!$G$27:$G$77,MATCH(IF(M9="Melee weapon","Melee (","Ranged (")&B9&")",Character!$A$27:$A$77,0)),IF(M9="Melee weapon",Character!$B$16,Character!$C$16))) | K9: =IF(A9="","",IFERROR(INDEX(Data_Gear!$E:$E,MATCH(A9,Data_Gear!$A:$A,0))&"","")) | M9: =IF(A9="","",IFERROR(INDEX(Data_Gear!$B:$B,MATCH(A9,Data_Gear!$A:$A,0))&"","")) | N9: =IF(A9="",0,MAX(0,N(H9)-IF(I9="Worn",1,0)))
B10: =IF(A10="","",IFERROR(INDEX(Data_Gear!$C:$C,MATCH(A10,Data_Gear!$A:$A,0))&"","")) | C10: =IF(A10="","",IFERROR(INDEX(Data_Gear!$D:$D,MATCH(A10,Data_Gear!$A:$A,0))&"","")) | D10: =IF(A10="","",IFERROR(INDEX(Data_Gear!$J:$J,MATCH(A10,Data_Gear!$A:$A,0))&"","")) | E10: =IF(A10="","",IFERROR(INDEX(Data_Gear!$K:$K,MATCH(A10,Data_Gear!$A:$A,0))&"","")) | F10: =IF(E10="","",IFERROR(IF(ISNUMBER(SEARCH("SB",E10)),Character!$D$17,0)+VALUE(SUBSTITUTE(SUBSTITUTE(SUBSTITUTE(SUBSTITUTE(SUBSTITUTE(E10,"+SB",""),"SB","")," ",""),"+",""),"–","-")),IF(ISNUMBER(SEARCH("SB",E10)),Character!$D$17,""))) | G10: =IF(A10="","",IFERROR(INDEX(Data_Gear!$L:$L,MATCH(A10,Data_Gear!$A:$A,0))&"","")) | H10: =IF(A10="","",IFERROR(INDEX(Data_Gear!$G:$G,MATCH(A10,Data_Gear!$A:$A,0)),"")) | J10: =IF(A10="","",IFERROR(INDEX(Character!$G$27:$G$77,MATCH(IF(M10="Melee weapon","Melee (","Ranged (")&B10&")",Character!$A$27:$A$77,0)),IF(M10="Melee weapon",Character!$B$16,Character!$C$16))) | K10: =IF(A10="","",IFERROR(INDEX(Data_Gear!$E:$E,MATCH(A10,Data_Gear!$A:$A,0))&"","")) | M10: =IF(A10="","",IFERROR(INDEX(Data_Gear!$B:$B,MATCH(A10,Data_Gear!$A:$A,0))&"","")) | N10: =IF(A10="",0,MAX(0,N(H10)-IF(I10="Worn",1,0)))
B11: =IF(A11="","",IFERROR(INDEX(Data_Gear!$C:$C,MATCH(A11,Data_Gear!$A:$A,0))&"","")) | C11: =IF(A11="","",IFERROR(INDEX(Data_Gear!$D:$D,MATCH(A11,Data_Gear!$A:$A,0))&"","")) | D11: =IF(A11="","",IFERROR(INDEX(Data_Gear!$J:$J,MATCH(A11,Data_Gear!$A:$A,0))&"","")) | E11: =IF(A11="","",IFERROR(INDEX(Data_Gear!$K:$K,MATCH(A11,Data_Gear!$A:$A,0))&"","")) | F11: =IF(E11="","",IFERROR(IF(ISNUMBER(SEARCH("SB",E11)),Character!$D$17,0)+VALUE(SUBSTITUTE(SUBSTITUTE(SUBSTITUTE(SUBSTITUTE(SUBSTITUTE(E11,"+SB",""),"SB","")," ",""),"+",""),"–","-")),IF(ISNUMBER(SEARCH("SB",E11)),Character!$D$17,""))) | G11: =IF(A11="","",IFERROR(INDEX(Data_Gear!$L:$L,MATCH(A11,Data_Gear!$A:$A,0))&"","")) | H11: =IF(A11="","",IFERROR(INDEX(Data_Gear!$G:$G,MATCH(A11,Data_Gear!$A:$A,0)),"")) | J11: =IF(A11="","",IFERROR(INDEX(Character!$G$27:$G$77,MATCH(IF(M11="Melee weapon","Melee (","Ranged (")&B11&")",Character!$A$27:$A$77,0)),IF(M11="Melee weapon",Character!$B$16,Character!$C$16))) | K11: =IF(A11="","",IFERROR(INDEX(Data_Gear!$E:$E,MATCH(A11,Data_Gear!$A:$A,0))&"","")) | M11: =IF(A11="","",IFERROR(INDEX(Data_Gear!$B:$B,MATCH(A11,Data_Gear!$A:$A,0))&"","")) | N11: =IF(A11="",0,MAX(0,N(H11)-IF(I11="Worn",1,0)))
B12: =IF(A12="","",IFERROR(INDEX(Data_Gear!$C:$C,MATCH(A12,Data_Gear!$A:$A,0))&"","")) | C12: =IF(A12="","",IFERROR(INDEX(Data_Gear!$D:$D,MATCH(A12,Data_Gear!$A:$A,0))&"","")) | D12: =IF(A12="","",IFERROR(INDEX(Data_Gear!$J:$J,MATCH(A12,Data_Gear!$A:$A,0))&"","")) | E12: =IF(A12="","",IFERROR(INDEX(Data_Gear!$K:$K,MATCH(A12,Data_Gear!$A:$A,0))&"","")) | F12: =IF(E12="","",IFERROR(IF(ISNUMBER(SEARCH("SB",E12)),Character!$D$17,0)+VALUE(SUBSTITUTE(SUBSTITUTE(SUBSTITUTE(SUBSTITUTE(SUBSTITUTE(E12,"+SB",""),"SB","")," ",""),"+",""),"–","-")),IF(ISNUMBER(SEARCH("SB",E12)),Character!$D$17,""))) | G12: =IF(A12="","",IFERROR(INDEX(Data_Gear!$L:$L,MATCH(A12,Data_Gear!$A:$A,0))&"","")) | H12: =IF(A12="","",IFERROR(INDEX(Data_Gear!$G:$G,MATCH(A12,Data_Gear!$A:$A,0)),"")) | J12: =IF(A12="","",IFERROR(INDEX(Character!$G$27:$G$77,MATCH(IF(M12="Melee weapon","Melee (","Ranged (")&B12&")",Character!$A$27:$A$77,0)),IF(M12="Melee weapon",Character!$B$16,Character!$C$16))) | K12: =IF(A12="","",IFERROR(INDEX(Data_Gear!$E:$E,MATCH(A12,Data_Gear!$A:$A,0))&"","")) | M12: =IF(A12="","",IFERROR(INDEX(Data_Gear!$B:$B,MATCH(A12,Data_Gear!$A:$A,0))&"","")) | N12: =IF(A12="",0,MAX(0,N(H12)-IF(I12="Worn",1,0)))
B13: =IF(A13="","",IFERROR(INDEX(Data_Gear!$C:$C,MATCH(A13,Data_Gear!$A:$A,0))&"","")) | C13: =IF(A13="","",IFERROR(INDEX(Data_Gear!$D:$D,MATCH(A13,Data_Gear!$A:$A,0))&"","")) | D13: =IF(A13="","",IFERROR(INDEX(Data_Gear!$J:$J,MATCH(A13,Data_Gear!$A:$A,0))&"","")) | E13: =IF(A13="","",IFERROR(INDEX(Data_Gear!$K:$K,MATCH(A13,Data_Gear!$A:$A,0))&"","")) | F13: =IF(E13="","",IFERROR(IF(ISNUMBER(SEARCH("SB",E13)),Character!$D$17,0)+VALUE(SUBSTITUTE(SUBSTITUTE(SUBSTITUTE(SUBSTITUTE(SUBSTITUTE(E13,"+SB",""),"SB","")," ",""),"+",""),"–","-")),IF(ISNUMBER(SEARCH("SB",E13)),Character!$D$17,""))) | G13: =IF(A13="","",IFERROR(INDEX(Data_Gear!$L:$L,MATCH(A13,Data_Gear!$A:$A,0))&"","")) | H13: =IF(A13="","",IFERROR(INDEX(Data_Gear!$G:$G,MATCH(A13,Data_Gear!$A:$A,0)),"")) | J13: =IF(A13="","",IFERROR(INDEX(Character!$G$27:$G$77,MATCH(IF(M13="Melee weapon","Melee (","Ranged (")&B13&")",Character!$A$27:$A$77,0)),IF(M13="Melee weapon",Character!$B$16,Character!$C$16))) | K13: =IF(A13="","",IFERROR(INDEX(Data_Gear!$E:$E,MATCH(A13,Data_Gear!$A:$A,0))&"","")) | M13: =IF(A13="","",IFERROR(INDEX(Data_Gear!$B:$B,MATCH(A13,Data_Gear!$A:$A,0))&"","")) | N13: =IF(A13="",0,MAX(0,N(H13)-IF(I13="Worn",1,0)))
A15: ARMOUR & SHIELDS
A16: Armour | B16: Locations | C16: AP | D16: Penalty | G16: Qualities & Flaws | H16: Enc | I16: Location | J16: Notes
B17: =IF(A17="","",IFERROR(INDEX(Data_Gear!$M:$M,MATCH(A17,Data_Gear!$A:$A,0))&"","")) | C17: =IF(A17="",0,IFERROR(N(INDEX(Data_Gear!$N:$N,MATCH(A17,Data_Gear!$A:$A,0))),0)) | D17: =IF(A17="","",IFERROR(INDEX(Data_Gear!$O:$O,MATCH(A17,Data_Gear!$A:$A,0))&"","")) | G17: =IF(A17="","",IFERROR(INDEX(Data_Gear!$L:$L,MATCH(A17,Data_Gear!$A:$A,0))&"","")) | H17: =IF(A17="","",IFERROR(INDEX(Data_Gear!$G:$G,MATCH(A17,Data_Gear!$A:$A,0)),"")) | N17: =IF(A17="",0,MAX(0,N(H17)-IF(I17="Worn",1,0)))
B18: =IF(A18="","",IFERROR(INDEX(Data_Gear!$M:$M,MATCH(A18,Data_Gear!$A:$A,0))&"","")) | C18: =IF(A18="",0,IFERROR(N(INDEX(Data_Gear!$N:$N,MATCH(A18,Data_Gear!$A:$A,0))),0)) | D18: =IF(A18="","",IFERROR(INDEX(Data_Gear!$O:$O,MATCH(A18,Data_Gear!$A:$A,0))&"","")) | G18: =IF(A18="","",IFERROR(INDEX(Data_Gear!$L:$L,MATCH(A18,Data_Gear!$A:$A,0))&"","")) | H18: =IF(A18="","",IFERROR(INDEX(Data_Gear!$G:$G,MATCH(A18,Data_Gear!$A:$A,0)),"")) | N18: =IF(A18="",0,MAX(0,N(H18)-IF(I18="Worn",1,0)))
B19: =IF(A19="","",IFERROR(INDEX(Data_Gear!$M:$M,MATCH(A19,Data_Gear!$A:$A,0))&"","")) | C19: =IF(A19="",0,IFERROR(N(INDEX(Data_Gear!$N:$N,MATCH(A19,Data_Gear!$A:$A,0))),0)) | D19: =IF(A19="","",IFERROR(INDEX(Data_Gear!$O:$O,MATCH(A19,Data_Gear!$A:$A,0))&"","")) | G19: =IF(A19="","",IFERROR(INDEX(Data_Gear!$L:$L,MATCH(A19,Data_Gear!$A:$A,0))&"","")) | H19: =IF(A19="","",IFERROR(INDEX(Data_Gear!$G:$G,MATCH(A19,Data_Gear!$A:$A,0)),"")) | N19: =IF(A19="",0,MAX(0,N(H19)-IF(I19="Worn",1,0)))
B20: =IF(A20="","",IFERROR(INDEX(Data_Gear!$M:$M,MATCH(A20,Data_Gear!$A:$A,0))&"","")) | C20: =IF(A20="",0,IFERROR(N(INDEX(Data_Gear!$N:$N,MATCH(A20,Data_Gear!$A:$A,0))),0)) | D20: =IF(A20="","",IFERROR(INDEX(Data_Gear!$O:$O,MATCH(A20,Data_Gear!$A:$A,0))&"","")) | G20: =IF(A20="","",IFERROR(INDEX(Data_Gear!$L:$L,MATCH(A20,Data_Gear!$A:$A,0))&"","")) | H20: =IF(A20="","",IFERROR(INDEX(Data_Gear!$G:$G,MATCH(A20,Data_Gear!$A:$A,0)),"")) | N20: =IF(A20="",0,MAX(0,N(H20)-IF(I20="Worn",1,0)))
B21: =IF(A21="","",IFERROR(INDEX(Data_Gear!$M:$M,MATCH(A21,Data_Gear!$A:$A,0))&"","")) | C21: =IF(A21="",0,IFERROR(N(INDEX(Data_Gear!$N:$N,MATCH(A21,Data_Gear!$A:$A,0))),0)) | D21: =IF(A21="","",IFERROR(INDEX(Data_Gear!$O:$O,MATCH(A21,Data_Gear!$A:$A,0))&"","")) | G21: =IF(A21="","",IFERROR(INDEX(Data_Gear!$L:$L,MATCH(A21,Data_Gear!$A:$A,0))&"","")) | H21: =IF(A21="","",IFERROR(INDEX(Data_Gear!$G:$G,MATCH(A21,Data_Gear!$A:$A,0)),"")) | N21: =IF(A21="",0,MAX(0,N(H21)-IF(I21="Worn",1,0)))
B22: =IF(A22="","",IFERROR(INDEX(Data_Gear!$M:$M,MATCH(A22,Data_Gear!$A:$A,0))&"","")) | C22: =IF(A22="",0,IFERROR(N(INDEX(Data_Gear!$N:$N,MATCH(A22,Data_Gear!$A:$A,0))),0)) | D22: =IF(A22="","",IFERROR(INDEX(Data_Gear!$O:$O,MATCH(A22,Data_Gear!$A:$A,0))&"","")) | G22: =IF(A22="","",IFERROR(INDEX(Data_Gear!$L:$L,MATCH(A22,Data_Gear!$A:$A,0))&"","")) | H22: =IF(A22="","",IFERROR(INDEX(Data_Gear!$G:$G,MATCH(A22,Data_Gear!$A:$A,0)),"")) | N22: =IF(A22="",0,MAX(0,N(H22)-IF(I22="Worn",1,0)))
B23: =IF(A23="","",IFERROR(INDEX(Data_Gear!$M:$M,MATCH(A23,Data_Gear!$A:$A,0))&"","")) | C23: =IF(A23="",0,IFERROR(N(INDEX(Data_Gear!$N:$N,MATCH(A23,Data_Gear!$A:$A,0))),0)) | D23: =IF(A23="","",IFERROR(INDEX(Data_Gear!$O:$O,MATCH(A23,Data_Gear!$A:$A,0))&"","")) | G23: =IF(A23="","",IFERROR(INDEX(Data_Gear!$L:$L,MATCH(A23,Data_Gear!$A:$A,0))&"","")) | H23: =IF(A23="","",IFERROR(INDEX(Data_Gear!$G:$G,MATCH(A23,Data_Gear!$A:$A,0)),"")) | N23: =IF(A23="",0,MAX(0,N(H23)-IF(I23="Worn",1,0)))
B24: =IF(A24="","",IFERROR(INDEX(Data_Gear!$M:$M,MATCH(A24,Data_Gear!$A:$A,0))&"","")) | C24: =IF(A24="",0,IFERROR(N(INDEX(Data_Gear!$N:$N,MATCH(A24,Data_Gear!$A:$A,0))),0)) | D24: =IF(A24="","",IFERROR(INDEX(Data_Gear!$O:$O,MATCH(A24,Data_Gear!$A:$A,0))&"","")) | G24: =IF(A24="","",IFERROR(INDEX(Data_Gear!$L:$L,MATCH(A24,Data_Gear!$A:$A,0))&"","")) | H24: =IF(A24="","",IFERROR(INDEX(Data_Gear!$G:$G,MATCH(A24,Data_Gear!$A:$A,0)),"")) | N24: =IF(A24="",0,MAX(0,N(H24)-IF(I24="Worn",1,0)))
A25: Armour Points (worn) | B25: Head | C25: Arms | D25: Body | E25: Legs | F25: Shield
A26: AP by hit location | B26: =SUMPRODUCT(ISNUMBER(SEARCH("Head",$B$17:$B$24))*($I$17:$I$24="Worn")*$C$17:$C$24) | C26: =SUMPRODUCT(ISNUMBER(SEARCH("Arms",$B$17:$B$24))*($I$17:$I$24="Worn")*$C$17:$C$24) | D26: =SUMPRODUCT(ISNUMBER(SEARCH("Body",$B$17:$B$24))*($I$17:$I$24="Worn")*$C$17:$C$24) | E26: =SUMPRODUCT(ISNUMBER(SEARCH("Legs",$B$17:$B$24))*($I$17:$I$24="Worn")*$C$17:$C$24) | F26: =SUMPRODUCT(($B$17:$B$24="Shield")*(($I$17:$I$24="Worn")+($I$17:$I$24="Carried"))*$C$17:$C$24)
A29: TRAPPINGS
A30: Item | B30: Qty | C30: Category | D30: Enc (each) | E30: Enc (total) | F30: Location | G30: Availability | H30: Price | I30: Value (pennies) | J30: Notes
C31: =IF(A31="","",IFERROR(INDEX(Data_Gear!$B:$B,MATCH(A31,Data_Gear!$A:$A,0))&"","")) | D31: =IF(A31="","",IFERROR(N(INDEX(Data_Gear!$G:$G,MATCH(A31,Data_Gear!$A:$A,0))),0)) | E31: =IF(A31="",0,MAX(0,IF(N(B31)=0,1,N(B31))*N(D31)-IF(F31="Worn",IF(N(B31)=0,1,N(B31)),0))) | G31: =IF(A31="","",IFERROR(INDEX(Data_Gear!$H:$H,MATCH(A31,Data_Gear!$A:$A,0))&"","")) | H31: =IF(A31="","",IFERROR(INDEX(Data_Gear!$E:$E,MATCH(A31,Data_Gear!$A:$A,0))&"","")) | I31: =IF(A31="","",IFERROR(IF(N(B31)=0,1,N(B31))*INDEX(Data_Gear!$F:$F,MATCH(A31,Data_Gear!$A:$A,0)),""))
C32: =IF(A32="","",IFERROR(INDEX(Data_Gear!$B:$B,MATCH(A32,Data_Gear!$A:$A,0))&"","")) | D32: =IF(A32="","",IFERROR(N(INDEX(Data_Gear!$G:$G,MATCH(A32,Data_Gear!$A:$A,0))),0)) | E32: =IF(A32="",0,MAX(0,IF(N(B32)=0,1,N(B32))*N(D32)-IF(F32="Worn",IF(N(B32)=0,1,N(B32)),0))) | G32: =IF(A32="","",IFERROR(INDEX(Data_Gear!$H:$H,MATCH(A32,Data_Gear!$A:$A,0))&"","")) | H32: =IF(A32="","",IFERROR(INDEX(Data_Gear!$E:$E,MATCH(A32,Data_Gear!$A:$A,0))&"","")) | I32: =IF(A32="","",IFERROR(IF(N(B32)=0,1,N(B32))*INDEX(Data_Gear!$F:$F,MATCH(A32,Data_Gear!$A:$A,0)),""))
C33: =IF(A33="","",IFERROR(INDEX(Data_Gear!$B:$B,MATCH(A33,Data_Gear!$A:$A,0))&"","")) | D33: =IF(A33="","",IFERROR(N(INDEX(Data_Gear!$G:$G,MATCH(A33,Data_Gear!$A:$A,0))),0)) | E33: =IF(A33="",0,MAX(0,IF(N(B33)=0,1,N(B33))*N(D33)-IF(F33="Worn",IF(N(B33)=0,1,N(B33)),0))) | G33: =IF(A33="","",IFERROR(INDEX(Data_Gear!$H:$H,MATCH(A33,Data_Gear!$A:$A,0))&"","")) | H33: =IF(A33="","",IFERROR(INDEX(Data_Gear!$E:$E,MATCH(A33,Data_Gear!$A:$A,0))&"","")) | I33: =IF(A33="","",IFERROR(IF(N(B33)=0,1,N(B33))*INDEX(Data_Gear!$F:$F,MATCH(A33,Data_Gear!$A:$A,0)),""))
C34: =IF(A34="","",IFERROR(INDEX(Data_Gear!$B:$B,MATCH(A34,Data_Gear!$A:$A,0))&"","")) | D34: =IF(A34="","",IFERROR(N(INDEX(Data_Gear!$G:$G,MATCH(A34,Data_Gear!$A:$A,0))),0)) | E34: =IF(A34="",0,MAX(0,IF(N(B34)=0,1,N(B34))*N(D34)-IF(F34="Worn",IF(N(B34)=0,1,N(B34)),0))) | G34: =IF(A34="","",IFERROR(INDEX(Data_Gear!$H:$H,MATCH(A34,Data_Gear!$A:$A,0))&"","")) | H34: =IF(A34="","",IFERROR(INDEX(Data_Gear!$E:$E,MATCH(A34,Data_Gear!$A:$A,0))&"","")) | I34: =IF(A34="","",IFERROR(IF(N(B34)=0,1,N(B34))*INDEX(Data_Gear!$F:$F,MATCH(A34,Data_Gear!$A:$A,0)),""))
C35: =IF(A35="","",IFERROR(INDEX(Data_Gear!$B:$B,MATCH(A35,Data_Gear!$A:$A,0))&"","")) | D35: =IF(A35="","",IFERROR(N(INDEX(Data_Gear!$G:$G,MATCH(A35,Data_Gear!$A:$A,0))),0)) | E35: =IF(A35="",0,MAX(0,IF(N(B35)=0,1,N(B35))*N(D35)-IF(F35="Worn",IF(N(B35)=0,1,N(B35)),0))) | G35: =IF(A35="","",IFERROR(INDEX(Data_Gear!$H:$H,MATCH(A35,Data_Gear!$A:$A,0))&"","")) | H35: =IF(A35="","",IFERROR(INDEX(Data_Gear!$E:$E,MATCH(A35,Data_Gear!$A:$A,0))&"","")) | I35: =IF(A35="","",IFERROR(IF(N(B35)=0,1,N(B35))*INDEX(Data_Gear!$F:$F,MATCH(A35,Data_Gear!$A:$A,0)),""))
C36: =IF(A36="","",IFERROR(INDEX(Data_Gear!$B:$B,MATCH(A36,Data_Gear!$A:$A,0))&"","")) | D36: =IF(A36="","",IFERROR(N(INDEX(Data_Gear!$G:$G,MATCH(A36,Data_Gear!$A:$A,0))),0)) | E36: =IF(A36="",0,MAX(0,IF(N(B36)=0,1,N(B36))*N(D36)-IF(F36="Worn",IF(N(B36)=0,1,N(B36)),0))) | G36: =IF(A36="","",IFERROR(INDEX(Data_Gear!$H:$H,MATCH(A36,Data_Gear!$A:$A,0))&"","")) | H36: =IF(A36="","",IFERROR(INDEX(Data_Gear!$E:$E,MATCH(A36,Data_Gear!$A:$A,0))&"","")) | I36: =IF(A36="","",IFERROR(IF(N(B36)=0,1,N(B36))*INDEX(Data_Gear!$F:$F,MATCH(A36,Data_Gear!$A:$A,0)),""))
C37: =IF(A37="","",IFERROR(INDEX(Data_Gear!$B:$B,MATCH(A37,Data_Gear!$A:$A,0))&"","")) | D37: =IF(A37="","",IFERROR(N(INDEX(Data_Gear!$G:$G,MATCH(A37,Data_Gear!$A:$A,0))),0)) | E37: =IF(A37="",0,MAX(0,IF(N(B37)=0,1,N(B37))*N(D37)-IF(F37="Worn",IF(N(B37)=0,1,N(B37)),0))) | G37: =IF(A37="","",IFERROR(INDEX(Data_Gear!$H:$H,MATCH(A37,Data_Gear!$A:$A,0))&"","")) | H37: =IF(A37="","",IFERROR(INDEX(Data_Gear!$E:$E,MATCH(A37,Data_Gear!$A:$A,0))&"","")) | I37: =IF(A37="","",IFERROR(IF(N(B37)=0,1,N(B37))*INDEX(Data_Gear!$F:$F,MATCH(A37,Data_Gear!$A:$A,0)),""))
C38: =IF(A38="","",IFERROR(INDEX(Data_Gear!$B:$B,MATCH(A38,Data_Gear!$A:$A,0))&"","")) | D38: =IF(A38="","",IFERROR(N(INDEX(Data_Gear!$G:$G,MATCH(A38,Data_Gear!$A:$A,0))),0)) | E38: =IF(A38="",0,MAX(0,IF(N(B38)=0,1,N(B38))*N(D38)-IF(F38="Worn",IF(N(B38)=0,1,N(B38)),0))) | G38: =IF(A38="","",IFERROR(INDEX(Data_Gear!$H:$H,MATCH(A38,Data_Gear!$A:$A,0))&"","")) | H38: =IF(A38="","",IFERROR(INDEX(Data_Gear!$E:$E,MATCH(A38,Data_Gear!$A:$A,0))&"","")) | I38: =IF(A38="","",IFERROR(IF(N(B38)=0,1,N(B38))*INDEX(Data_Gear!$F:$F,MATCH(A38,Data_Gear!$A:$A,0)),""))
C39: =IF(A39="","",IFERROR(INDEX(Data_Gear!$B:$B,MATCH(A39,Data_Gear!$A:$A,0))&"","")) | D39: =IF(A39="","",IFERROR(N(INDEX(Data_Gear!$G:$G,MATCH(A39,Data_Gear!$A:$A,0))),0)) | E39: =IF(A39="",0,MAX(0,IF(N(B39)=0,1,N(B39))*N(D39)-IF(F39="Worn",IF(N(B39)=0,1,N(B39)),0))) | G39: =IF(A39="","",IFERROR(INDEX(Data_Gear!$H:$H,MATCH(A39,Data_Gear!$A:$A,0))&"","")) | H39: =IF(A39="","",IFERROR(INDEX(Data_Gear!$E:$E,MATCH(A39,Data_Gear!$A:$A,0))&"","")) | I39: =IF(A39="","",IFERROR(IF(N(B39)=0,1,N(B39))*INDEX(Data_Gear!$F:$F,MATCH(A39,Data_Gear!$A:$A,0)),""))
C40: =IF(A40="","",IFERROR(INDEX(Data_Gear!$B:$B,MATCH(A40,Data_Gear!$A:$A,0))&"","")) | D40: =IF(A40="","",IFERROR(N(INDEX(Data_Gear!$G:$G,MATCH(A40,Data_Gear!$A:$A,0))),0)) | E40: =IF(A40="",0,MAX(0,IF(N(B40)=0,1,N(B40))*N(D40)-IF(F40="Worn",IF(N(B40)=0,1,N(B40)),0))) | G40: =IF(A40="","",IFERROR(INDEX(Data_Gear!$H:$H,MATCH(A40,Data_Gear!$A:$A,0))&"","")) | H40: =IF(A40="","",IFERROR(INDEX(Data_Gear!$E:$E,MATCH(A40,Data_Gear!$A:$A,0))&"","")) | I40: =IF(A40="","",IFERROR(IF(N(B40)=0,1,N(B40))*INDEX(Data_Gear!$F:$F,MATCH(A40,Data_Gear!$A:$A,0)),""))
C41: =IF(A41="","",IFERROR(INDEX(Data_Gear!$B:$B,MATCH(A41,Data_Gear!$A:$A,0))&"","")) | D41: =IF(A41="","",IFERROR(N(INDEX(Data_Gear!$G:$G,MATCH(A41,Data_Gear!$A:$A,0))),0)) | E41: =IF(A41="",0,MAX(0,IF(N(B41)=0,1,N(B41))*N(D41)-IF(F41="Worn",IF(N(B41)=0,1,N(B41)),0))) | G41: =IF(A41="","",IFERROR(INDEX(Data_Gear!$H:$H,MATCH(A41,Data_Gear!$A:$A,0))&"","")) | H41: =IF(A41="","",IFERROR(INDEX(Data_Gear!$E:$E,MATCH(A41,Data_Gear!$A:$A,0))&"","")) | I41: =IF(A41="","",IFERROR(IF(N(B41)=0,1,N(B41))*INDEX(Data_Gear!$F:$F,MATCH(A41,Data_Gear!$A:$A,0)),""))
C42: =IF(A42="","",IFERROR(INDEX(Data_Gear!$B:$B,MATCH(A42,Data_Gear!$A:$A,0))&"","")) | D42: =IF(A42="","",IFERROR(N(INDEX(Data_Gear!$G:$G,MATCH(A42,Data_Gear!$A:$A,0))),0)) | E42: =IF(A42="",0,MAX(0,IF(N(B42)=0,1,N(B42))*N(D42)-IF(F42="Worn",IF(N(B42)=0,1,N(B42)),0))) | G42: =IF(A42="","",IFERROR(INDEX(Data_Gear!$H:$H,MATCH(A42,Data_Gear!$A:$A,0))&"","")) | H42: =IF(A42="","",IFERROR(INDEX(Data_Gear!$E:$E,MATCH(A42,Data_Gear!$A:$A,0))&"","")) | I42: =IF(A42="","",IFERROR(IF(N(B42)=0,1,N(B42))*INDEX(Data_Gear!$F:$F,MATCH(A42,Data_Gear!$A:$A,0)),""))
... C70: =IF(A70="","",IFERROR(INDEX(Data_Gear!$B:$B,MATCH(A70,Data_Gear!$A:$A,0))&"","")) | D70: =IF(A70="","",IFERROR(N(INDEX(Data_Gear!$G:$G,MATCH(A70,Data_Gear!$A:$A,0))),0)) | E70: =IF(A70="",0,MAX(0,IF(N(B70)=0,1,N(B70))*N(D70)-IF(F70="Worn",IF(N(B70)=0,1,N(B70)),0))) | G70: =IF(A70="","",IFERROR(INDEX(Data_Gear!$H:$H,MATCH(A70,Data_Gear!$A:$A,0))&"","")) | H70: =IF(A70="","",IFERROR(INDEX(Data_Gear!$E:$E,MATCH(A70,Data_Gear!$A:$A,0))&"","")) | I70: =IF(A70="","",IFERROR(IF(N(B70)=0,1,N(B70))*INDEX(Data_Gear!$F:$F,MATCH(A70,Data_Gear!$A:$A,0)),""))
A71: MONEY (1 GC = 20 shillings = 240 pennies · 200 coins = 1 Enc)
A72: Coin | B72: Amount | C72: Location | D72: Value (pennies) | E72: Enc
A73: Gold Crowns (GC) | B73: 0 | C73: Pouch | D73: =N(B73)*240 | E73: =INT(N(B73)/200)
A74: Silver Shillings (s) | B74: 0 | C74: Pouch | D74: =N(B74)*12 | E74: =INT(N(B74)/200)
A75: Brass Pennies (d) | B75: 0 | C75: Pouch | D75: =N(B75)*1 | E75: =INT(N(B75)/200)
A76: Total wealth | D76: =SUM(D73:D75) | F76: =INT(D76/240)&" GC "&INT(MOD(D76,240)/12)&"/"&MOD(D76,12) | I76: Trappings value | J76: =INT(SUM(I31:I70)/240)&" GC "&INT(MOD(SUM(I31:I70),240)/12)&"/"&MOD(SUM(I31:I70),12)
A78: ENCUMBRANCE BY LOCATION
A79: Location | B79: Enc | C79: Capacity | D79: Status
A80: Worn | B80: =SUMIF($I$6:$I$13,A80,$N$6:$N$13)+SUMIF($I$17:$I$24,A80,$N$17:$N$24)+SUMIF($F$31:$F$70,A80,$E$31:$E$70)+SUMIF($C$73:$C$75,A80,$E$73:$E$75) | D80: =IF(C80="","",IF(B80>C80,"Over capacity",""))
A81: Carried | B81: =SUMIF($I$6:$I$13,A81,$N$6:$N$13)+SUMIF($I$17:$I$24,A81,$N$17:$N$24)+SUMIF($F$31:$F$70,A81,$E$31:$E$70)+SUMIF($C$73:$C$75,A81,$E$73:$E$75) | D81: =IF(C81="","",IF(B81>C81,"Over capacity",""))
A82: Backpack | B82: =SUMIF($I$6:$I$13,A82,$N$6:$N$13)+SUMIF($I$17:$I$24,A82,$N$17:$N$24)+SUMIF($F$31:$F$70,A82,$E$31:$E$70)+SUMIF($C$73:$C$75,A82,$E$73:$E$75) | C82: 4 | D82: =IF(C82="","",IF(B82>C82,"Over capacity",""))
A83: Sling Bag | B83: =SUMIF($I$6:$I$13,A83,$N$6:$N$13)+SUMIF($I$17:$I$24,A83,$N$17:$N$24)+SUMIF($F$31:$F$70,A83,$E$31:$E$70)+SUMIF($C$73:$C$75,A83,$E$73:$E$75) | C83: 2 | D83: =IF(C83="","",IF(B83>C83,"Over capacity",""))
A84: Pouch | B84: =SUMIF($I$6:$I$13,A84,$N$6:$N$13)+SUMIF($I$17:$I$24,A84,$N$17:$N$24)+SUMIF($F$31:$F$70,A84,$E$31:$E$70)+SUMIF($C$73:$C$75,A84,$E$73:$E$75) | C84: 1 | D84: =IF(C84="","",IF(B84>C84,"Over capacity",""))
A85: Sack | B85: =SUMIF($I$6:$I$13,A85,$N$6:$N$13)+SUMIF($I$17:$I$24,A85,$N$17:$N$24)+SUMIF($F$31:$F$70,A85,$E$31:$E$70)+SUMIF($C$73:$C$75,A85,$E$73:$E$75) | C85: 4 | D85: =IF(C85="","",IF(B85>C85,"Over capacity",""))
A86: Large Sack | B86: =SUMIF($I$6:$I$13,A86,$N$6:$N$13)+SUMIF($I$17:$I$24,A86,$N$17:$N$24)+SUMIF($F$31:$F$70,A86,$E$31:$E$70)+SUMIF($C$73:$C$75,A86,$E$73:$E$75) | C86: 6 | D86: =IF(C86="","",IF(B86>C86,"Over capacity",""))
A87: Saddlebags | B87: =SUMIF($I$6:$I$13,A87,$N$6:$N$13)+SUMIF($I$17:$I$24,A87,$N$17:$N$24)+SUMIF($F$31:$F$70,A87,$E$31:$E$70)+SUMIF($C$73:$C$75,A87,$E$73:$E$75) | C87: 8 | D87: =IF(C87="","",IF(B87>C87,"Over capacity",""))
A88: Mount / Cart | B88: =SUMIF($I$6:$I$13,A88,$N$6:$N$13)+SUMIF($I$17:$I$24,A88,$N$17:$N$24)+SUMIF($F$31:$F$70,A88,$E$31:$E$70)+SUMIF($C$73:$C$75,A88,$E$73:$E$75) | D88: =IF(C88="","",IF(B88>C88,"Over capacity",""))
A89: Stored | B89: =SUMIF($I$6:$I$13,A89,$N$6:$N$13)+SUMIF($I$17:$I$24,A89,$N$17:$N$24)+SUMIF($F$31:$F$70,A89,$E$31:$E$70)+SUMIF($C$73:$C$75,A89,$E$73:$E$75) | D89: =IF(C89="","",IF(B89>C89,"Over capacity",""))
A90: ON YOUR PERSON (Worn + Carried) | B90: =B80+B81 | C90: =Character!$P$16 | D90: =IF(N(C90)=0,"",IF(B90>C90,"OVERBURDENED","OK")) | E90: Capacity of containers comes from the rulebook (Carries).

Sheet Spells & Prayers
A1: SPELLS & PRAYERS
A2: XP cost follows the number already known: 1st–5th spell 100 XP (petty 50), 6th–10th 200 (petty 100) … up to 500 (petty 250). Mark spells learnt at character creation as free.
A3: Arcane lore | D3: Channelling | E3: =IFERROR(INDEX(Character!$G$27:$G$77,MATCH("Channelling*",Character!$A$27:$A$77,0)),"—") | F3: Language (Magick) | G3: =IFERROR(INDEX(Character!$G$27:$G$77,MATCH("Language (Magick)",Character!$A$27:$A$77,0)),"—") | I3: Deity | L3: Pray | M3: =IFERROR(INDEX(Character!$G$27:$G$77,MATCH("Pray",Character!$A$27:$A$77,0)),"—")
A4: XP spent (spells & miracles) | B4: =SUM(H9:H38)+SUM(H51:H62)
A7: SPELLS (Petty, Arcane and Lore spells)
A8: Name | B8: Lore / God | C8: CN | D8: Range | E8: Target | F8: Duration | G8: Learnt free? | H8: XP cost | I8: Description | M8: Page
B9: =IF(A9="","",IFERROR(INDEX(Data_Spells!$C:$C,MATCH(A9,Data_Spells!$A:$A,0))&"","")) | C9: =IF(A9="","",IFERROR(INDEX(Data_Spells!$D:$D,MATCH(A9,Data_Spells!$A:$A,0))&"","")) | D9: =IF(A9="","",IFERROR(INDEX(Data_Spells!$E:$E,MATCH(A9,Data_Spells!$A:$A,0))&"","")) | E9: =IF(A9="","",IFERROR(INDEX(Data_Spells!$F:$F,MATCH(A9,Data_Spells!$A:$A,0))&"","")) | F9: =IF(A9="","",IFERROR(INDEX(Data_Spells!$G:$G,MATCH(A9,Data_Spells!$A:$A,0))&"","")) | H9: =IF(A9="","",IF(G9="Yes",0,IF(N9="P",50,100)*MIN(5,INT((COUNTIF($N$9:N9,N9)-1)/5)+1))) | I9: =IF(A9="","",IFERROR(INDEX(Data_Spells!$H:$H,MATCH(A9,Data_Spells!$A:$A,0))&"","")) | M9: =IF(A9="","",IFERROR(INDEX(Data_Spells!$I:$I,MATCH(A9,Data_Spells!$A:$A,0))&"","")) | N9: =IF(A9="","",IF(B9="Petty","P","L"))
B10: =IF(A10="","",IFERROR(INDEX(Data_Spells!$C:$C,MATCH(A10,Data_Spells!$A:$A,0))&"","")) | C10: =IF(A10="","",IFERROR(INDEX(Data_Spells!$D:$D,MATCH(A10,Data_Spells!$A:$A,0))&"","")) | D10: =IF(A10="","",IFERROR(INDEX(Data_Spells!$E:$E,MATCH(A10,Data_Spells!$A:$A,0))&"","")) | E10: =IF(A10="","",IFERROR(INDEX(Data_Spells!$F:$F,MATCH(A10,Data_Spells!$A:$A,0))&"","")) | F10: =IF(A10="","",IFERROR(INDEX(Data_Spells!$G:$G,MATCH(A10,Data_Spells!$A:$A,0))&"","")) | H10: =IF(A10="","",IF(G10="Yes",0,IF(N10="P",50,100)*MIN(5,INT((COUNTIF($N$9:N10,N10)-1)/5)+1))) | I10: =IF(A10="","",IFERROR(INDEX(Data_Spells!$H:$H,MATCH(A10,Data_Spells!$A:$A,0))&"","")) | M10: =IF(A10="","",IFERROR(INDEX(Data_Spells!$I:$I,MATCH(A10,Data_Spells!$A:$A,0))&"","")) | N10: =IF(A10="","",IF(B10="Petty","P","L"))
B11: =IF(A11="","",IFERROR(INDEX(Data_Spells!$C:$C,MATCH(A11,Data_Spells!$A:$A,0))&"","")) | C11: =IF(A11="","",IFERROR(INDEX(Data_Spells!$D:$D,MATCH(A11,Data_Spells!$A:$A,0))&"","")) | D11: =IF(A11="","",IFERROR(INDEX(Data_Spells!$E:$E,MATCH(A11,Data_Spells!$A:$A,0))&"","")) | E11: =IF(A11="","",IFERROR(INDEX(Data_Spells!$F:$F,MATCH(A11,Data_Spells!$A:$A,0))&"","")) | F11: =IF(A11="","",IFERROR(INDEX(Data_Spells!$G:$G,MATCH(A11,Data_Spells!$A:$A,0))&"","")) | H11: =IF(A11="","",IF(G11="Yes",0,IF(N11="P",50,100)*MIN(5,INT((COUNTIF($N$9:N11,N11)-1)/5)+1))) | I11: =IF(A11="","",IFERROR(INDEX(Data_Spells!$H:$H,MATCH(A11,Data_Spells!$A:$A,0))&"","")) | M11: =IF(A11="","",IFERROR(INDEX(Data_Spells!$I:$I,MATCH(A11,Data_Spells!$A:$A,0))&"","")) | N11: =IF(A11="","",IF(B11="Petty","P","L"))
B12: =IF(A12="","",IFERROR(INDEX(Data_Spells!$C:$C,MATCH(A12,Data_Spells!$A:$A,0))&"","")) | C12: =IF(A12="","",IFERROR(INDEX(Data_Spells!$D:$D,MATCH(A12,Data_Spells!$A:$A,0))&"","")) | D12: =IF(A12="","",IFERROR(INDEX(Data_Spells!$E:$E,MATCH(A12,Data_Spells!$A:$A,0))&"","")) | E12: =IF(A12="","",IFERROR(INDEX(Data_Spells!$F:$F,MATCH(A12,Data_Spells!$A:$A,0))&"","")) | F12: =IF(A12="","",IFERROR(INDEX(Data_Spells!$G:$G,MATCH(A12,Data_Spells!$A:$A,0))&"","")) | H12: =IF(A12="","",IF(G12="Yes",0,IF(N12="P",50,100)*MIN(5,INT((COUNTIF($N$9:N12,N12)-1)/5)+1))) | I12: =IF(A12="","",IFERROR(INDEX(Data_Spells!$H:$H,MATCH(A12,Data_Spells!$A:$A,0))&"","")) | M12: =IF(A12="","",IFERROR(INDEX(Data_Spells!$I:$I,MATCH(A12,Data_Spells!$A:$A,0))&"","")) | N12: =IF(A12="","",IF(B12="Petty","P","L"))
B13: =IF(A13="","",IFERROR(INDEX(Data_Spells!$C:$C,MATCH(A13,Data_Spells!$A:$A,0))&"","")) | C13: =IF(A13="","",IFERROR(INDEX(Data_Spells!$D:$D,MATCH(A13,Data_Spells!$A:$A,0))&"","")) | D13: =IF(A13="","",IFERROR(INDEX(Data_Spells!$E:$E,MATCH(A13,Data_Spells!$A:$A,0))&"","")) | E13: =IF(A13="","",IFERROR(INDEX(Data_Spells!$F:$F,MATCH(A13,Data_Spells!$A:$A,0))&"","")) | F13: =IF(A13="","",IFERROR(INDEX(Data_Spells!$G:$G,MATCH(A13,Data_Spells!$A:$A,0))&"","")) | H13: =IF(A13="","",IF(G13="Yes",0,IF(N13="P",50,100)*MIN(5,INT((COUNTIF($N$9:N13,N13)-1)/5)+1))) | I13: =IF(A13="","",IFERROR(INDEX(Data_Spells!$H:$H,MATCH(A13,Data_Spells!$A:$A,0))&"","")) | M13: =IF(A13="","",IFERROR(INDEX(Data_Spells!$I:$I,MATCH(A13,Data_Spells!$A:$A,0))&"","")) | N13: =IF(A13="","",IF(B13="Petty","P","L"))
B14: =IF(A14="","",IFERROR(INDEX(Data_Spells!$C:$C,MATCH(A14,Data_Spells!$A:$A,0))&"","")) | C14: =IF(A14="","",IFERROR(INDEX(Data_Spells!$D:$D,MATCH(A14,Data_Spells!$A:$A,0))&"","")) | D14: =IF(A14="","",IFERROR(INDEX(Data_Spells!$E:$E,MATCH(A14,Data_Spells!$A:$A,0))&"","")) | E14: =IF(A14="","",IFERROR(INDEX(Data_Spells!$F:$F,MATCH(A14,Data_Spells!$A:$A,0))&"","")) | F14: =IF(A14="","",IFERROR(INDEX(Data_Spells!$G:$G,MATCH(A14,Data_Spells!$A:$A,0))&"","")) | H14: =IF(A14="","",IF(G14="Yes",0,IF(N14="P",50,100)*MIN(5,INT((COUNTIF($N$9:N14,N14)-1)/5)+1))) | I14: =IF(A14="","",IFERROR(INDEX(Data_Spells!$H:$H,MATCH(A14,Data_Spells!$A:$A,0))&"","")) | M14: =IF(A14="","",IFERROR(INDEX(Data_Spells!$I:$I,MATCH(A14,Data_Spells!$A:$A,0))&"","")) | N14: =IF(A14="","",IF(B14="Petty","P","L"))
B15: =IF(A15="","",IFERROR(INDEX(Data_Spells!$C:$C,MATCH(A15,Data_Spells!$A:$A,0))&"","")) | C15: =IF(A15="","",IFERROR(INDEX(Data_Spells!$D:$D,MATCH(A15,Data_Spells!$A:$A,0))&"","")) | D15: =IF(A15="","",IFERROR(INDEX(Data_Spells!$E:$E,MATCH(A15,Data_Spells!$A:$A,0))&"","")) | E15: =IF(A15="","",IFERROR(INDEX(Data_Spells!$F:$F,MATCH(A15,Data_Spells!$A:$A,0))&"","")) | F15: =IF(A15="","",IFERROR(INDEX(Data_Spells!$G:$G,MATCH(A15,Data_Spells!$A:$A,0))&"","")) | H15: =IF(A15="","",IF(G15="Yes",0,IF(N15="P",50,100)*MIN(5,INT((COUNTIF($N$9:N15,N15)-1)/5)+1))) | I15: =IF(A15="","",IFERROR(INDEX(Data_Spells!$H:$H,MATCH(A15,Data_Spells!$A:$A,0))&"","")) | M15: =IF(A15="","",IFERROR(INDEX(Data_Spells!$I:$I,MATCH(A15,Data_Spells!$A:$A,0))&"","")) | N15: =IF(A15="","",IF(B15="Petty","P","L"))
B16: =IF(A16="","",IFERROR(INDEX(Data_Spells!$C:$C,MATCH(A16,Data_Spells!$A:$A,0))&"","")) | C16: =IF(A16="","",IFERROR(INDEX(Data_Spells!$D:$D,MATCH(A16,Data_Spells!$A:$A,0))&"","")) | D16: =IF(A16="","",IFERROR(INDEX(Data_Spells!$E:$E,MATCH(A16,Data_Spells!$A:$A,0))&"","")) | E16: =IF(A16="","",IFERROR(INDEX(Data_Spells!$F:$F,MATCH(A16,Data_Spells!$A:$A,0))&"","")) | F16: =IF(A16="","",IFERROR(INDEX(Data_Spells!$G:$G,MATCH(A16,Data_Spells!$A:$A,0))&"","")) | H16: =IF(A16="","",IF(G16="Yes",0,IF(N16="P",50,100)*MIN(5,INT((COUNTIF($N$9:N16,N16)-1)/5)+1))) | I16: =IF(A16="","",IFERROR(INDEX(Data_Spells!$H:$H,MATCH(A16,Data_Spells!$A:$A,0))&"","")) | M16: =IF(A16="","",IFERROR(INDEX(Data_Spells!$I:$I,MATCH(A16,Data_Spells!$A:$A,0))&"","")) | N16: =IF(A16="","",IF(B16="Petty","P","L"))
B17: =IF(A17="","",IFERROR(INDEX(Data_Spells!$C:$C,MATCH(A17,Data_Spells!$A:$A,0))&"","")) | C17: =IF(A17="","",IFERROR(INDEX(Data_Spells!$D:$D,MATCH(A17,Data_Spells!$A:$A,0))&"","")) | D17: =IF(A17="","",IFERROR(INDEX(Data_Spells!$E:$E,MATCH(A17,Data_Spells!$A:$A,0))&"","")) | E17: =IF(A17="","",IFERROR(INDEX(Data_Spells!$F:$F,MATCH(A17,Data_Spells!$A:$A,0))&"","")) | F17: =IF(A17="","",IFERROR(INDEX(Data_Spells!$G:$G,MATCH(A17,Data_Spells!$A:$A,0))&"","")) | H17: =IF(A17="","",IF(G17="Yes",0,IF(N17="P",50,100)*MIN(5,INT((COUNTIF($N$9:N17,N17)-1)/5)+1))) | I17: =IF(A17="","",IFERROR(INDEX(Data_Spells!$H:$H,MATCH(A17,Data_Spells!$A:$A,0))&"","")) | M17: =IF(A17="","",IFERROR(INDEX(Data_Spells!$I:$I,MATCH(A17,Data_Spells!$A:$A,0))&"","")) | N17: =IF(A17="","",IF(B17="Petty","P","L"))
B18: =IF(A18="","",IFERROR(INDEX(Data_Spells!$C:$C,MATCH(A18,Data_Spells!$A:$A,0))&"","")) | C18: =IF(A18="","",IFERROR(INDEX(Data_Spells!$D:$D,MATCH(A18,Data_Spells!$A:$A,0))&"","")) | D18: =IF(A18="","",IFERROR(INDEX(Data_Spells!$E:$E,MATCH(A18,Data_Spells!$A:$A,0))&"","")) | E18: =IF(A18="","",IFERROR(INDEX(Data_Spells!$F:$F,MATCH(A18,Data_Spells!$A:$A,0))&"","")) | F18: =IF(A18="","",IFERROR(INDEX(Data_Spells!$G:$G,MATCH(A18,Data_Spells!$A:$A,0))&"","")) | H18: =IF(A18="","",IF(G18="Yes",0,IF(N18="P",50,100)*MIN(5,INT((COUNTIF($N$9:N18,N18)-1)/5)+1))) | I18: =IF(A18="","",IFERROR(INDEX(Data_Spells!$H:$H,MATCH(A18,Data_Spells!$A:$A,0))&"","")) | M18: =IF(A18="","",IFERROR(INDEX(Data_Spells!$I:$I,MATCH(A18,Data_Spells!$A:$A,0))&"","")) | N18: =IF(A18="","",IF(B18="Petty","P","L"))
B19: =IF(A19="","",IFERROR(INDEX(Data_Spells!$C:$C,MATCH(A19,Data_Spells!$A:$A,0))&"","")) | C19: =IF(A19="","",IFERROR(INDEX(Data_Spells!$D:$D,MATCH(A19,Data_Spells!$A:$A,0))&"","")) | D19: =IF(A19="","",IFERROR(INDEX(Data_Spells!$E:$E,MATCH(A19,Data_Spells!$A:$A,0))&"","")) | E19: =IF(A19="","",IFERROR(INDEX(Data_Spells!$F:$F,MATCH(A19,Data_Spells!$A:$A,0))&"","")) | F19: =IF(A19="","",IFERROR(INDEX(Data_Spells!$G:$G,MATCH(A19,Data_Spells!$A:$A,0))&"","")) | H19: =IF(A19="","",IF(G19="Yes",0,IF(N19="P",50,100)*MIN(5,INT((COUNTIF($N$9:N19,N19)-1)/5)+1))) | I19: =IF(A19="","",IFERROR(INDEX(Data_Spells!$H:$H,MATCH(A19,Data_Spells!$A:$A,0))&"","")) | M19: =IF(A19="","",IFERROR(INDEX(Data_Spells!$I:$I,MATCH(A19,Data_Spells!$A:$A,0))&"","")) | N19: =IF(A19="","",IF(B19="Petty","P","L"))
B20: =IF(A20="","",IFERROR(INDEX(Data_Spells!$C:$C,MATCH(A20,Data_Spells!$A:$A,0))&"","")) | C20: =IF(A20="","",IFERROR(INDEX(Data_Spells!$D:$D,MATCH(A20,Data_Spells!$A:$A,0))&"","")) | D20: =IF(A20="","",IFERROR(INDEX(Data_Spells!$E:$E,MATCH(A20,Data_Spells!$A:$A,0))&"","")) | E20: =IF(A20="","",IFERROR(INDEX(Data_Spells!$F:$F,MATCH(A20,Data_Spells!$A:$A,0))&"","")) | F20: =IF(A20="","",IFERROR(INDEX(Data_Spells!$G:$G,MATCH(A20,Data_Spells!$A:$A,0))&"","")) | H20: =IF(A20="","",IF(G20="Yes",0,IF(N20="P",50,100)*MIN(5,INT((COUNTIF($N$9:N20,N20)-1)/5)+1))) | I20: =IF(A20="","",IFERROR(INDEX(Data_Spells!$H:$H,MATCH(A20,Data_Spells!$A:$A,0))&"","")) | M20: =IF(A20="","",IFERROR(INDEX(Data_Spells!$I:$I,MATCH(A20,Data_Spells!$A:$A,0))&"","")) | N20: =IF(A20="","",IF(B20="Petty","P","L"))
... B38: =IF(A38="","",IFERROR(INDEX(Data_Spells!$C:$C,MATCH(A38,Data_Spells!$A:$A,0))&"","")) | C38: =IF(A38="","",IFERROR(INDEX(Data_Spells!$D:$D,MATCH(A38,Data_Spells!$A:$A,0))&"","")) | D38: =IF(A38="","",IFERROR(INDEX(Data_Spells!$E:$E,MATCH(A38,Data_Spells!$A:$A,0))&"","")) | E38: =IF(A38="","",IFERROR(INDEX(Data_Spells!$F:$F,MATCH(A38,Data_Spells!$A:$A,0))&"","")) | F38: =IF(A38="","",IFERROR(INDEX(Data_Spells!$G:$G,MATCH(A38,Data_Spells!$A:$A,0))&"","")) | H38: =IF(A38="","",IF(G38="Yes",0,IF(N38="P",50,100)*MIN(5,INT((COUNTIF($N$9:N38,N38)-1)/5)+1))) | I38: =IF(A38="","",IFERROR(INDEX(Data_Spells!$H:$H,MATCH(A38,Data_Spells!$A:$A,0))&"","")) | M38: =IF(A38="","",IFERROR(INDEX(Data_Spells!$I:$I,MATCH(A38,Data_Spells!$A:$A,0))&"","")) | N38: =IF(A38="","",IF(B38="Petty","P","L"))
A40: BLESSINGS (granted by the Bless talent)
A41: Name | B41: Lore / God | C41: CN | D41: Range | E41: Target | F41: Duration | G41: Learnt free? | H41: XP cost | I41: Description | M41: Page
B42: =IF(A42="","",IFERROR(INDEX(Data_Spells!$C:$C,MATCH(A42,Data_Spells!$A:$A,0))&"","")) | C42: =IF(A42="","",IFERROR(INDEX(Data_Spells!$D:$D,MATCH(A42,Data_Spells!$A:$A,0))&"","")) | D42: =IF(A42="","",IFERROR(INDEX(Data_Spells!$E:$E,MATCH(A42,Data_Spells!$A:$A,0))&"","")) | E42: =IF(A42="","",IFERROR(INDEX(Data_Spells!$F:$F,MATCH(A42,Data_Spells!$A:$A,0))&"","")) | F42: =IF(A42="","",IFERROR(INDEX(Data_Spells!$G:$G,MATCH(A42,Data_Spells!$A:$A,0))&"","")) | I42: =IF(A42="","",IFERROR(INDEX(Data_Spells!$H:$H,MATCH(A42,Data_Spells!$A:$A,0))&"","")) | M42: =IF(A42="","",IFERROR(INDEX(Data_Spells!$I:$I,MATCH(A42,Data_Spells!$A:$A,0))&"",""))
B43: =IF(A43="","",IFERROR(INDEX(Data_Spells!$C:$C,MATCH(A43,Data_Spells!$A:$A,0))&"","")) | C43: =IF(A43="","",IFERROR(INDEX(Data_Spells!$D:$D,MATCH(A43,Data_Spells!$A:$A,0))&"","")) | D43: =IF(A43="","",IFERROR(INDEX(Data_Spells!$E:$E,MATCH(A43,Data_Spells!$A:$A,0))&"","")) | E43: =IF(A43="","",IFERROR(INDEX(Data_Spells!$F:$F,MATCH(A43,Data_Spells!$A:$A,0))&"","")) | F43: =IF(A43="","",IFERROR(INDEX(Data_Spells!$G:$G,MATCH(A43,Data_Spells!$A:$A,0))&"","")) | I43: =IF(A43="","",IFERROR(INDEX(Data_Spells!$H:$H,MATCH(A43,Data_Spells!$A:$A,0))&"","")) | M43: =IF(A43="","",IFERROR(INDEX(Data_Spells!$I:$I,MATCH(A43,Data_Spells!$A:$A,0))&"",""))
B44: =IF(A44="","",IFERROR(INDEX(Data_Spells!$C:$C,MATCH(A44,Data_Spells!$A:$A,0))&"","")) | C44: =IF(A44="","",IFERROR(INDEX(Data_Spells!$D:$D,MATCH(A44,Data_Spells!$A:$A,0))&"","")) | D44: =IF(A44="","",IFERROR(INDEX(Data_Spells!$E:$E,MATCH(A44,Data_Spells!$A:$A,0))&"","")) | E44: =IF(A44="","",IFERROR(INDEX(Data_Spells!$F:$F,MATCH(A44,Data_Spells!$A:$A,0))&"","")) | F44: =IF(A44="","",IFERROR(INDEX(Data_Spells!$G:$G,MATCH(A44,Data_Spells!$A:$A,0))&"","")) | I44: =IF(A44="","",IFERROR(INDEX(Data_Spells!$H:$H,MATCH(A44,Data_Spells!$A:$A,0))&"","")) | M44: =IF(A44="","",IFERROR(INDEX(Data_Spells!$I:$I,MATCH(A44,Data_Spells!$A:$A,0))&"",""))
B45: =IF(A45="","",IFERROR(INDEX(Data_Spells!$C:$C,MATCH(A45,Data_Spells!$A:$A,0))&"","")) | C45: =IF(A45="","",IFERROR(INDEX(Data_Spells!$D:$D,MATCH(A45,Data_Spells!$A:$A,0))&"","")) | D45: =IF(A45="","",IFERROR(INDEX(Data_Spells!$E:$E,MATCH(A45,Data_Spells!$A:$A,0))&"","")) | E45: =IF(A45="","",IFERROR(INDEX(Data_Spells!$F:$F,MATCH(A45,Data_Spells!$A:$A,0))&"","")) | F45: =IF(A45="","",IFERROR(INDEX(Data_Spells!$G:$G,MATCH(A45,Data_Spells!$A:$A,0))&"","")) | I45: =IF(A45="","",IFERROR(INDEX(Data_Spells!$H:$H,MATCH(A45,Data_Spells!$A:$A,0))&"","")) | M45: =IF(A45="","",IFERROR(INDEX(Data_Spells!$I:$I,MATCH(A45,Data_Spells!$A:$A,0))&"",""))
B46: =IF(A46="","",IFERROR(INDEX(Data_Spells!$C:$C,MATCH(A46,Data_Spells!$A:$A,0))&"","")) | C46: =IF(A46="","",IFERROR(INDEX(Data_Spells!$D:$D,MATCH(A46,Data_Spells!$A:$A,0))&"","")) | D46: =IF(A46="","",IFERROR(INDEX(Data_Spells!$E:$E,MATCH(A46,Data_Spells!$A:$A,0))&"","")) | E46: =IF(A46="","",IFERROR(INDEX(Data_Spells!$F:$F,MATCH(A46,Data_Spells!$A:$A,0))&"","")) | F46: =IF(A46="","",IFERROR(INDEX(Data_Spells!$G:$G,MATCH(A46,Data_Spells!$A:$A,0))&"","")) | I46: =IF(A46="","",IFERROR(INDEX(Data_Spells!$H:$H,MATCH(A46,Data_Spells!$A:$A,0))&"","")) | M46: =IF(A46="","",IFERROR(INDEX(Data_Spells!$I:$I,MATCH(A46,Data_Spells!$A:$A,0))&"",""))
B47: =IF(A47="","",IFERROR(INDEX(Data_Spells!$C:$C,MATCH(A47,Data_Spells!$A:$A,0))&"","")) | C47: =IF(A47="","",IFERROR(INDEX(Data_Spells!$D:$D,MATCH(A47,Data_Spells!$A:$A,0))&"","")) | D47: =IF(A47="","",IFERROR(INDEX(Data_Spells!$E:$E,MATCH(A47,Data_Spells!$A:$A,0))&"","")) | E47: =IF(A47="","",IFERROR(INDEX(Data_Spells!$F:$F,MATCH(A47,Data_Spells!$A:$A,0))&"","")) | F47: =IF(A47="","",IFERROR(INDEX(Data_Spells!$G:$G,MATCH(A47,Data_Spells!$A:$A,0))&"","")) | I47: =IF(A47="","",IFERROR(INDEX(Data_Spells!$H:$H,MATCH(A47,Data_Spells!$A:$A,0))&"","")) | M47: =IF(A47="","",IFERROR(INDEX(Data_Spells!$I:$I,MATCH(A47,Data_Spells!$A:$A,0))&"",""))
A49: MIRACLES (granted by the Invoke talent)
A50: Name | B50: Lore / God | C50: CN | D50: Range | E50: Target | F50: Duration | G50: Learnt free? | H50: XP cost | I50: Description | M50: Page
B51: =IF(A51="","",IFERROR(INDEX(Data_Spells!$C:$C,MATCH(A51,Data_Spells!$A:$A,0))&"","")) | C51: =IF(A51="","",IFERROR(INDEX(Data_Spells!$D:$D,MATCH(A51,Data_Spells!$A:$A,0))&"","")) | D51: =IF(A51="","",IFERROR(INDEX(Data_Spells!$E:$E,MATCH(A51,Data_Spells!$A:$A,0))&"","")) | E51: =IF(A51="","",IFERROR(INDEX(Data_Spells!$F:$F,MATCH(A51,Data_Spells!$A:$A,0))&"","")) | F51: =IF(A51="","",IFERROR(INDEX(Data_Spells!$G:$G,MATCH(A51,Data_Spells!$A:$A,0))&"","")) | H51: =IF(A51="","",IF(G51="Yes",0,IF(N51="P",50,100)*MIN(5,INT((COUNTIF($N$51:N51,N51)-1)/5)+1))) | I51: =IF(A51="","",IFERROR(INDEX(Data_Spells!$H:$H,MATCH(A51,Data_Spells!$A:$A,0))&"","")) | M51: =IF(A51="","",IFERROR(INDEX(Data_Spells!$I:$I,MATCH(A51,Data_Spells!$A:$A,0))&"","")) | N51: =IF(A51="","","M")
B52: =IF(A52="","",IFERROR(INDEX(Data_Spells!$C:$C,MATCH(A52,Data_Spells!$A:$A,0))&"","")) | C52: =IF(A52="","",IFERROR(INDEX(Data_Spells!$D:$D,MATCH(A52,Data_Spells!$A:$A,0))&"","")) | D52: =IF(A52="","",IFERROR(INDEX(Data_Spells!$E:$E,MATCH(A52,Data_Spells!$A:$A,0))&"","")) | E52: =IF(A52="","",IFERROR(INDEX(Data_Spells!$F:$F,MATCH(A52,Data_Spells!$A:$A,0))&"","")) | F52: =IF(A52="","",IFERROR(INDEX(Data_Spells!$G:$G,MATCH(A52,Data_Spells!$A:$A,0))&"","")) | H52: =IF(A52="","",IF(G52="Yes",0,IF(N52="P",50,100)*MIN(5,INT((COUNTIF($N$51:N52,N52)-1)/5)+1))) | I52: =IF(A52="","",IFERROR(INDEX(Data_Spells!$H:$H,MATCH(A52,Data_Spells!$A:$A,0))&"","")) | M52: =IF(A52="","",IFERROR(INDEX(Data_Spells!$I:$I,MATCH(A52,Data_Spells!$A:$A,0))&"","")) | N52: =IF(A52="","","M")
B53: =IF(A53="","",IFERROR(INDEX(Data_Spells!$C:$C,MATCH(A53,Data_Spells!$A:$A,0))&"","")) | C53: =IF(A53="","",IFERROR(INDEX(Data_Spells!$D:$D,MATCH(A53,Data_Spells!$A:$A,0))&"","")) | D53: =IF(A53="","",IFERROR(INDEX(Data_Spells!$E:$E,MATCH(A53,Data_Spells!$A:$A,0))&"","")) | E53: =IF(A53="","",IFERROR(INDEX(Data_Spells!$F:$F,MATCH(A53,Data_Spells!$A:$A,0))&"","")) | F53: =IF(A53="","",IFERROR(INDEX(Data_Spells!$G:$G,MATCH(A53,Data_Spells!$A:$A,0))&"","")) | H53: =IF(A53="","",IF(G53="Yes",0,IF(N53="P",50,100)*MIN(5,INT((COUNTIF($N$51:N53,N53)-1)/5)+1))) | I53: =IF(A53="","",IFERROR(INDEX(Data_Spells!$H:$H,MATCH(A53,Data_Spells!$A:$A,0))&"","")) | M53: =IF(A53="","",IFERROR(INDEX(Data_Spells!$I:$I,MATCH(A53,Data_Spells!$A:$A,0))&"","")) | N53: =IF(A53="","","M")
B54: =IF(A54="","",IFERROR(INDEX(Data_Spells!$C:$C,MATCH(A54,Data_Spells!$A:$A,0))&"","")) | C54: =IF(A54="","",IFERROR(INDEX(Data_Spells!$D:$D,MATCH(A54,Data_Spells!$A:$A,0))&"","")) | D54: =IF(A54="","",IFERROR(INDEX(Data_Spells!$E:$E,MATCH(A54,Data_Spells!$A:$A,0))&"","")) | E54: =IF(A54="","",IFERROR(INDEX(Data_Spells!$F:$F,MATCH(A54,Data_Spells!$A:$A,0))&"","")) | F54: =IF(A54="","",IFERROR(INDEX(Data_Spells!$G:$G,MATCH(A54,Data_Spells!$A:$A,0))&"","")) | H54: =IF(A54="","",IF(G54="Yes",0,IF(N54="P",50,100)*MIN(5,INT((COUNTIF($N$51:N54,N54)-1)/5)+1))) | I54: =IF(A54="","",IFERROR(INDEX(Data_Spells!$H:$H,MATCH(A54,Data_Spells!$A:$A,0))&"","")) | M54: =IF(A54="","",IFERROR(INDEX(Data_Spells!$I:$I,MATCH(A54,Data_Spells!$A:$A,0))&"","")) | N54: =IF(A54="","","M")
B55: =IF(A55="","",IFERROR(INDEX(Data_Spells!$C:$C,MATCH(A55,Data_Spells!$A:$A,0))&"","")) | C55: =IF(A55="","",IFERROR(INDEX(Data_Spells!$D:$D,MATCH(A55,Data_Spells!$A:$A,0))&"","")) | D55: =IF(A55="","",IFERROR(INDEX(Data_Spells!$E:$E,MATCH(A55,Data_Spells!$A:$A,0))&"","")) | E55: =IF(A55="","",IFERROR(INDEX(Data_Spells!$F:$F,MATCH(A55,Data_Spells!$A:$A,0))&"","")) | F55: =IF(A55="","",IFERROR(INDEX(Data_Spells!$G:$G,MATCH(A55,Data_Spells!$A:$A,0))&"","")) | H55: =IF(A55="","",IF(G55="Yes",0,IF(N55="P",50,100)*MIN(5,INT((COUNTIF($N$51:N55,N55)-1)/5)+1))) | I55: =IF(A55="","",IFERROR(INDEX(Data_Spells!$H:$H,MATCH(A55,Data_Spells!$A:$A,0))&"","")) | M55: =IF(A55="","",IFERROR(INDEX(Data_Spells!$I:$I,MATCH(A55,Data_Spells!$A:$A,0))&"","")) | N55: =IF(A55="","","M")
B56: =IF(A56="","",IFERROR(INDEX(Data_Spells!$C:$C,MATCH(A56,Data_Spells!$A:$A,0))&"","")) | C56: =IF(A56="","",IFERROR(INDEX(Data_Spells!$D:$D,MATCH(A56,Data_Spells!$A:$A,0))&"","")) | D56: =IF(A56="","",IFERROR(INDEX(Data_Spells!$E:$E,MATCH(A56,Data_Spells!$A:$A,0))&"","")) | E56: =IF(A56="","",IFERROR(INDEX(Data_Spells!$F:$F,MATCH(A56,Data_Spells!$A:$A,0))&"","")) | F56: =IF(A56="","",IFERROR(INDEX(Data_Spells!$G:$G,MATCH(A56,Data_Spells!$A:$A,0))&"","")) | H56: =IF(A56="","",IF(G56="Yes",0,IF(N56="P",50,100)*MIN(5,INT((COUNTIF($N$51:N56,N56)-1)/5)+1))) | I56: =IF(A56="","",IFERROR(INDEX(Data_Spells!$H:$H,MATCH(A56,Data_Spells!$A:$A,0))&"","")) | M56: =IF(A56="","",IFERROR(INDEX(Data_Spells!$I:$I,MATCH(A56,Data_Spells!$A:$A,0))&"","")) | N56: =IF(A56="","","M")
B57: =IF(A57="","",IFERROR(INDEX(Data_Spells!$C:$C,MATCH(A57,Data_Spells!$A:$A,0))&"","")) | C57: =IF(A57="","",IFERROR(INDEX(Data_Spells!$D:$D,MATCH(A57,Data_Spells!$A:$A,0))&"","")) | D57: =IF(A57="","",IFERROR(INDEX(Data_Spells!$E:$E,MATCH(A57,Data_Spells!$A:$A,0))&"","")) | E57: =IF(A57="","",IFERROR(INDEX(Data_Spells!$F:$F,MATCH(A57,Data_Spells!$A:$A,0))&"","")) | F57: =IF(A57="","",IFERROR(INDEX(Data_Spells!$G:$G,MATCH(A57,Data_Spells!$A:$A,0))&"","")) | H57: =IF(A57="","",IF(G57="Yes",0,IF(N57="P",50,100)*MIN(5,INT((COUNTIF($N$51:N57,N57)-1)/5)+1))) | I57: =IF(A57="","",IFERROR(INDEX(Data_Spells!$H:$H,MATCH(A57,Data_Spells!$A:$A,0))&"","")) | M57: =IF(A57="","",IFERROR(INDEX(Data_Spells!$I:$I,MATCH(A57,Data_Spells!$A:$A,0))&"","")) | N57: =IF(A57="","","M")
B58: =IF(A58="","",IFERROR(INDEX(Data_Spells!$C:$C,MATCH(A58,Data_Spells!$A:$A,0))&"","")) | C58: =IF(A58="","",IFERROR(INDEX(Data_Spells!$D:$D,MATCH(A58,Data_Spells!$A:$A,0))&"","")) | D58: =IF(A58="","",IFERROR(INDEX(Data_Spells!$E:$E,MATCH(A58,Data_Spells!$A:$A,0))&"","")) | E58: =IF(A58="","",IFERROR(INDEX(Data_Spells!$F:$F,MATCH(A58,Data_Spells!$A:$A,0))&"","")) | F58: =IF(A58="","",IFERROR(INDEX(Data_Spells!$G:$G,MATCH(A58,Data_Spells!$A:$A,0))&"","")) | H58: =IF(A58="","",IF(G58="Yes",0,IF(N58="P",50,100)*MIN(5,INT((COUNTIF($N$51:N58,N58)-1)/5)+1))) | I58: =IF(A58="","",IFERROR(INDEX(Data_Spells!$H:$H,MATCH(A58,Data_Spells!$A:$A,0))&"","")) | M58: =IF(A58="","",IFERROR(INDEX(Data_Spells!$I:$I,MATCH(A58,Data_Spells!$A:$A,0))&"","")) | N58: =IF(A58="","","M")
B59: =IF(A59="","",IFERROR(INDEX(Data_Spells!$C:$C,MATCH(A59,Data_Spells!$A:$A,0))&"","")) | C59: =IF(A59="","",IFERROR(INDEX(Data_Spells!$D:$D,MATCH(A59,Data_Spells!$A:$A,0))&"","")) | D59: =IF(A59="","",IFERROR(INDEX(Data_Spells!$E:$E,MATCH(A59,Data_Spells!$A:$A,0))&"","")) | E59: =IF(A59="","",IFERROR(INDEX(Data_Spells!$F:$F,MATCH(A59,Data_Spells!$A:$A,0))&"","")) | F59: =IF(A59="","",IFERROR(INDEX(Data_Spells!$G:$G,MATCH(A59,Data_Spells!$A:$A,0))&"","")) | H59: =IF(A59="","",IF(G59="Yes",0,IF(N59="P",50,100)*MIN(5,INT((COUNTIF($N$51:N59,N59)-1)/5)+1))) | I59: =IF(A59="","",IFERROR(INDEX(Data_Spells!$H:$H,MATCH(A59,Data_Spells!$A:$A,0))&"","")) | M59: =IF(A59="","",IFERROR(INDEX(Data_Spells!$I:$I,MATCH(A59,Data_Spells!$A:$A,0))&"","")) | N59: =IF(A59="","","M")
B60: =IF(A60="","",IFERROR(INDEX(Data_Spells!$C:$C,MATCH(A60,Data_Spells!$A:$A,0))&"","")) | C60: =IF(A60="","",IFERROR(INDEX(Data_Spells!$D:$D,MATCH(A60,Data_Spells!$A:$A,0))&"","")) | D60: =IF(A60="","",IFERROR(INDEX(Data_Spells!$E:$E,MATCH(A60,Data_Spells!$A:$A,0))&"","")) | E60: =IF(A60="","",IFERROR(INDEX(Data_Spells!$F:$F,MATCH(A60,Data_Spells!$A:$A,0))&"","")) | F60: =IF(A60="","",IFERROR(INDEX(Data_Spells!$G:$G,MATCH(A60,Data_Spells!$A:$A,0))&"","")) | H60: =IF(A60="","",IF(G60="Yes",0,IF(N60="P",50,100)*MIN(5,INT((COUNTIF($N$51:N60,N60)-1)/5)+1))) | I60: =IF(A60="","",IFERROR(INDEX(Data_Spells!$H:$H,MATCH(A60,Data_Spells!$A:$A,0))&"","")) | M60: =IF(A60="","",IFERROR(INDEX(Data_Spells!$I:$I,MATCH(A60,Data_Spells!$A:$A,0))&"","")) | N60: =IF(A60="","","M")
B61: =IF(A61="","",IFERROR(INDEX(Data_Spells!$C:$C,MATCH(A61,Data_Spells!$A:$A,0))&"","")) | C61: =IF(A61="","",IFERROR(INDEX(Data_Spells!$D:$D,MATCH(A61,Data_Spells!$A:$A,0))&"","")) | D61: =IF(A61="","",IFERROR(INDEX(Data_Spells!$E:$E,MATCH(A61,Data_Spells!$A:$A,0))&"","")) | E61: =IF(A61="","",IFERROR(INDEX(Data_Spells!$F:$F,MATCH(A61,Data_Spells!$A:$A,0))&"","")) | F61: =IF(A61="","",IFERROR(INDEX(Data_Spells!$G:$G,MATCH(A61,Data_Spells!$A:$A,0))&"","")) | H61: =IF(A61="","",IF(G61="Yes",0,IF(N61="P",50,100)*MIN(5,INT((COUNTIF($N$51:N61,N61)-1)/5)+1))) | I61: =IF(A61="","",IFERROR(INDEX(Data_Spells!$H:$H,MATCH(A61,Data_Spells!$A:$A,0))&"","")) | M61: =IF(A61="","",IFERROR(INDEX(Data_Spells!$I:$I,MATCH(A61,Data_Spells!$A:$A,0))&"","")) | N61: =IF(A61="","","M")
B62: =IF(A62="","",IFERROR(INDEX(Data_Spells!$C:$C,MATCH(A62,Data_Spells!$A:$A,0))&"","")) | C62: =IF(A62="","",IFERROR(INDEX(Data_Spells!$D:$D,MATCH(A62,Data_Spells!$A:$A,0))&"","")) | D62: =IF(A62="","",IFERROR(INDEX(Data_Spells!$E:$E,MATCH(A62,Data_Spells!$A:$A,0))&"","")) | E62: =IF(A62="","",IFERROR(INDEX(Data_Spells!$F:$F,MATCH(A62,Data_Spells!$A:$A,0))&"","")) | F62: =IF(A62="","",IFERROR(INDEX(Data_Spells!$G:$G,MATCH(A62,Data_Spells!$A:$A,0))&"","")) | H62: =IF(A62="","",IF(G62="Yes",0,IF(N62="P",50,100)*MIN(5,INT((COUNTIF($N$51:N62,N62)-1)/5)+1))) | I62: =IF(A62="","",IFERROR(INDEX(Data_Spells!$H:$H,MATCH(A62,Data_Spells!$A:$A,0))&"","")) | M62: =IF(A62="","",IFERROR(INDEX(Data_Spells!$I:$I,MATCH(A62,Data_Spells!$A:$A,0))&"","")) | N62: =IF(A62="","","M")

Sheet Background
A1: PERSONALITY & BACKGROUND
A3: BACKGROUND QUESTIONS
A4: Where are you from?
A5: What is your family like?
A6: Who are your best friends?
A7: What are your best and worst memories?
A8: What are your religious beliefs?
A9: To whom, or what, are you loyal?
A10: What have you been doing lately?
A12: PSYCHOLOGY & MUTATIONS
A18: CONDITIONS, INJURIES & DISEASES
A24: CONTACTS, ALLIES & ENEMIES
A30: NOTES

Sheet Data_Lists
A1: Species | B1: Fate | C1: Fortune | D1: Move | E1: Fluent languages (+30) | F1: Species skills (pick 5) | G1: Species talents | H1: Random talents | J1: Career | L1: Class | M1: Class trappings | O1: Yes/No | Q1: Location | R1: Capacity | T1: Availability | V1: Career entered as | W1: XP | Y1: Lore | Z1: Wind | AB1: Deity | AC1: Blessings | AE1: Advance (+) | AF1: Char XP (total) | AG1: Skill XP (total) | AI1: d100 up to | AJ1: Random talent
A2: Human (Reiklander) | B2: 4 | C2: 3 | D2: 4 | E2: Language (Reikspiel) | F2: Animal Care, Charm, Cool, Evaluate, Gossip, Haggle, Language (Bretonnian), Language (Wastelander), Leadership, Lore (Reikland), Melee (Basic), Ranged (Bow) | G2: Doomed | H2: 4 | J2: Adviser | L2: Academic | M2: Sling Bag, Writing Kit, Parchment (1d10 sheets) | O2: Yes | Q2: Worn | T2: Common | V2: Starting career | W2: 0 | Y2: Beasts | Z2: Ghur | AB2: Manann | AC2: Battle, Breath, Courage, Hardiness, Savagery, Tenacity | AE2: 0 | AF2: 0 | AG2: 0 | AI2: 2 | AJ2: Acute Sense (Sight)
A3: Dwarf | B3: 2 | C3: 2 | D3: 3 | E3: Language (Khazalid), Language (Reikspiel) | F3: Consume Alcohol, Cool, Endurance, Entertain (Storytelling), Evaluate, Intimidate, Lore (Dwarfs), Lore (Geology), Lore (Metallurgy), Melee (Basic), Trade (Any One) | G3: Magic Resistance, Night Vision, Read/Write or Relentless, Resolute or Strong-minded, Sturdy | H3: 0 | J3: Agitator | L3: Burgher | M3: Cloak, Hat, Sling Bag, Lunch | O3: No | Q3: Carried | T3: Scarce | V3: Same class | W3: 100 | Y3: Death | Z3: Shyish | AB3: Morr | AC3: Breath, Courage, Fortune, Righteousness, Tenacity, Wisdom | AE3: 5 | AF3: 125 | AG3: 50 | AI3: 5 | AJ3: Ambidextrous
A4: Halfling | B4: 2 | C4: 3 | D4: 3 | E4: Language (Haffennaff), Language (Reikspiel) | F4: Charm, Consume Alcohol, Dodge, Gamble, Haggle, Intuition, Lore (Reikland), Perception, Sleight of Hand, Stealth (Any One), Trade (Cook) | G4: Acute Sense (Taste), Night Vision, Resistant (Chaos) | H4: 2 | J4: Apothecary | L4: Courtier | M4: Fine Clothing, Tweezers, Ear Pick, Comb | Q4: Backpack | R4: 4 | T4: Rare | V4: Different class | W4: 200 | Y4: Fire | Z4: Aqshy | AB4: Myrmidia | AC4: Battle, Conscience, Courage, Fortune, Protection, Righteousness | AE4: 10 | AF4: 300 | AG4: 125 | AI4: 7 | AJ4: Artistic (Any One)
A5: High Elf | B5: 1 | C5: 2 | D5: 5 | E5: Language (Eltharin), Language (Reikspiel) | F5: Cool, Entertain (Sing), Evaluate, Leadership, Melee (Basic), Navigation, Perception, Play (Any One), Ranged (Bow), Sail, Swim | G5: Acute Sense (Sight), Coolheaded or Savvy, Night Vision, Second Sight or Sixth Sense, Read/Write | H5: 0 | J5: Artisan | L5: Peasant | M5: Cloak, Sling Bag, Rations (1 day) | Q5: Sling Bag | R5: 2 | T5: Exotic | Y5: Heavens | Z5: Azyr | AB5: Ranald | AC5: Charisma, Conscience, Finesse, Fortune, Protection, Wit | AE5: 15 | AF5: 550 | AG5: 225 | AI5: 10 | AJ5: Attractive
A6: Wood Elf | B6: 1 | C6: 2 | D6: 5 | E6: Language (Eltharin), Language (Reikspiel) | F6: Athletics, Climb, Endurance, Entertain (Sing), Intimidate, Melee (Basic), Outdoor Survival, Perception, Ranged (Bow), Stealth (Rural), Track | G6: Acute Sense (Sight), Hardy or Second Sight, Night Vision, Read/Write or Very Resilient, Rover | H6: 0 | J6: Artist | L6: Ranger | M6: Cloak, Backpack, Tinderbox, Blanket, Rations (1 day) | Q6: Pouch | R6: 1 | Y6: Life | Z6: Ghyran | AB6: Rhya | AC6: Breath, Conscience, Grace, Healing, Protection, Recuperation | AE6: 20 | AF6: 900 | AG6: 375 | AI6: 12 | AJ6: Briber
J7: Bailiff | L7: Riverfolk | M7: Cloak, Sling Bag, Flask of Spirits | Q7: Sack | R7: 4 | Y7: Light | Z7: Hysh | AB7: Shallya | AC7: Breath, Conscience, Healing, Protection, Recuperation, Tenacity | AE7: 25 | AF7: 1400 | AG7: 625 | AI7: 15 | AJ7: Cardsharp
J8: Beggar | L8: Rogue | M8: Sling Bag, Candles (2), Matches (1d10), Hood or Mask | Q8: Large Sack | R8: 6 | Y8: Metal | Z8: Chamon | AB8: Sigmar | AC8: Battle, Courage, Hardiness, Might, Protection, Righteousness | AE8: 30 | AF8: 2100 | AG8: 1025 | AI8: 17 | AJ8: Catfall
J9: Boatman | L9: Warrior | M9: Hand Weapon | Q9: Saddlebags | R9: 8 | Y9: Shadows | Z9: Ulgu | AB9: Taal | AC9: Battle, Breath, Conscience, Hardiness, The Hunt, Savagery | AE9: 35 | AF9: 3050 | AG9: 1625 | AI9: 20 | AJ9: Coolheaded
J10: Bounty Hunter | Q10: Mount / Cart | Y10: Hedgecraft | AB10: Ulric | AC10: Battle, Courage, Hardiness, Might, Savagery, Tenacity | AE10: 40 | AF10: 4350 | AG10: 2475 | AI10: 22 | AJ10: Contortionist
J11: Cavalryman | Q11: Stored | Y11: Witchcraft | AB11: Verena | AC11: Conscience, Courage, Fortune, Righteousness, Wisdom, Wit | AE11: 45 | AF11: 6150 | AG11: 3325 | AI11: 25 | AJ11: Flee!
J12: Charlatan | Y12: Daemonology | AE12: 50 | AF12: 8700 | AG12: 5025 | AI12: 27 | AJ12: Gregarious
J13: Coachman | Y13: Necromancy | AE13: 55 | AF13: 12300 | AG13: 7525 | AI13: 30 | AJ13: Iron Jaw
J14: Duellist | Y14: Nurgle | AE14: 60 | AF14: 17325 | AG14: 11025 | AI14: 32 | AJ14: Lightning Reflexes
J15: Engineer | Y15: Slaanesh | AE15: 65 | AF15: 24275 | AG15: 15775 | AI15: 35 | AJ15: Linguistics
J16: Entertainer | Y16: Tzeentch | AE16: 70 | AF16: 33275 | AG16: 22275 | AI16: 37 | AJ16: Marksman
J17: Envoy | AE17: 75 | AF17: 44525 | AG17: 30775 | AI17: 40 | AJ17: Mimic
J18: Fence | AI18: 42 | AJ18: Night Vision
J19: Flagellant | AI19: 45 | AJ19: Nimble-fingered
J20: Grave Robber | AI20: 47 | AJ20: Noble Blood
J21: Guard | AI21: 50 | AJ21: Nose for Trouble
J22: Hedge Witch | AI22: 52 | AJ22: Orientation
J23: Herbalist | AI23: 55 | AJ23: Perfect Pitch
J24: Hunter | AI24: 57 | AJ24: Pure Soul
J25: Investigator | AI25: 60 | AJ25: Read/Write
J26: Knave | AI26: 62 | AJ26: Resistant (Poison)
J27: Knight | AI27: 65 | AJ27: Rover
J28: Lawyer | AI28: 67 | AJ28: Savvy
J29: Merchant | AI29: 70 | AJ29: Sea Legs
... J41: Protagonist | AI41: 100 | AJ41: Warrior Born
J42: Racketeer
J43: Rat Catcher
J44: Riverwarden
J45: Riverwoman
J46: Roadwarden
J47: Sailor
J48: Scholar
J49: Scout
J50: Servant
J51: Slayer
J52: Smuggler
J53: Soldier
... J65: Wrecker

Sheet Data_Skills
A1: Skill | B1: Base skill | C1: Char | D1: Type | E1: Grouped | F1: Description | G1: Page
A2: Animal Care | B2: Animal Care | C2: Int | D2: Advanced | E2: No | F2: Care for animals and heal them from disease or injury. A Character with an Advance in this Skill can keep animals healthy under normal conditions without needing to Test. A Test is required to diagnose or resolve problems with animals, such as spotting signs of illness or healing an injury (page 171). | G2: 111
A3: Animal Training (Demigryph) | B3: Animal Training | C3: Int | D3: Advanced | E3: Yes | F3: To train a beast, undertake the Animal Training Endeavour between adventures (see page 196). | G3: 111
A4: Animal Training (Dog) | B4: Animal Training | C4: Int | D4: Advanced | E4: Yes | F4: To train a beast, undertake the Animal Training Endeavour between adventures (see page 196). | G4: 111
A5: Animal Training (Hawk) | B5: Animal Training | C5: Int | D5: Advanced | E5: Yes | F5: To train a beast, undertake the Animal Training Endeavour between adventures (see page 196). | G5: 111
A6: Animal Training (Horse) | B6: Animal Training | C6: Int | D6: Advanced | E6: Yes | F6: To train a beast, undertake the Animal Training Endeavour between adventures (see page 196). | G6: 111
A7: Animal Training (Pigeon) | B7: Animal Training | C7: Int | D7: Advanced | E7: Yes | F7: To train a beast, undertake the Animal Training Endeavour between adventures (see page 196). | G7: 111
A8: Art | B8: Art | C8: Dex | D8: Basic | E8: Yes | F8: Create works of art in your chosen medium. The more SL achieved, the better the quality of the final piece. For complicated or large works of art, an Extended Test may be required. | G8: 111
A9: Art (Calligraphy) | B9: Art | C9: Dex | D9: Basic | E9: Yes | F9: Create works of art in your chosen medium. The more SL achieved, the better the quality of the final piece. For complicated or large works of art, an Extended Test may be required. | G9: 111
A10: Art (Drawing) | B10: Art | C10: Dex | D10: Basic | E10: Yes | F10: Create works of art in your chosen medium. The more SL achieved, the better the quality of the final piece. For complicated or large works of art, an Extended Test may be required. | G10: 111
A11: Art (Engraving) | B11: Art | C11: Dex | D11: Basic | E11: Yes | F11: Create works of art in your chosen medium. The more SL achieved, the better the quality of the final piece. For complicated or large works of art, an Extended Test may be required. | G11: 111
A12: Art (Icons) | B12: Art | C12: Dex | D12: Basic | E12: Yes | F12: Create works of art in your chosen medium. The more SL achieved, the better the quality of the final piece. For complicated or large works of art, an Extended Test may be required. | G12: 111
A13: Art (Mosaics) | B13: Art | C13: Dex | D13: Basic | E13: Yes | F13: Create works of art in your chosen medium. The more SL achieved, the better the quality of the final piece. For complicated or large works of art, an Extended Test may be required. | G13: 111
... A202: Trade (Tinker) | B202: Trade | C202: Dex | D202: Advanced | E202: Yes | F202: Your ability to practice a trade, to create something or provide a service, as well as your knowledge of the relevant lore surrounding your trade. | G202: 114

Sheet Data_Talents
A1: Talent | B1: Base talent | C1: Can take multiple times | D1: Characteristic bonus (+5) | E1: Description | F1: Page
A2: Accurate Shot | B2: Accurate Shot | C2: No | E2: You are an exceptional shot and know where to shoot an enemy to inflict maximum damage. Your successful Ranged Attacks inflict +1 Damage, or +2 if you took the time to aim (page 167). | F2: 114
A3: Acute Sense (Hearing) | B3: Acute Sense | C3: Yes | E3: You may take Perception Tests to detect normally imperceptible details with the associated sense, as dictated by the GM. For example, you might be able to hear the difference between the cry of one wolf and another, or taste the difference between the exact same vintage of wine bottled on two different days. | F3: 114
A4: Acute Sense (Sense) | B4: Acute Sense | C4: Yes | E4: You may take Perception Tests to detect normally imperceptible details with the associated sense, as dictated by the GM. For example, you might be able to hear the difference between the cry of one wolf and another, or taste the difference between the exact same vintage of wine bottled on two different days. | F4: 114
A5: Acute Sense (Sight) | B5: Acute Sense | C5: Yes | E5: You may take Perception Tests to detect normally imperceptible details with the associated sense, as dictated by the GM. For example, you might be able to hear the difference between the cry of one wolf and another, or taste the difference between the exact same vintage of wine bottled on two different days. | F5: 114
A6: Acute Sense (Taste) | B6: Acute Sense | C6: Yes | E6: You may take Perception Tests to detect normally imperceptible details with the associated sense, as dictated by the GM. For example, you might be able to hear the difference between the cry of one wolf and another, or taste the difference between the exact same vintage of wine bottled on two different days. | F6: 114
A7: Acute Sense (Touch) | B7: Acute Sense | C7: Yes | E7: You may take Perception Tests to detect normally imperceptible details with the associated sense, as dictated by the GM. For example, you might be able to hear the difference between the cry of one wolf and another, or taste the difference between the exact same vintage of wine bottled on two different days. | F7: 114
A8: Aethyric Attunement | B8: Aethyric Attunement | C8: Yes | E8: Your experience, talent, or training lets you accumulate magical energy with a reduced risk of miscasts. If you would roll on the Minor Miscast Table, you may roll twice and choose whichever result you prefer. You may purchase this Talent a second time to gain the same benefit when rolling on the Major Miscast Table. | F8: 114
A9: Alley Cat | B9: Alley Cat | C9: No | E9: You are at home in cities, able to move about without drawing attention to yourself and vanish into any crowd. You gain Advantage on Stealth (Urban) Tests, and can figure out the quickest or least noticeable way to get across any town or city you are familiar with without making a Test. | F9: 114
A10: Ambidextrous | B10: Ambidextrous | C10: No | E10: You can use your off-hand far better than most folk, either by training or innate talent. You do not suffer the –2 SL penalty to Tests relying solely on your secondary hand, including attacks made with weapons held in that hand. | F10: 114
A11: Animal Affinity | B11: Animal Affinity | C11: No | E11: As long as you do not act aggressively towards them, wild animals will not ordinarily attack you. Specialisations: Grey Order, Guild (Any One), Ranger, Scout, Thief, Vagabond. You have been taught how to use clandestine markings only intelligible to members of a select group. | F11: 114
A12: Arcane Magic (Heavens) | B12: Arcane Magic | C12: No | E12: Upon learning the Talent, you gain one Spell of your choice from your chosen Lore. You may now memorise additional Spells from your chosen Lore for the following cost in XP. You may normally learn only one Arcane Lore of Magic. | F12: 115
A13: Arcane Magic (Hedgecraft) | B13: Arcane Magic | C13: No | E13: Upon learning the Talent, you gain one Spell of your choice from your chosen Lore. You may now memorise additional Spells from your chosen Lore for the following cost in XP. You may normally learn only one Arcane Lore of Magic. | F13: 115
... A40: Contortionist | B40: Contortionist | C40: No | E40: You can bend and manipulate your body in a myriad of seemingly unnatural ways. This allows you to squeeze through gaps that would normally be difficult or impossible, at the GM's discretion. You gain Advantage on any Athletics Test made to escape from bonds. | F40: 117
A41: Coolheaded | B41: Coolheaded | C41: No | D41: WP | E41: Gain +5 Willpower. This does not count toward Advances. | F41: 117
A42: Crack the Whip | B42: Crack the Whip | C42: No | E42: You know how to get the most out of your animals. Assuming you have the Drive Skill, you can direct your vehicle's animals to take an Action, as well as a Move, without a Test. When a Drive Test is required, make it with Advantage. When driving a vehicle in a Pursuit, add +1 to the animals' Movement Attributes. | F42: 117
A43: Craftsman (Apothecary) | B43: Craftsman | C43: Yes | E43: Choose a Trade Specialisation. You gain Advantage on Tests of this skill, and may Advance it even if it is not part of your current Career. You may purchase this Talent more than once, choosing a new Trade Specialisation each time you do. | F43: 117
A44: Craftsman (Barber) | B44: Craftsman | C44: Yes | E44: Choose a Trade Specialisation. You gain Advantage on Tests of this skill, and may Advance it even if it is not part of your current Career. You may purchase this Talent more than once, choosing a new Trade Specialisation each time you do. | F44: 117
A45: Craftsman (Boatbuilder) | B45: Craftsman | C45: Yes | E45: Choose a Trade Specialisation. You gain Advantage on Tests of this skill, and may Advance it even if it is not part of your current Career. You may purchase this Talent more than once, choosing a new Trade Specialisation each time you do. | F45: 117
A46: Craftsman (Cartographer) | B46: Craftsman | C46: Yes | E46: Choose a Trade Specialisation. You gain Advantage on Tests of this skill, and may Advance it even if it is not part of your current Career. You may purchase this Talent more than once, choosing a new Trade Specialisation each time you do. | F46: 117
A47: Craftsman (Engineer) | B47: Craftsman | C47: Yes | E47: Choose a Trade Specialisation. You gain Advantage on Tests of this skill, and may Advance it even if it is not part of your current Career. You may purchase this Talent more than once, choosing a new Trade Specialisation each time you do. | F47: 117
A48: Craftsman (Explosives) | B48: Craftsman | C48: Yes | E48: Choose a Trade Specialisation. You gain Advantage on Tests of this skill, and may Advance it even if it is not part of your current Career. You may purchase this Talent more than once, choosing a new Trade Specialisation each time you do. | F48: 117
A49: Craftsman (Herbalist) | B49: Craftsman | C49: Yes | E49: Choose a Trade Specialisation. You gain Advantage on Tests of this skill, and may Advance it even if it is not part of your current Career. You may purchase this Talent more than once, choosing a new Trade Specialisation each time you do. | F49: 117
A50: Craftsman (Trade) | B50: Craftsman | C50: Yes | E50: Choose a Trade Specialisation. You gain Advantage on Tests of this skill, and may Advance it even if it is not part of your current Career. You may purchase this Talent more than once, choosing a new Trade Specialisation each time you do. | F50: 117
A51: Criminal | B51: Criminal | C51: No | E51: When you successfully use the Income Endeavour to earn coin from a criminal enterprise of any kind, double the resulting coin. Whether through distinctive tattoos, shifty looks, or a rough demeanour, your criminal nature is hard to hide. | F51: 117
A52: Deadeye Shot | B52: Deadeye Shot | C52: No | E52: You always hit an opponent right between the eyes, or wherever else you intend to hit. When making a Ranged Attack, the penalty for making a Called Shot is reduced to -1 SL, or removed entirely if you are making an aimed shot (page 167). | F52: 117
A53: Dealmaker | B53: Dealmaker | C53: No | E53: You are a skilled businessman who knows how to close a deal. You gain Advantage on any Haggle Test you make, and usually have a good idea of when an offer really is final. | F53: 117
... A119: Kingpin | B119: Kingpin | C119: No | E119: You have earned an air of respectability despite your nefarious ways. The Criminal Talent no longer makes law enforcers suspect you or prevents you from accessing certain Careers. Most other Criminals recognise you as someone to respect — unless they're well prepared and gunning for your position and status. | F119: 121
A120: Lightning Reflexes | B120: Lightning Reflexes | C120: No | D120: Ag | E120: Gain +5 Agility. This does not count toward Advances. | F120: 121
A121: Linguistics | B121: Linguistics | C121: No | E121: You gain Advantage on Language Tests. Additionally, Advances in any Language Specialisations always cost 50 XP, no matter how many Advances you have already taken. This Talent applies only to languages used for true communication — its effects do not apply to Language (Magick). | F121: 121
A122: Lip Reading | B122: Lip Reading | C122: No | E122: You can work out what people are saying by watching their lips move. If you have an unobstructed view of the speaker's mouth, you can attempt a Challenging (+0 SL) Intuition Test to understand what they are saying. | F122: 122
A123: Luck | B123: Luck | C123: No | E123: They say when you were born, Ranald smiled. You gain +1 maximum Fortune. If you wish, you may purchase this Talent up to three times, for a maximum of +3 Fortune. | F123: 122
A124: Magic Resistance | B124: Magic Resistance | C124: No | E124: You are resistant to magic. The SL of any Spell that would affect you is reduced by 3. Furthermore, if you have this Talent, you may never learn the Channelling Skill or the Arcane Magic, Bless, Chaos Magic, Invoke, Petty Magic, or Witch! Talents, and vice versa. | F124: 122
A125: Magical Sense | B125: Magical Sense | C125: No | E125: You immediately become aware of any spellcasting within your Perception in yards, although you cannot discern the nature of the magic and can tell only the rough direction of the source. | F125: 122
A126: Magnum Opus | B126: Magnum Opus | C126: Yes | E126: When you take this Talent, you may create a single, extraordinary work of art with one of your Art or Trade Skills. | F126: 122
A127: Marksman | B127: Marksman | C127: No | D127: BS | E127: Gain +5 Ballistic Skill. This does not count toward Advances. | F127: 122
A128: Master of Disguise | B128: Master of Disguise | C128: No | E128: With nothing but posture changes, face twisting, and careful use of appropriate clothing, you no longer look like yourself. Furthermore, when you successfully use the Entertain (Acting) Skill, you can choose to either use your rolled SL, or the number rolled on your units die. | F128: 122
A129: Master Orator | B129: Master Orator | C129: No | E129: You gain Advantage on Lore (Law) Tests made to argue a case before a magistrate, or similar Lore Tests made to argue an academic, theological, or political point before a crowd. | F129: 122
A130: Master Tradesman (Apothecary) | B130: Master Tradesman | C130: Yes | E130: You are a skilled and reliable artisan. When you take this Talent, choose a Trade Specialisation. When you successfully use this Skill, you can choose to either use your rolled SL, or the number rolled on your units die. You may take this Talent more than once, choosing a new Trade Specialisation each time you do. | F130: 122
A131: Master Tradesman (Boatbuilder) | B131: Master Tradesman | C131: Yes | E131: You are a skilled and reliable artisan. When you take this Talent, choose a Trade Specialisation. When you successfully use this Skill, you can choose to either use your rolled SL, or the number rolled on your units die. You may take this Talent more than once, choosing a new Trade Specialisation each time you do. | F131: 122
A132: Master Tradesman (Engineer) | B132: Master Tradesman | C132: Yes | E132: You are a skilled and reliable artisan. When you take this Talent, choose a Trade Specialisation. When you successfully use this Skill, you can choose to either use your rolled SL, or the number rolled on your units die. You may take this Talent more than once, choosing a new Trade Specialisation each time you do. | F132: 122
A133: Master Tradesman (Herbalist) | B133: Master Tradesman | C133: Yes | E133: You are a skilled and reliable artisan. When you take this Talent, choose a Trade Specialisation. When you successfully use this Skill, you can choose to either use your rolled SL, or the number rolled on your units die. You may take this Talent more than once, choosing a new Trade Specialisation each time you do. | F133: 122
A134: Master Tradesman (Trade) | B134: Master Tradesman | C134: Yes | E134: You are a skilled and reliable artisan. When you take this Talent, choose a Trade Specialisation. When you successfully use this Skill, you can choose to either use your rolled SL, or the number rolled on your units die. You may take this Talent more than once, choosing a new Trade Specialisation each time you do. | F134: 122
A135: Menacing | B135: Menacing | C135: No | E135: You have an imposing presence, and most people know to steer clear of you. You gain Advantage on Intimidation Tests, and most sensible thieves, bandits, and pickpockets will choose another target as long as one is available. | F135: 122
A136: Mimic | B136: Mimic | C136: No | E136: You gain Advantage on Entertain (Acting, Comedy) and Perform (Clowning) Tests. Additionally, you may replicate any accent you are exposed to for at least a day, which may help with dealing with locals in an area at the GM's discretion. | F136: 122
A137: Night Vision | B137: Night Vision | C137: No | E137: Assuming you have at least a faint source of light (such as moonlight obscured by a Marienburg fog, the glowing eyes of a wight, or a bioluminescent fungus) you can see clearly for 20 yards and can extend the effective illumination distance of any light sources by a further 20 yards. | F137: 123
A138: Nimble-fingered | B138: Nimble-fingered | C138: No | D138: Dex | E138: Gain +5 Dexterity. This does not count toward Advances. | F138: 123
A139: Noble Blood | B139: Noble Blood | C139: No | E139: Assuming you are dressed appropriately, you are always considered to be at least one Status Tier higher than others unless they also have the Noble Blood Talent, where Status is compared as normal. Furthermore, you may enter the Noble Career as if it were within the same Class as your current Career. | F139: 123
A140: Nose for Trouble | B140: Nose for Trouble | C140: No | E140: You are used to getting into, and preferably out of, trouble. You gain Advantage on Intuition Tests, and can usually tell where in a town or village you can find the opportunity to gamble, fight, or get stinking drunk. | F140: 123
A141: Numismatics | B141: Numismatics | C141: No | E141: You gain Advantage on Lore (Heraldry) Tests to identify the providence of any coin, medal, or flag. When you successfully make an Evaluate Test to determine the value of an item, you may use either the rolled SL or the value of your units die. | F141: 123
A142: Old Salt | B142: Old Salt | C142: No | E142: You are an experienced seaman and are very used to sea life. When you successfully use the Row or Sail Skill on the ocean, you can choose to either use your rolled SL, or the number rolled on your units die. You count as two boatmen towards the minimum number of crew to pilot an ocean-going vessel. | F142: 123
A143: Orientation | B143: Orientation | C143: No | E143: You have an instinctive sense of direction. You gain Advantage on Navigation Tests. You also automatically know which direction is north with a glimpse at the stars, trees, or whatever other signs you are familiar with. | F143: 123
A144: Panhandle | B144: Panhandle | C144: No | E144: You gain Advantage on Charm Tests while begging, including those made during an Income Endeavour. Additionally, you can usually find the best places to find shelter for a safe but uncomfortable night's sleep beneath bridges, near middens, and in other urban locations most folks choose to ignore. | F144: 123
A145: Perfect Pitch | B145: Perfect Pitch | C145: No | E145: You have perfect pitch, able to replicate notes perfectly. You can learn a piece of music simply by listening to it once, and gain Advantage on Entertain (Singing) and Play (Any) Tests. | F145: 123
A146: Petty Magic | B146: Petty Magic | C146: No | E146: Upon learning the Talent, you manifest a number of Spells equal to your Willpower Bonus. You can learn additional Petty Magic Spells for the following cost in XP. Full rules for learning new Spells are provided in Chapter 8: Magic. | F146: 123
A147: Pharmacist | B147: Pharmacist | C147: No | E147: You are highly skilled at pharmacy, better able than most to make pills, unguents, oils, creams, and more. When creating an alchemical remedy (see page 154), you produce an additional dose. | F147: 124
A148: Pilot | B148: Pilot | C148: No | E148: You are skilled at leading vessels through dangerous waters, high winds, or when making haste to escape pirates or wreckers. Gain Advantage on Row and Sail Tests. | F148: 124
A149: Public Speaker | B149: Public Speaker | C149: No | E149: You know how to gather a crowd with ease and can usually gauge the mood of a group and what might motivate them to take action. You gain Advantage on Charm Tests made to influence groups of people. | F149: 124
A150: Pure Soul | B150: Pure Soul | C150: No | E150: Your soul is pure, quite resistant to the depredations of Chaos. You may gain double the usual number of Corruption Points before having to Test to resist mutation (see page 188). | F150: 124
... A177: Savant (Theology) | B177: Savant | C177: Yes | E177: You are exceptionally learned and have a significant degree of specialised knowledge in your field of study. Choose any Lore Specialisation you possess. Tests made using this Lore Specialisation are made with Advantage. You may acquire this Talent more than once, choosing a new Lore Specialisation each time you do so. | F177: 125
A178: Savvy | B178: Savvy | C178: No | D178: Int | E178: Gain +5 Intelligence. This does not count toward Advances. | F178: 125
A179: Scale Sheer Surface | B179: Scale Sheer Surface | C179: No | E179: You are an exceptional climber. You gain Advantage on Climb Tests. Additionally, you can attempt to climb even seemingly impossible surfaces such as sheer fortifications, ice shelves, greased poles, and similar, at a maximum imposed Difficulty of Very Hard (-3 SL). | F179: 125
A180: Schemer | B180: Schemer | C180: No | E180: You are a master of politics, seeing conspiracy around every corner, and are adept at weaselling secrets and rumour from those in the know. When you successfully use Gossip or Lore (Politics), you can choose to either use your rolled SL, or the number rolled on your units die. | F180: 125
A181: Sea Legs | B181: Sea Legs | C181: No | E181: You are used to the rolling motion of the oceans, and are unlikely to get seasick, even in the worst storms. Under normal conditions, you need never Test to see if you become seasick, and you gain Advantage on Tests to avoid it should the GM require one. | F181: 125
A182: Seasoned Traveller | B182: Seasoned Traveller | C182: No | E182: You are an inquisitive soul who has travelled far and wide, and quickly pick up all manner of local information. You can always advance the relevant regional Lore (Local) Skill whilst you remain in that region, even if it is not part of your current Career. | F182: 125
A183: Second Sight | B183: Second Sight | C183: No | E183: You can perceive the shifting Winds of Magic that course from the Chaos Gates at the poles of the world. You now have the ability to percieve the Winds of Magic (see page 236). | F183: 125
A184: Secret Identity | B184: Secret Identity | C184: No | E184: You can adopt an alternate persona with a Career of your choice for a set period of time (an encounter, a day, an entire adventure) without having to Test to maintain the charade, and during this period you are treated as having the Class and Status of the chosen Career. | F184: 125
A185: Shadow | B185: Shadow | C185: No | E185: You instinctively know when to abandon a tail before your quarry spots you. If someone you are following succeeds on a Perception Test to spot you, you may either allow them to spot you and continue following them, or lose track of them and remain unseen. | F185: 125
A186: Sharp | B186: Sharp | C186: No | D186: I | E186: Gain +5 Initiative. This does not count toward Advances. | F186: 125
A187: Sharpshooter | B187: Sharpshooter | C187: No | E187: Ranged Tests you make do not incur any penalties from your target being Prone or in cover. You may also perform feats of accuracy with your weapons that most would think impossible, such as cutting a hangman's noose with an arrow or punching a hole in a tossed coin with a pistol shot. | F187: 125
A188: Shieldsman | B188: Shieldsman | C188: No | E188: Once per Round, while carrying a shield, you may lose Momentum to either grant your shield's AP bonus to an adjacent ally who is not carrying a shield, or, if you win an Opposed Melee Test while attacking or defending, push your opponent up to 2 yards directly away and no longer count as Engaged. | F188: 125
A189: Sixth Sense | B189: Sixth Sense | C189: No | E189: You get a strange feeling whenever danger is near. If you are about to trigger a trap or fall victim to a hidden danger, such as an ambush, collapsing tunnel, or poisoned glass of wine, you may make a Challenging (+0 SL) Intuition Test. On a success, you detect the danger at the last possible moment. | F189: 126
A190: Slayer | B190: Slayer | C190: No | E190: You are undaunted by large enemies and attack them with great gusto. If you Charge a creature whose Size is larger than you, you automatically gain Momentum. | F190: 126
A191: Small | B191: Small | C191: No | E191: You are much shorter than most folk in the Old World. Gain Size (Small). The full rules for different Sizes are found in Chapter 12: Bestiary on page 360. | F191: 126
A192: Sniper | B192: Sniper | C192: No | E192: Distance is of no import to your shooting skills, and you are just as adept at picking off far away targets as those nearby. You suffer no penalties for shooting at Long Range, and only a -1 SL penalty for shots made at Extreme Range. | F192: 126
A193: Speedreader | B193: Speedreader | C193: No | E193: You read books at a voracious pace. A single glance is all you require to read a full page of text, and you can easily make your way through even a lengthy tome in a single day. When you make an Extended Research Test, double the SL added by any successful Test you make. | F193: 126
A194: Sprinter | B194: Sprinter | C194: No | E194: You are a swift runner with a good level of physical fitness. You gain Advantage on Athletics Tests to run and jump. | F194: 126
A195: Step Aside | B195: Step Aside | C195: No | E195: You are skilled at being where enemy weapons are not. If you successfully use Dodge to defend against an attack, you may move up to 2 yards as you dive away, and no longer count as Engaged. Opponents do not gain a free attack when you do this. | F195: 126
A196: Stone Soup | B196: Stone Soup | C196: No | E196: You are used to getting by with less, and know how to survive lean times. If a member of the party makes a Foraging Test (see page 152), they automatically locate sufficient food to feed you, over and above the number of Characters fed by the Test result, even if the Test fails. | F196: 126
A197: Stout-hearted | B197: Stout-hearted | C197: No | E197: No matter how bad things get, you always seem to come back for more. The first time in an encounter you gain one or more Broken Conditions, you gain one less. | F197: 126
A198: Striding Gait (Coastal) | B198: Striding Gait | C198: Yes | E198: You ignore all movement penalties when crossing over or through a specified terrain. If engaged in a Pursuit in your chosen terrain, you receive +2 SL to all Tests relating to the Pursuit. Example Terrains are: Coastal, Desert, Rocky, Tundra, Wetland, Woodland. | F198: 127
... A209: Sturdy | B209: Sturdy | C209: No | E209: You have a brawny physique, or are very used to carrying things. When calculating the number of Encumbrance Points you can carry, count your Strength Bonus twice. | F209: 127
A210: Suave | B210: Suave | C210: No | D210: Fel | E210: Gain +5 Fellowship. This does not count toward Advances. | F210: 127
A211: Super Numerate | B211: Super Numerate | C211: No | E211: You have a gift for calculation and can work out solutions to most mathematical problems with ease, without the need for a quill, paper, or abacus. You gain Advantage on Evaluate Tests, and you can keep track of the passage of time accurately so long as you are conscious. | F211: 127
A212: Supportive | B212: Supportive | C212: No | E212: You know what to say and when to make the most impact upon your superiors. You not only ignore the penalty to using Charm on those of a higher Status Tier, but also gain Advantage on Charm Tests made to ingratiate yourself with those of higher Status. | F212: 127
A213: Sure Shot | B213: Sure Shot | C213: No | E213: Your Ranged Attacks inflict +1 Damage, and may ignore armour with the Partial Flaw. If your weapon has the Impale Quality, you can ignore armour with the Weakpoints Flaw as well. | F213: 127
A214: Surgery | B214: Surgery | C214: No | E214: When you successfully use the Heal Skill outside of combat, you can choose to either use your rolled SL, or the number rolled on your units die. Furthermore, you can treat any Critical Wound marked as needing Surgery, for effects see pages 172 to 179. | F214: 127
A215: Tenacious | B215: Tenacious | C215: No | E215: You are a vigorous sort. The first time in an encounter you would gain one or more Fatigued Conditions, you gain one less. | F215: 127
A216: Tinker | B216: Tinker | C216: No | E216: You are somewhat of a Johann-of-all-trades, able to repair almost anything. You count all Trade Skills as Basic when repairing broken items. If you have at least 1 Advance in a Trade Skill, you have Advantage on Tests to repair associated items, and such repairs take half as much time. | F216: 127
A217: Tower of Memories | B217: Tower of Memories | C217: No | E217: When you successfully use the Lore Skill, you can choose to either use your rolled SL, or the number rolled on your units die. | F217: 128
A218: Trapper | B218: Trapper | C218: No | E218: You are skilled at using all manner of traps, and know how to make basic snares and pitfalls from whatever comes to hand. You gain Advantage on Set Trap Tests. Additionally, with an hour to prepare, you can craft a small animal trap or covered pit (see page 136). | F218: 128
A219: Trick Rider | B219: Trick Rider | C219: No | E219: You are capable of amazing feats of agility while in the saddle. You can use any of your Perform Skills and unmodified Dodge Skill when mounted. | F219: 128
A220: Tunnel Fighter | B220: Tunnel Fighter | C220: No | E220: You are at home in tunnels, sewers, and other underground environments. You gain Advantage on Stealth (Underground) Tests, and can easily tell how far you have travelled underground and roughly how deep beneath the surface you are. | F220: 128
A221: Unshakeable | B221: Unshakeable | C221: No | E221: You are a jaded veteran who has survived more than one hail of shots from blackpowder weapons. You do not need to Test to resist a Broken Condition if shot at by a Blackpowder weapon. | F221: 128
A222: Very Resilient | B222: Very Resilient | C222: No | D222: T | E222: Gain +5 Toughness. This does not count toward Advances. | F222: 128
A223: Very Strong | B223: Very Strong | C223: No | D223: S | E223: Gain +5 Strength. This does not count toward Advances. | F223: 128
A224: War Leader | B224: War Leader | C224: No | E224: All allies you influence with Leadership during battle (see page 169) may use your Leadership rather than their Cool to resist Fear until the end of the battle. The effect ends if you die, or while you are subject to Broken, Unconscious, or Fear Conditions. | F224: 128
A225: War Wizard | B225: War Wizard | C225: No | E225: You are trained to cast magic while in the thick of combat. On your Turn, you may cast one Spell with a Casting Number of 5 or less for free without using your Action. If you do this, you may not cast another Spell this Turn. | F225: 128
A226: Warrior Born | B226: Warrior Born | C226: No | D226: WS | E226: Gain +5 Weapon Skill. This does not count toward Advances. | F226: 128
A227: Waterman | B227: Waterman | C227: No | E227: You are an experienced freshwater sailor and are well-versed with river vessels. When you successfully use the Row or Sail Skill on a river or lake, you can choose to either use your rolled SL, or the number rolled on your units die. You count as two crewmen towards the minimum number of crew to pilot a river vessel. | F227: 128
...

Sheet Data_Careers
A1: Key | B1: Career | C1: Level | D1: Class | E1: Title | F1: Status | G1: Skills | H1: Talents | I1: Trappings | J1: Career skills up to this level (lookup) | K1: Career talents up to this level (lookup) | L1: Summary | M1: Income skill | N1: Species | O1: Page | P1: WS opens at | Q1: BS opens at | R1: S opens at | S1: T opens at | T1: I opens at | U1: Ag opens at | V1: Dex opens at | W1: Int opens at | X1: WP opens at | Y1: Fel opens at
A2: Adviser|1 | B2: Adviser | C2: 1 | D2: Courtier | E2: Aide | F2: Silver 1 | G2: Bribery, Charm, Evaluate, Gossip, Haggle, Intuition, Lore (Local), Lore (Politics), Research, Secret Signs (Any One) | H2: Beneath Notice, Etiquette (All), Gregarious, Read/Write | I2: Writing Kit | J2: |Bribery|Charm|Evaluate|Gossip|Haggle|Intuition|Lore (Local)|Lore (Politics)|Research|Secret Signs (any)| | K2: |Beneath Notice|Etiquette (any)|Gregarious|Read/Write| | L2: Wise and well-informed, you provide insight and guidance to your employer. | M2: Lore (Politics) | N2: Dwarf, Halfling, High Elf, Human, Wood Elf | O2: 45 | T2: 2 | U2: 4 | V2: 1 | W2: 1 | X2: 3 | Y2: 1
A3: Adviser|2 | B3: Adviser | C3: 2 | D3: Courtier | E3: Adviser | F3: Silver 3 | G3: Consume Alcohol, Cool, Gamble, Intimidate, Language (Classical, Guilder, or Thieves Tongue), Lore (Heraldry) | H3: Criminal, Embezzle, Schemer, Supportive | I3: Livery | J3: |Bribery|Charm|Evaluate|Gossip|Haggle|Intuition|Lore (Local)|Lore (Politics)|Research|Secret Signs (any)|Consume Alcohol|Cool|Gamble|Intimidate|Language (Classical)|Language (Guilder)|Language (Thieves Tongue)|Lore (Heraldry)| | K3: |Beneath Notice|Etiquette (any)|Gregarious|Read/Write|Criminal|Embezzle|Schemer|Supportive| | L3: Wise and well-informed, you provide insight and guidance to your employer. | M3: Lore (Politics) | N3: Dwarf, Halfling, High Elf, Human, Wood Elf | O3: 45 | T3: 2 | U3: 4 | V3: 1 | W3: 1 | X3: 3 | Y3: 1
A4: Adviser|3 | B4: Adviser | C4: 3 | D4: Courtier | E4: Counsellor | F4: Silver 5 | G4: Entertain (Storytelling), Language (Any One), Leadership, Lore (Any One) | H4: Argumentative, Briber, Cat-tongued, Kingpin | I4: Aide, Quality Clothing | J4: |Bribery|Charm|Evaluate|Gossip|Haggle|Intuition|Lore (Local)|Lore (Politics)|Research|Secret Signs (any)|Consume Alcohol|Cool|Gamble|Intimidate|Language (Classical)|Language (Guilder)|Language (Thieves Tongue)|Lore (Heraldry)|Entertain (Storytelling)|Language (any)|Leadership|Lore (any)| | K4: |Beneath Notice|Etiquette (any)|Gregarious|Read/Write|Criminal|Embezzle|Schemer|Supportive|Argumentative|Briber|Cat-tongued|Kingpin| | L4: Wise and well-informed, you provide insight and guidance to your employer. | M4: Lore (Politics) | N4: Dwarf, Halfling, High Elf, Human, Wood Elf | O4: 45 | T4: 2 | U4: 4 | V4: 1 | W4: 1 | X4: 3 | Y4: 1
A5: Adviser|4 | B5: Adviser | C5: 4 | D5: Courtier | E5: Chancellor | F5: Gold 3 | G5: Perform (Dancing), Ride (Horse) | H5: Carouser, Commanding Presence, Noble Blood, Suave | I5: Quality Courtly Garb, Riding Horse, Staff of Advisers and Aides | J5: |Bribery|Charm|Evaluate|Gossip|Haggle|Intuition|Lore (Local)|Lore (Politics)|Research|Secret Signs (any)|Consume Alcohol|Cool|Gamble|Intimidate|Language (Classical)|Language (Guilder)|Language (Thieves Tongue)|Lore (Heraldry)|Entertain (Storytelling)|Language (any)|Leadership|Lore (any)|Perform (Dancing)|Ride (Horse)| | K5: |Beneath Notice|Etiquette (any)|Gregarious|Read/Write|Criminal|Embezzle|Schemer|Supportive|Argumentative|Briber|Cat-tongued|Kingpin|Carouser|Commanding Presence|Noble Blood|Suave| | L5: Wise and well-informed, you provide insight and guidance to your employer. | M5: Lore (Politics) | N5: Dwarf, Halfling, High Elf, Human, Wood Elf | O5: 45 | T5: 2 | U5: 4 | V5: 1 | W5: 1 | X5: 3 | Y5: 1
A6: Agitator|1 | B6: Agitator | C6: 1 | D6: Burgher | E6: Pamphleteer | F6: Brass 1 | G6: Art (Writing), Charm, Consume Alcohol, Entertain (Storytelling), Gossip, Haggle, Lore (Local), Lore (Politics), Trade (Printing), Stealth (Urban) | H6: Blather, Gregarious, Panhandle, Read/Write | I6: Hammer and Nails, Pile of Leaflets, Writing Kit | J6: |Art (Writing)|Charm|Consume Alcohol|Entertain (Storytelling)|Gossip|Haggle|Lore (Local)|Lore (Politics)|Trade (Printing)|Stealth (Urban)| | K6: |Blather|Gregarious|Panhandle|Read/Write| | L6: Charismatic and articulate, you champion your cause and try to change the world. | M6: Charm | N6: Dwarf, Halfling, Human | O6: 46 | P6: 3 | T6: 2 | U6: 1 | W6: 1 | X6: 4 | Y6: 1
A7: Agitator|2 | B7: Agitator | C7: 2 | D7: Burgher | E7: Agitator | F7: Brass 2 | G7: Cool, Dodge, Gamble, Intuition, Leadership, Melee (Brawling) | H7: Alley Cat, Argumentative, Impassioned Zeal, Public Speaker | I7: Leather Jack, Sturdy Crate | J7: |Art (Writing)|Charm|Consume Alcohol|Entertain (Storytelling)|Gossip|Haggle|Lore (Local)|Lore (Politics)|Trade (Printing)|Stealth (Urban)|Cool|Dodge|Gamble|Intuition|Leadership|Melee (Brawling)| | K7: |Blather|Gregarious|Panhandle|Read/Write|Alley Cat|Argumentative|Impassioned Zeal|Public Speaker| | L7: Charismatic and articulate, you champion your cause and try to change the world. | M7: Charm | N7: Dwarf, Halfling, Human | O7: 46 | P7: 3 | T7: 2 | U7: 1 | W7: 1 | X7: 4 | Y7: 1
A8: Agitator|3 | B8: Agitator | C8: 3 | D8: Burgher | E8: Rabble Rouser | F8: Brass 3 | G8: Athletics, Intimidate, Perception, Ranged (Throwing) | H8: Cat-tongued, Dirty Fighting, Flee!, Step Aside | I8: Hand Weapon, Pamphleteer | J8: |Art (Writing)|Charm|Consume Alcohol|Entertain (Storytelling)|Gossip|Haggle|Lore (Local)|Lore (Politics)|Trade (Printing)|Stealth (Urban)|Cool|Dodge|Gamble|Intuition|Leadership|Melee (Brawling)|Athletics|Intimidate|Perception|Ranged (Throwing)| | K8: |Blather|Gregarious|Panhandle|Read/Write|Alley Cat|Argumentative|Impassioned Zeal|Public Speaker|Cat-tongued|Dirty Fighting|Flee!|Step Aside| | L8: Charismatic and articulate, you champion your cause and try to change the world. | M8: Charm | N8: Dwarf, Halfling, Human | O8: 46 | P8: 3 | T8: 2 | U8: 1 | W8: 1 | X8: 4 | Y8: 1
A9: Agitator|4 | B9: Agitator | C9: 4 | D9: Burgher | E9: Demagogue | F9: Brass 5 | G9: Bribery, Lore (Heraldry) | H9: Etiquette (All), Master Orator, Schemer, Suave | I9: Impressive Hat, 3 Pamphleteers, Patron, Printing Press | J9: |Art (Writing)|Charm|Consume Alcohol|Entertain (Storytelling)|Gossip|Haggle|Lore (Local)|Lore (Politics)|Trade (Printing)|Stealth (Urban)|Cool|Dodge|Gamble|Intuition|Leadership|Melee (Brawling)|Athletics|Intimidate|Perception|Ranged (Throwing)|Bribery|Lore (Heraldry)| | K9: |Blather|Gregarious|Panhandle|Read/Write|Alley Cat|Argumentative|Impassioned Zeal|Public Speaker|Cat-tongued|Dirty Fighting|Flee!|Step Aside|Etiquette (any)|Master Orator|Schemer|Suave| | L9: Charismatic and articulate, you champion your cause and try to change the world. | M9: Charm | N9: Dwarf, Halfling, Human | O9: 46 | P9: 3 | T9: 2 | U9: 1 | W9: 1 | X9: 4 | Y9: 1
A10: Apothecary|1 | B10: Apothecary | C10: 1 | D10: Academic | E10: Apothecary's Apprentice | F10: Brass 3 | G10: Consume Alcohol, Endurance, Haggle, Heal, Language (Classical), Lore (Chemistry), Lore (Medicine), Perception, Trade (Apothecary), Trade (Poisoner) | H10: Acute Sense (Taste), Concoct, Craftsman (Apothecary), Read/Write | I10: Book (Blank), Leather Jerkin, Pestle and Mortar | J10: |Consume Alcohol|Endurance|Haggle|Heal|Language (Classical)|Lore (Chemistry)|Lore (Medicine)|Perception|Trade (Apothecary)|Trade (Poisoner)| | K10: |Acute Sense (Taste)|Concoct|Craftsman (Apothecary)|Read/Write| | L10: You use your knowledge of chemistry and concoction to mix and trade all manner of medicines and remedies. | M10: Trade (Apothecary) | N10: Dwarf, Halfling, High Elf, Human | O10: 47 | S10: 3 | T10: 1 | V10: 1 | W10: 1 | X10: 4 | Y10: 2
A11: Apothecary|2 | B11: Apothecary | C11: 2 | D11: Academic | E11: Apothecary | F11: Silver 1 | G11: Charm, Evaluate, Gossip, Language (Guilder), Secret Signs (Guilder), Stealth (Urban) | H11: Criminal, Dealmaker, Etiquette (Guilder), Pharmacist | I11: Guild Licence, Trade Tools (Apothecary) | J11: |Consume Alcohol|Endurance|Haggle|Heal|Language (Classical)|Lore (Chemistry)|Lore (Medicine)|Perception|Trade (Apothecary)|Trade (Poisoner)|Charm|Evaluate|Gossip|Language (Guilder)|Secret Signs (Guilder)|Stealth (Urban)| | K11: |Acute Sense (Taste)|Concoct|Craftsman (Apothecary)|Read/Write|Criminal|Dealmaker|Etiquette (Guilder)|Pharmacist| | L11: You use your knowledge of chemistry and concoction to mix and trade all manner of medicines and remedies. | M11: Trade (Apothecary) | N11: Dwarf, Halfling, High Elf, Human | O11: 47 | S11: 3 | T11: 1 | V11: 1 | W11: 1 | X11: 4 | Y11: 2
A12: Apothecary|3 | B12: Apothecary | C12: 3 | D12: Academic | E12: Master Apothecary | F12: Silver 3 | G12: Intuition, Leadership, Lore (Science), Research | H12: Bookish, Etiquette (Criminals or Scholars), Master Tradesman (Apothecary), Resistant (Poison) | I12: Apprentice, Book (Apothecary), Workshop (Apothecary) | J12: |Consume Alcohol|Endurance|Haggle|Heal|Language (Classical)|Lore (Chemistry)|Lore (Medicine)|Perception|Trade (Apothecary)|Trade (Poisoner)|Charm|Evaluate|Gossip|Language (Guilder)|Secret Signs (Guilder)|Stealth (Urban)|Intuition|Leadership|Lore (Science)|Research| | K12: |Acute Sense (Taste)|Concoct|Craftsman (Apothecary)|Read/Write|Criminal|Dealmaker|Etiquette (Guilder)|Pharmacist|Bookish|Etiquette (Criminals)|Etiquette (Scholars)|Master Tradesman (Apothecary)|Resistant (Poison)| | L12: You use your knowledge of chemistry and concoction to mix and trade all manner of medicines and remedies. | M12: Trade (Apothecary) | N12: Dwarf, Halfling, High Elf, Human | O12: 47 | S12: 3 | T12: 1 | V12: 1 | W12: 1 | X12: 4 | Y12: 2
A13: Apothecary|4 | B13: Apothecary | C13: 4 | D13: Academic | E13: Apothecary General | F13: Gold 1 | G13: Bribery, Intimidate | H13: Coolheaded, Kingpin, Savant (Chemistry), Savvy | I13: Commission Papers, Large Workshop (Apothecary) | J13: |Consume Alcohol|Endurance|Haggle|Heal|Language (Classical)|Lore (Chemistry)|Lore (Medicine)|Perception|Trade (Apothecary)|Trade (Poisoner)|Charm|Evaluate|Gossip|Language (Guilder)|Secret Signs (Guilder)|Stealth (Urban)|Intuition|Leadership|Lore (Science)|Research|Bribery|Intimidate| | K13: |Acute Sense (Taste)|Concoct|Craftsman (Apothecary)|Read/Write|Criminal|Dealmaker|Etiquette (Guilder)|Pharmacist|Bookish|Etiquette (Criminals)|Etiquette (Scholars)|Master Tradesman (Apothecary)|Resistant (Poison)|Coolheaded|Kingpin|Savant (Chemistry)|Savvy| | L13: You use your knowledge of chemistry and concoction to mix and trade all manner of medicines and remedies. | M13: Trade (Apothecary) | N13: Dwarf, Halfling, High Elf, Human | O13: 47 | S13: 3 | T13: 1 | V13: 1 | W13: 1 | X13: 4 | Y13: 2
A14: Artisan|1 | B14: Artisan | C14: 1 | D14: Burgher | E14: Apprentice Artisan | F14: Brass 2 | G14: Art (Any One), Athletics, Consume Alcohol, Cool, Dodge, Haggle, Endurance, Evaluate, Pick Lock, Trade (Any One) | H14: Craftsman (as Trade), Strong Back, Tenacious, Very Strong | I14: Chalk, Leather Jerkin, 1d10 Rags | J14: |Art (any)|Athletics|Consume Alcohol|Cool|Dodge|Haggle|Endurance|Evaluate|Pick Lock|Trade (any)| | K14: |Craftsman (any)|Strong Back|Tenacious|Very Strong| | L14: A skilled craftsperson, you take pride in your work, creating products for sale and commission. | M14: Trade (Any One) | N14: Dwarf, Halfling, High Elf, Human, Wood Elf | O14: 48 | R14: 1 | S14: 1 | V14: 1 | W14: 3 | X14: 4 | Y14: 2
A15: Artisan|2 | B15: Artisan | C15: 2 | D15: Burgher | E15: Artisan | F15: Silver 1 | G15: Charm, Drive, Lore (Local), Gossip, Language (Guilder), Perception | H15: Dealmaker, Etiquette (Guilder), Nimble-fingered, Sturdy | I15: Guild Licence, Trade Tools (as Trade) | J15: |Art (any)|Athletics|Consume Alcohol|Cool|Dodge|Haggle|Endurance|Evaluate|Pick Lock|Trade (any)|Charm|Drive|Lore (Local)|Gossip|Language (Guilder)|Perception| | K15: |Craftsman (any)|Strong Back|Tenacious|Very Strong|Dealmaker|Etiquette (Guilder)|Nimble-fingered|Sturdy| | L15: A skilled craftsperson, you take pride in your work, creating products for sale and commission. | M15: Trade (Any One) | N15: Dwarf, Halfling, High Elf, Human, Wood Elf | O15: 48 | R15: 1 | S15: 1 | V15: 1 | W15: 3 | X15: 4 | Y15: 2
A16: Artisan|3 | B16: Artisan | C16: 3 | D16: Burgher | E16: Master Artisan | F16: Silver 3 | G16: Intuition, Leadership, Research, Secret Signs (Guilder) | H16: Acute Sense (Taste or Touch), Master Tradesman (as Trade), Read/Write, Tinker | I16: Apprentice, Workshop (as Trade) | J16: |Art (any)|Athletics|Consume Alcohol|Cool|Dodge|Haggle|Endurance|Evaluate|Pick Lock|Trade (any)|Charm|Drive|Lore (Local)|Gossip|Language (Guilder)|Perception|Intuition|Leadership|Research|Secret Signs (Guilder)| | K16: |Craftsman (any)|Strong Back|Tenacious|Very Strong|Dealmaker|Etiquette (Guilder)|Nimble-fingered|Sturdy|Acute Sense (Taste)|Acute Sense (Touch)|Master Tradesman (any)|Read/Write|Tinker| | L16: A skilled craftsperson, you take pride in your work, creating products for sale and commission. | M16: Trade (Any One) | N16: Dwarf, Halfling, High Elf, Human, Wood Elf | O16: 48 | R16: 1 | S16: 1 | V16: 1 | W16: 3 | X16: 4 | Y16: 2
A17: Artisan|4 | B17: Artisan | C17: 4 | D17: Burgher | E17: Guildmaster | F17: Gold 1 | G17: Bribery, Intimidate | H17: Briber, Magnum Opus, Public Speaker, Schemer | I17: Guild, Quality Clothing | J17: |Art (any)|Athletics|Consume Alcohol|Cool|Dodge|Haggle|Endurance|Evaluate|Pick Lock|Trade (any)|Charm|Drive|Lore (Local)|Gossip|Language (Guilder)|Perception|Intuition|Leadership|Research|Secret Signs (Guilder)|Bribery|Intimidate| | K17: |Craftsman (any)|Strong Back|Tenacious|Very Strong|Dealmaker|Etiquette (Guilder)|Nimble-fingered|Sturdy|Acute Sense (Taste)|Acute Sense (Touch)|Master Tradesman (any)|Read/Write|Tinker|Briber|Magnum Opus|Public Speaker|Schemer| | L17: A skilled craftsperson, you take pride in your work, creating products for sale and commission. | M17: Trade (Any One) | N17: Dwarf, Halfling, High Elf, Human, Wood Elf | O17: 48 | R17: 1 | S17: 1 | V17: 1 | W17: 3 | X17: 4 | Y17: 2
A18: Artist|1 | B18: Artist | C18: 1 | D18: Courtier | E18: Apprentice Artist | F18: Brass 2 | G18: Art (Any One), Charm, Climb, Consume Alcohol, Evaluate, Gossip, Intuition, Lore (Art), Perception, Trade (Art Supplies) | H18: Artistic, Read/Write, Sharp, Strong Back | I18: Brush or Chisel or Writing Kit | J18: |Art (any)|Charm|Climb|Consume Alcohol|Evaluate|Gossip|Intuition|Lore (Art)|Perception|Trade (Art Supplies)| | K18: |Artistic|Read/Write|Sharp|Strong Back| | L18: You possess an artistic gift, and strive to create works that uplift the soul… or at least pay the bills. | M18: Art (Any One) | N18: Dwarf, Halfling, High Elf, Human, Wood Elf | O18: 49 | R18: 1 | T18: 1 | V18: 1 | W18: 3 | X18: 4 | Y18: 2
A19: Artist|2 | B19: Artist | C19: 2 | D19: Courtier | E19: Artist | F19: Silver 1 | G19: Endurance, Entertain (Storytelling), Gamble, Haggle, Lore (Heraldry), Melee (Fencing) | H19: Attractive, Carouser, Gregarious, Nimble-fingered | I19: Sling Bag containing Trade Tools (Artist) | J19: |Art (any)|Charm|Climb|Consume Alcohol|Evaluate|Gossip|Intuition|Lore (Art)|Perception|Trade (Art Supplies)|Endurance|Entertain (Storytelling)|Gamble|Haggle|Lore (Heraldry)|Melee (Fencing)| | K19: |Artistic|Read/Write|Sharp|Strong Back|Attractive|Carouser|Gregarious|Nimble-fingered| | L19: You possess an artistic gift, and strive to create works that uplift the soul… or at least pay the bills. | M19: Art (Any One) | N19: Dwarf, Halfling, High Elf, Human, Wood Elf | O19: 49 | R19: 1 | T19: 1 | V19: 1 | W19: 3 | X19: 4 | Y19: 2
A20: Artist|3 | B20: Artist | C20: 3 | D20: Courtier | E20: Master Artist | F20: Silver 4 | G20: Leadership, Lore (Any One), Research, Sleight of Hand | H20: Acute Sense (Sight or Touch), Dealmaker, Etiquette (Any One), Tenacious | I20: Apprentice, Patron, Workshop (Artist) | J20: |Art (any)|Charm|Climb|Consume Alcohol|Evaluate|Gossip|Intuition|Lore (Art)|Perception|Trade (Art Supplies)|Endurance|Entertain (Storytelling)|Gamble|Haggle|Lore (Heraldry)|Melee (Fencing)|Leadership|Lore (any)|Research|Sleight of Hand| | K20: |Artistic|Read/Write|Sharp|Strong Back|Attractive|Carouser|Gregarious|Nimble-fingered|Acute Sense (Sight)|Acute Sense (Touch)|Dealmaker|Etiquette (any)|Tenacious| | L20: You possess an artistic gift, and strive to create works that uplift the soul… or at least pay the bills. | M20: Art (Any One) | N20: Dwarf, Halfling, High Elf, Human, Wood Elf | O20: 49 | R20: 1 | T20: 1 | V20: 1 | W20: 3 | X20: 4 | Y20: 2
A21: Artist|4 | B21: Artist | C21: 4 | D21: Courtier | E21: Maestro | F21: Gold 2 | G21: Cool, Secret Signs (Any One) | H21: Ambidextrous, Magnum Opus, Savant (Art), Wealthy | I21: 3 Apprentices, Large Workshop (Artist), Library (Art) | J21: |Art (any)|Charm|Climb|Consume Alcohol|Evaluate|Gossip|Intuition|Lore (Art)|Perception|Trade (Art Supplies)|Endurance|Entertain (Storytelling)|Gamble|Haggle|Lore (Heraldry)|Melee (Fencing)|Leadership|Lore (any)|Research|Sleight of Hand|Cool|Secret Signs (any)| | K21: |Artistic|Read/Write|Sharp|Strong Back|Attractive|Carouser|Gregarious|Nimble-fingered|Acute Sense (Sight)|Acute Sense (Touch)|Dealmaker|Etiquette (any)|Tenacious|Ambidextrous|Magnum Opus|Savant (Art)|Wealthy| | L21: You possess an artistic gift, and strive to create works that uplift the soul… or at least pay the bills. | M21: Art (Any One) | N21: Dwarf, Halfling, High Elf, Human, Wood Elf | O21: 49 | R21: 1 | T21: 1 | V21: 1 | W21: 3 | X21: 4 | Y21: 2
A22: Bailiff|1 | B22: Bailiff | C22: 1 | D22: Peasant | E22: Tax Collector | F22: Silver 1 | G22: Athletics, Cool, Dodge, Endurance, Evaluate, Gossip, Intimidate, Melee (Basic), Perception, Pick Lock | H22: Break and Enter, Embezzle, Numismatics, Strong Back | I22: Hand Weapon, Small Lock Box | J22: |Athletics|Cool|Dodge|Endurance|Evaluate|Gossip|Intimidate|Melee (Basic)|Perception|Pick Lock| | K22: |Break and Enter|Embezzle|Numismatics|Strong Back| | L22: You are trusted by a local ruler to represent the law and administer their lands with a firm hand. | M22: Intimidate | N22: Dwarf, Halfling, Human | O22: 50 | P22: 1 | R22: 1 | T22: 1 | W22: 4 | X22: 3 | Y22: 2
A23: Bailiff|2 | B23: Bailiff | C23: 2 | D23: Peasant | E23: Bailiff | F23: Silver 5 | G23: Bribery, Charm, Haggle, Intuition, Leadership, Lore (Local) | H23: Criminal, Menacing, Public Speaker, Strike to Stun | I23: Leather Jack, 3 Tax Collectors | J23: |Athletics|Cool|Dodge|Endurance|Evaluate|Gossip|Intimidate|Melee (Basic)|Perception|Pick Lock|Bribery|Charm|Haggle|Intuition|Leadership|Lore (Local)| | K23: |Break and Enter|Embezzle|Numismatics|Strong Back|Criminal|Menacing|Public Speaker|Strike to Stun| | L23: You are trusted by a local ruler to represent the law and administer their lands with a firm hand. | M23: Intimidate | N23: Dwarf, Halfling, Human | O23: 50 | P23: 1 | R23: 1 | T23: 1 | W23: 4 | X23: 3 | Y23: 2
A24: Bailiff|3 | B24: Bailiff | C24: 3 | D24: Peasant | E24: Reeve | F24: Gold 1 | G24: Animal Care, Lore (Heraldry), Navigation, Ride (Horse) | H24: Argumentative, Kingpin, Nose for Trouble, Read/Write | I24: Bailiff, Breastplate, Riding Horse | J24: |Athletics|Cool|Dodge|Endurance|Evaluate|Gossip|Intimidate|Melee (Basic)|Perception|Pick Lock|Bribery|Charm|Haggle|Intuition|Leadership|Lore (Local)|Animal Care|Lore (Heraldry)|Navigation|Ride (Horse)| | K24: |Break and Enter|Embezzle|Numismatics|Strong Back|Criminal|Menacing|Public Speaker|Strike to Stun|Argumentative|Kingpin|Nose for Trouble|Read/Write| | L24: You are trusted by a local ruler to represent the law and administer their lands with a firm hand. | M24: Intimidate | N24: Dwarf, Halfling, Human | O24: 50 | P24: 1 | R24: 1 | T24: 1 | W24: 4 | X24: 3 | Y24: 2
A25: Bailiff|4 | B25: Bailiff | C25: 4 | D25: Peasant | E25: Magistrate | F25: Gold 2 | G25: Language (Classical), Lore (Law) | H25: Commanding Presence, Iron Will, Savvy, Schemer | I25: Library (Law), Quality Robes, Seal of Office | J25: |Athletics|Cool|Dodge|Endurance|Evaluate|Gossip|Intimidate|Melee (Basic)|Perception|Pick Lock|Bribery|Charm|Haggle|Intuition|Leadership|Lore (Local)|Animal Care|Lore (Heraldry)|Navigation|Ride (Horse)|Language (Classical)|Lore (Law)| | K25: |Break and Enter|Embezzle|Numismatics|Strong Back|Criminal|Menacing|Public Speaker|Strike to Stun|Argumentative|Kingpin|Nose for Trouble|Read/Write|Commanding Presence|Iron Will|Savvy|Schemer| | L25: You are trusted by a local ruler to represent the law and administer their lands with a firm hand. | M25: Intimidate | N25: Dwarf, Halfling, Human | O25: 50 | P25: 1 | R25: 1 | T25: 1 | W25: 4 | X25: 3 | Y25: 2
A26: Beggar|1 | B26: Beggar | C26: 1 | D26: Burgher | E26: Pauper | F26: Brass 0 | G26: Charm, Consume Alcohol, Dodge, Endurance, Gossip, Intuition, Outdoor Survival, Perception, Secret Signs (Vagabond), Stealth (Rural or Urban) | H26: Beneath Notice, Panhandle, Resistant (Disease), Stone Soup | I26: Cup, Poor Quality Blanket | J26: |Charm|Consume Alcohol|Dodge|Endurance|Gossip|Intuition|Outdoor Survival|Perception|Secret Signs (Vagabond)|Stealth (Rural)|Stealth (Urban)| | K26: |Beneath Notice|Panhandle|Resistant (Disease)|Stone Soup| | L26: Street-smart, you make a living from the charity of others using persuasion and charm. | M26: Charm | N26: Dwarf, Halfling, Human | O26: 51 | P26: 4 | S26: 1 | T26: 2 | U26: 1 | X26: 3 | Y26: 1
A27: Beggar|2 | B27: Beggar | C27: 2 | D27: Burgher | E27: Beggar | F27: Brass 1 | G27: Athletics, Cool, Entertain (Acting), Entertain (Any One), Lore (Local), Sleight of Hand | H27: Alley Cat, Blather, Criminal, Etiquette (Criminals) | I27: Bowl, Crutch | J27: |Charm|Consume Alcohol|Dodge|Endurance|Gossip|Intuition|Outdoor Survival|Perception|Secret Signs (Vagabond)|Stealth (Rural)|Stealth (Urban)|Athletics|Cool|Entertain (Acting)|Entertain (any)|Lore (Local)|Sleight of Hand| | K27: |Beneath Notice|Panhandle|Resistant (Disease)|Stone Soup|Alley Cat|Blather|Criminal|Etiquette (Criminals)| | L27: Street-smart, you make a living from the charity of others using persuasion and charm. | M27: Charm | N27: Dwarf, Halfling, Human | O27: 51 | P27: 4 | S27: 1 | T27: 2 | U27: 1 | X27: 3 | Y27: 1
A28: Beggar|3 | B28: Beggar | C28: 3 | D28: Burgher | E28: Master Beggar | F28: Brass 4 | G28: Charm Animal, Haggle, Leadership, Melee (Brawling) | H28: Dirty Fighting, Hardy, Step Aside, Very Resilient | I28: Disguise Kit, Hiding Place, Pauper Follower | J28: |Charm|Consume Alcohol|Dodge|Endurance|Gossip|Intuition|Outdoor Survival|Perception|Secret Signs (Vagabond)|Stealth (Rural)|Stealth (Urban)|Athletics|Cool|Entertain (Acting)|Entertain (any)|Lore (Local)|Sleight of Hand|Charm Animal|Haggle|Leadership|Melee (Brawling)| | K28: |Beneath Notice|Panhandle|Resistant (Disease)|Stone Soup|Alley Cat|Blather|Criminal|Etiquette (Criminals)|Dirty Fighting|Hardy|Step Aside|Very Resilient| | L28: Street-smart, you make a living from the charity of others using persuasion and charm. | M28: Charm | N28: Dwarf, Halfling, Human | O28: 51 | P28: 4 | S28: 1 | T28: 2 | U28: 1 | X28: 3 | Y28: 1
A29: Beggar|4 | B29: Beggar | C29: 4 | D29: Burgher | E29: Beggar King | F29: Silver 2 | G29: Bribery, Intimidate | H29: Cat-tongued, Dealmaker, Fearless (Watchmen), Suave | I29: Lair, Large Group of Beggar Followers | J29: |Charm|Consume Alcohol|Dodge|Endurance|Gossip|Intuition|Outdoor Survival|Perception|Secret Signs (Vagabond)|Stealth (Rural)|Stealth (Urban)|Athletics|Cool|Entertain (Acting)|Entertain (any)|Lore (Local)|Sleight of Hand|Charm Animal|Haggle|Leadership|Melee (Brawling)|Bribery|Intimidate| | K29: |Beneath Notice|Panhandle|Resistant (Disease)|Stone Soup|Alley Cat|Blather|Criminal|Etiquette (Criminals)|Dirty Fighting|Hardy|Step Aside|Very Resilient|Cat-tongued|Dealmaker|Fearless (Watchmen)|Suave| | L29: Street-smart, you make a living from the charity of others using persuasion and charm. | M29: Charm | N29: Dwarf, Halfling, Human | O29: 51 | P29: 4 | S29: 1 | T29: 2 | U29: 1 | X29: 3 | Y29: 1
A30: Boatman|1 | B30: Boatman | C30: 1 | D30: Riverfolk | E30: Boathand | F30: Brass 3 | G30: Athletics, Charm, Consume Alcohol, Dodge, Endurance, Gossip, Melee (Brawling), Row, Sail, Swim | H30: Fisherman, Strong Back, Strong Swimmer, Waterman | I30: Hand Weapon (Boat Hook), Leather Jack, Pole | J30: |Athletics|Charm|Consume Alcohol|Dodge|Endurance|Gossip|Melee (Brawling)|Row|Sail|Swim| | K30: |Fisherman|Strong Back|Strong Swimmer|Waterman| | L30: You ply the dangerous waters of the Old World, transporting people, goods, and the latest news. | M30: Sail | N30: Dwarf, Halfling, High Elf, Human | O30: 52 | R30: 1 | S30: 1 | T30: 2 | U30: 1 | V30: 3 | W30: 4
A31: Boatman|2 | B31: Boatman | C31: 2 | D31: Riverfolk | E31: Boatman | F31: Silver 1 | G31: Entertain (Storytelling), Haggle, Navigation, Lore (Riverways), Perception, Secret Signs (Guilder) | H31: Dirty Fighting, Etiquette (Guilder), Seasoned Traveller, Very Strong | I31: Rope, Rowboat | J31: |Athletics|Charm|Consume Alcohol|Dodge|Endurance|Gossip|Melee (Brawling)|Row|Sail|Swim|Entertain (Storytelling)|Haggle|Navigation|Lore (Riverways)|Perception|Secret Signs (Guilder)| | K31: |Fisherman|Strong Back|Strong Swimmer|Waterman|Dirty Fighting|Etiquette (Guilder)|Seasoned Traveller|Very Strong| | L31: You ply the dangerous waters of the Old World, transporting people, goods, and the latest news. | M31: Sail | N31: Dwarf, Halfling, High Elf, Human | O31: 52 | R31: 1 | S31: 1 | T31: 2 | U31: 1 | V31: 3 | W31: 4
A32: Boatman|3 | B32: Boatman | C32: 3 | D32: Riverfolk | E32: Bargeswain | F32: Silver 2 | G32: Climb, Heal, Intuition, Trade (Boatbuilder) | H32: Craftsman (Boatbuilder), Dealmaker, Embezzle, Nose for Trouble | I32: Backpack, Trade Tools (Carpenter), Trade Tools (Physician) | J32: |Athletics|Charm|Consume Alcohol|Dodge|Endurance|Gossip|Melee (Brawling)|Row|Sail|Swim|Entertain (Storytelling)|Haggle|Navigation|Lore (Riverways)|Perception|Secret Signs (Guilder)|Climb|Heal|Intuition|Trade (Boatbuilder)| | K32: |Fisherman|Strong Back|Strong Swimmer|Waterman|Dirty Fighting|Etiquette (Guilder)|Seasoned Traveller|Very Strong|Craftsman (Boatbuilder)|Dealmaker|Embezzle|Nose for Trouble| | L32: You ply the dangerous waters of the Old World, transporting people, goods, and the latest news. | M32: Sail | N32: Dwarf, Halfling, High Elf, Human | O32: 52 | R32: 1 | S32: 1 | T32: 2 | U32: 1 | V32: 3 | W32: 4
A33: Boatman|4 | B33: Boatman | C33: 4 | D33: Riverfolk | E33: Barge Master | F33: Silver 5 | G33: Cool, Leadership | H33: Orientation, Pilot, Public Speaker, Savant (Riverways) | I33: Barge and Crew, Hat | J33: |Athletics|Charm|Consume Alcohol|Dodge|Endurance|Gossip|Melee (Brawling)|Row|Sail|Swim|Entertain (Storytelling)|Haggle|Navigation|Lore (Riverways)|Perception|Secret Signs (Guilder)|Climb|Heal|Intuition|Trade (Boatbuilder)|Cool|Leadership| | K33: |Fisherman|Strong Back|Strong Swimmer|Waterman|Dirty Fighting|Etiquette (Guilder)|Seasoned Traveller|Very Strong|Craftsman (Boatbuilder)|Dealmaker|Embezzle|Nose for Trouble|Orientation|Pilot|Public Speaker|Savant (Riverways)| | L33: You ply the dangerous waters of the Old World, transporting people, goods, and the latest news. | M33: Sail | N33: Dwarf, Halfling, High Elf, Human | O33: 52 | R33: 1 | S33: 1 | T33: 2 | U33: 1 | V33: 3 | W33: 4
A34: Bounty Hunter|1 | B34: Bounty Hunter | C34: 1 | D34: Ranger | E34: Thief-taker | F34: Silver 1 | G34: Athletics, Charm, Cool, Gossip, Haggle, Intuition, Melee (Basic), Perception, Pick Lock, Stealth (Any One) | H34: Break and Enter, Shadow, Strike to Stun, Suave | I34: Hand Weapon, Leather Jerkin, Rope | J34: |Athletics|Charm|Cool|Gossip|Haggle|Intuition|Melee (Basic)|Perception|Pick Lock|Stealth (any)| | K34: |Break and Enter|Shadow|Strike to Stun|Suave| | L34: Ruthless and determined, you pursue your quarry to the bitter end: for justice, money, or both. | M34: Melee (Basic) | N34: Dwarf, Halfling, High Elf, Human, Wood Elf | O34: 53 | P34: 1 | Q34: 2 | R34: 1 | S34: 3 | U34: 1 | X34: 4
A35: Bounty Hunter|2 | B35: Bounty Hunter | C35: 2 | D35: Ranger | E35: Bounty Hunter | F35: Silver 3 | G35: Bribery, Endurance, Intimidate, Outdoor Survival, Ranged (Crossbow, Entangling, or Throwing), Track | H35: Marksman, Relentless, Seasoned Traveller, Strong Back | I35: 2 Bolas or Crossbow with 10 Bolts or Lasso, Leather Skullcap, Manacles, Net, Warrant Papers | J35: |Athletics|Charm|Cool|Gossip|Haggle|Intuition|Melee (Basic)|Perception|Pick Lock|Stealth (any)|Bribery|Endurance|Intimidate|Outdoor Survival|Ranged (Crossbow)|Ranged (Entangling)|Ranged (Throwing)|Track| | K35: |Break and Enter|Shadow|Strike to Stun|Suave|Marksman|Relentless|Seasoned Traveller|Strong Back| | L35: Ruthless and determined, you pursue your quarry to the bitter end: for justice, money, or both. | M35: Melee (Basic) | N35: Dwarf, Halfling, High Elf, Human, Wood Elf | O35: 53 | P35: 1 | Q35: 2 | R35: 1 | S35: 3 | U35: 1 | X35: 4
A36: Bounty Hunter|3 | B36: Bounty Hunter | C36: 3 | D36: Ranger | E36: Master Bounty Hunter | F36: Silver 5 | G36: Animal Care, Climb, Ride (Horse), Swim | H36: Accurate Shot, Careful Strike, Dual Wielder, Sprinter | I36: Mail Shirt, Riding Horse | J36: |Athletics|Charm|Cool|Gossip|Haggle|Intuition|Melee (Basic)|Perception|Pick Lock|Stealth (any)|Bribery|Endurance|Intimidate|Outdoor Survival|Ranged (Crossbow)|Ranged (Entangling)|Ranged (Throwing)|Track|Animal Care|Climb|Ride (Horse)|Swim| | K36: |Break and Enter|Shadow|Strike to Stun|Suave|Marksman|Relentless|Seasoned Traveller|Strong Back|Accurate Shot|Careful Strike|Dual Wielder|Sprinter| | L36: Ruthless and determined, you pursue your quarry to the bitter end: for justice, money, or both. | M36: Melee (Basic) | N36: Dwarf, Halfling, High Elf, Human, Wood Elf | O36: 53 | P36: 1 | Q36: 2 | R36: 1 | S36: 3 | U36: 1 | X36: 4
A37: Bounty Hunter|4 | B37: Bounty Hunter | C37: 4 | D37: Ranger | E37: Bounty Hunter General | F37: Gold 1 | G37: Drive, Lore (Law) | H37: Deadeye Shot, Fearless (Bounties), Hardy, Sure Shot | I37: Draught Horse and Cart, 4 Pairs of Manacles | J37: |Athletics|Charm|Cool|Gossip|Haggle|Intuition|Melee (Basic)|Perception|Pick Lock|Stealth (any)|Bribery|Endurance|Intimidate|Outdoor Survival|Ranged (Crossbow)|Ranged (Entangling)|Ranged (Throwing)|Track|Animal Care|Climb|Ride (Horse)|Swim|Drive|Lore (Law)| | K37: |Break and Enter|Shadow|Strike to Stun|Suave|Marksman|Relentless|Seasoned Traveller|Strong Back|Accurate Shot|Careful Strike|Dual Wielder|Sprinter|Deadeye Shot|Fearless (Bounties)|Hardy|Sure Shot| | L37: Ruthless and determined, you pursue your quarry to the bitter end: for justice, money, or both. | M37: Melee (Basic) | N37: Dwarf, Halfling, High Elf, Human, Wood Elf | O37: 53 | P37: 1 | Q37: 2 | R37: 1 | S37: 3 | U37: 1 | X37: 4
A38: Cavalryman|1 | B38: Cavalryman | C38: 1 | D38: Warrior | E38: Horseman | F38: Silver 3 | G38: Animal Care, Charm Animal, Consume Alcohol, Cool, Language (Battle), Melee (Cavalry), Outdoor Survival, Perception, Ranged (Blackpowder or Bow), Ride (Horse) | H38: Combat Aware, Dual Wielder, Lightning Reflexes, Roughrider | I38: Bow with 10 Arrows or Pistol with 10 Shots, Leather Jack, Light Warhorse | J38: |Animal Care|Charm Animal|Consume Alcohol|Cool|Language (Battle)|Melee (Cavalry)|Outdoor Survival|Perception|Ranged (Blackpowder)|Ranged (Bow)|Ride (Horse)| | K38: |Combat Aware|Dual Wielder|Lightning Reflexes|Roughrider| | L38: A dashing and fearless rider, you bring speed, versatility, and skill-at-arms to the battlefield. | M38: Ride (Horse) | N38: High Elf, Human, Wood Elf | O38: 54 | P38: 1 | Q38: 1 | R38: 2 | T38: 3 | U38: 1 | Y38: 4
A39: Cavalryman|2 | B39: Cavalryman | C39: 2 | D39: Warrior | E39: Cavalryman | F39: Silver 4 | G39: Charm, Endurance, Gamble, Gossip, Melee (Basic), Play (Horn) | H39: Etiquette (Soldiers), Gunner, Seasoned Traveller, Trick Rider | I39: Breastplate, Open Helm | J39: |Animal Care|Charm Animal|Consume Alcohol|Cool|Language (Battle)|Melee (Cavalry)|Outdoor Survival|Perception|Ranged (Blackpowder)|Ranged (Bow)|Ride (Horse)|Charm|Endurance|Gamble|Gossip|Melee (Basic)|Play (Horn)| | K39: |Combat Aware|Dual Wielder|Lightning Reflexes|Roughrider|Etiquette (Soldiers)|Gunner|Seasoned Traveller|Trick Rider| | L39: A dashing and fearless rider, you bring speed, versatility, and skill-at-arms to the battlefield. | M39: Ride (Horse) | N39: High Elf, Human, Wood Elf | O39: 54 | P39: 1 | Q39: 1 | R39: 2 | T39: 3 | U39: 1 | Y39: 4
A40: Cavalryman|3 | B40: Cavalryman | C40: 3 | D40: Warrior | E40: Cavalry Sergeant | F40: Gold 1 | G40: Intimidate, Leadership, Lore (Warfare), Ranged (Engineering) | H40: Combat Reflexes, Fast Shot, Hatred (Any One), War Leader | I40: Sash | J40: |Animal Care|Charm Animal|Consume Alcohol|Cool|Language (Battle)|Melee (Cavalry)|Outdoor Survival|Perception|Ranged (Blackpowder)|Ranged (Bow)|Ride (Horse)|Charm|Endurance|Gamble|Gossip|Melee (Basic)|Play (Horn)|Intimidate|Leadership|Lore (Warfare)|Ranged (Engineering)| | K40: |Combat Aware|Dual Wielder|Lightning Reflexes|Roughrider|Etiquette (Soldiers)|Gunner|Seasoned Traveller|Trick Rider|Combat Reflexes|Fast Shot|Hatred (any)|War Leader| | L40: A dashing and fearless rider, you bring speed, versatility, and skill-at-arms to the battlefield. | M40: Ride (Horse) | N40: High Elf, Human, Wood Elf | O40: 54 | P40: 1 | Q40: 1 | R40: 2 | T40: 3 | U40: 1 | Y40: 4
A41: Cavalryman|4 | B41: Cavalryman | C41: 4 | D41: Warrior | E41: Cavalry Officer | F41: Gold 2 | G41: Intuition, Lore (Heraldry) | H41: Accurate Shot, Inspiring, Read/Write, Robust | I41: Deck of Cards, Quality Clothing | J41: |Animal Care|Charm Animal|Consume Alcohol|Cool|Language (Battle)|Melee (Cavalry)|Outdoor Survival|Perception|Ranged (Blackpowder)|Ranged (Bow)|Ride (Horse)|Charm|Endurance|Gamble|Gossip|Melee (Basic)|Play (Horn)|Intimidate|Leadership|Lore (Warfare)|Ranged (Engineering)|Intuition|Lore (Heraldry)| | K41: |Combat Aware|Dual Wielder|Lightning Reflexes|Roughrider|Etiquette (Soldiers)|Gunner|Seasoned Traveller|Trick Rider|Combat Reflexes|Fast Shot|Hatred (any)|War Leader|Accurate Shot|Inspiring|Read/Write|Robust| | L41: A dashing and fearless rider, you bring speed, versatility, and skill-at-arms to the battlefield. | M41: Ride (Horse) | N41: High Elf, Human, Wood Elf | O41: 54 | P41: 1 | Q41: 1 | R41: 2 | T41: 3 | U41: 1 | Y41: 4
A42: Charlatan|1 | B42: Charlatan | C42: 1 | D42: Rogue | E42: Swindler | F42: Brass 3 | G42: Charm, Consume Alcohol, Cool, Entertain (Acting), Entertain (Storytelling), Gamble, Gossip, Haggle, Intuition, Sleight of Hand | H42: Cardsharp, Criminal, Dicer, Fast Hands | I42: Deck of Cards, Dice, 2 Sets of Clothing | J42: |Charm|Consume Alcohol|Cool|Entertain (Acting)|Entertain (Storytelling)|Gamble|Gossip|Haggle|Intuition|Sleight of Hand| | K42: |Cardsharp|Criminal|Dicer|Fast Hands| | L42: Unscrupulous and charming, you separate fools from their money; thankfully, there is no shortage of fools… | M42: Charm | N42: Halfling, High Elf, Human | O42: 55 | T42: 1 | U42: 3 | V42: 1 | W42: 2 | X42: 4 | Y42: 1
A43: Charlatan|2 | B43: Charlatan | C43: 2 | D43: Rogue | E43: Charlatan | F43: Brass 5 | G43: Bribery, Dodge, Evaluate, Language (Thieves Tongue), Perception, Secret Signs (Thief) | H43: Blather, Etiquette (Criminals), Mimic, Secret Identity | I43: Forged Document, Colourful Mixtures, Trinkets and Charms, 2 Sets of Quality Clothing | J43: |Charm|Consume Alcohol|Cool|Entertain (Acting)|Entertain (Storytelling)|Gamble|Gossip|Haggle|Intuition|Sleight of Hand|Bribery|Dodge|Evaluate|Language (Thieves Tongue)|Perception|Secret Signs (Thief)| | K43: |Cardsharp|Criminal|Dicer|Fast Hands|Blather|Etiquette (Criminals)|Mimic|Secret Identity| | L43: Unscrupulous and charming, you separate fools from their money; thankfully, there is no shortage of fools… | M43: Charm | N43: Halfling, High Elf, Human | O43: 55 | T43: 1 | U43: 3 | V43: 1 | W43: 2 | X43: 4 | Y43: 1
A44: Charlatan|3 | B44: Charlatan | C44: 3 | D44: Rogue | E44: Con Artist | F44: Silver 2 | G44: Language (Any One), Lore (Art), Lore (Heraldry), Pick Lock | H44: Attractive, Cat-tongued, Dealmaker, Read/Write | I44: Disguise Kit, Multiple Forged Documents | J44: |Charm|Consume Alcohol|Cool|Entertain (Acting)|Entertain (Storytelling)|Gamble|Gossip|Haggle|Intuition|Sleight of Hand|Bribery|Dodge|Evaluate|Language (Thieves Tongue)|Perception|Secret Signs (Thief)|Language (any)|Lore (Art)|Lore (Heraldry)|Pick Lock| | K44: |Cardsharp|Criminal|Dicer|Fast Hands|Blather|Etiquette (Criminals)|Mimic|Secret Identity|Attractive|Cat-tongued|Dealmaker|Read/Write| | L44: Unscrupulous and charming, you separate fools from their money; thankfully, there is no shortage of fools… | M44: Charm | N44: Halfling, High Elf, Human | O44: 55 | T44: 1 | U44: 3 | V44: 1 | W44: 2 | X44: 4 | Y44: 1
A45: Charlatan|4 | B45: Charlatan | C45: 4 | D45: Rogue | E45: Scoundrel | F45: Silver 4 | G45: Lore (Genealogy), Research | H45: Gregarious, Master of Disguise, Nose for Trouble, Suave | I45: Forged Seal, Writing Kit | J45: |Charm|Consume Alcohol|Cool|Entertain (Acting)|Entertain (Storytelling)|Gamble|Gossip|Haggle|Intuition|Sleight of Hand|Bribery|Dodge|Evaluate|Language (Thieves Tongue)|Perception|Secret Signs (Thief)|Language (any)|Lore (Art)|Lore (Heraldry)|Pick Lock|Lore (Genealogy)|Research| | K45: |Cardsharp|Criminal|Dicer|Fast Hands|Blather|Etiquette (Criminals)|Mimic|Secret Identity|Attractive|Cat-tongued|Dealmaker|Read/Write|Gregarious|Master of Disguise|Nose for Trouble|Suave| | L45: Unscrupulous and charming, you separate fools from their money; thankfully, there is no shortage of fools… | M45: Charm | N45: Halfling, High Elf, Human | O45: 55 | T45: 1 | U45: 3 | V45: 1 | W45: 2 | X45: 4 | Y45: 1
A46: Coachman|1 | B46: Coachman | C46: 1 | D46: Ranger | E46: Postilion | F46: Silver 1 | G46: Animal Care, Charm Animal, Climb, Drive, Endurance, Gossip, Melee (Basic), Perception, Play (Horn), Ride (Horse) | H46: Animal Affinity, Combat Aware, Seasoned Traveller, Tenacious | I46: Coach Horn, Hat, Leather Jerkin, Warm Coat | J46: |Animal Care|Charm Animal|Climb|Drive|Endurance|Gossip|Melee (Basic)|Perception|Play (Horn)|Ride (Horse)| | K46: |Animal Affinity|Combat Aware|Seasoned Traveller|Tenacious| | L46: Determined and rugged, you deliver passengers by coach, defying the perils of the Empire's roads. | M46: Drive | N46: Dwarf, Halfling, Human | O46: 56 | Q46: 2 | S46: 1 | T46: 3 | U46: 1 | X46: 1 | Y46: 4
A47: Coachman|2 | B47: Coachman | C47: 2 | D47: Ranger | E47: Coachman | F47: Silver 2 | G47: Consume Alcohol, Intuition, Lore (Local), Navigation, Ranged (Blackpowder), Ranged (Entangling) | H47: Crack the Whip, Criminal, Gunner, Strong-minded | I47: Blunderbuss with 10 Shots, Whip | J47: |Animal Care|Charm Animal|Climb|Drive|Endurance|Gossip|Melee (Basic)|Perception|Play (Horn)|Ride (Horse)|Consume Alcohol|Intuition|Lore (Local)|Navigation|Ranged (Blackpowder)|Ranged (Entangling)| | K47: |Animal Affinity|Combat Aware|Seasoned Traveller|Tenacious|Crack the Whip|Criminal|Gunner|Strong-minded| | L47: Determined and rugged, you deliver passengers by coach, defying the perils of the Empire's roads. | M47: Drive | N47: Dwarf, Halfling, Human | O47: 56 | Q47: 2 | S47: 1 | T47: 3 | U47: 1 | X47: 1 | Y47: 4
A48: Coachman|3 | B48: Coachman | C48: 3 | D48: Ranger | E48: Coach Master | F48: Silver 3 | G48: Animal Training (Horse), Intimidate, Language (Any One), Lore (Routes) | H48: Accurate Shot, Fearless (Outlaws), Marksman, Nose for Trouble | I48: Pistol with 10 Shots, Quality Cloak | J48: |Animal Care|Charm Animal|Climb|Drive|Endurance|Gossip|Melee (Basic)|Perception|Play (Horn)|Ride (Horse)|Consume Alcohol|Intuition|Lore (Local)|Navigation|Ranged (Blackpowder)|Ranged (Entangling)|Animal Training (Horse)|Intimidate|Language (any)|Lore (Routes)| | K48: |Animal Affinity|Combat Aware|Seasoned Traveller|Tenacious|Crack the Whip|Criminal|Gunner|Strong-minded|Accurate Shot|Fearless (Outlaws)|Marksman|Nose for Trouble| | L48: Determined and rugged, you deliver passengers by coach, defying the perils of the Empire's roads. | M48: Drive | N48: Dwarf, Halfling, Human | O48: 56 | Q48: 2 | S48: 1 | T48: 3 | U48: 1 | X48: 1 | Y48: 4
A49: Coachman|4 | B49: Coachman | C49: 4 | D49: Ranger | E49: Route Master | F49: Gold 2 | G49: Haggle, Leadership | H49: Dealmaker, Etiquette (Any One), Orientation, Read/Write | I49: Fleet of Coaches and Horses, Maps | J49: |Animal Care|Charm Animal|Climb|Drive|Endurance|Gossip|Melee (Basic)|Perception|Play (Horn)|Ride (Horse)|Consume Alcohol|Intuition|Lore (Local)|Navigation|Ranged (Blackpowder)|Ranged (Entangling)|Animal Training (Horse)|Intimidate|Language (any)|Lore (Routes)|Haggle|Leadership| | K49: |Animal Affinity|Combat Aware|Seasoned Traveller|Tenacious|Crack the Whip|Criminal|Gunner|Strong-minded|Accurate Shot|Fearless (Outlaws)|Marksman|Nose for Trouble|Dealmaker|Etiquette (any)|Orientation|Read/Write| | L49: Determined and rugged, you deliver passengers by coach, defying the perils of the Empire's roads. | M49: Drive | N49: Dwarf, Halfling, Human | O49: 56 | Q49: 2 | S49: 1 | T49: 3 | U49: 1 | X49: 1 | Y49: 4
A50: Duellist|1 | B50: Duellist | C50: 1 | D50: Courtier | E50: Fencer | F50: Silver 3 | G50: Athletics, Charm, Cool, Dodge, Gamble, Heal, Intuition, Language (Classical), Melee (Any One), Perception | H50: Beat Blade, Distract, Feint, Step Aside | I50: Melee Weapon (Any), Sling Bag containing Clothing and 1d10 Bandages | J50: |Athletics|Charm|Cool|Dodge|Gamble|Heal|Intuition|Language (Classical)|Melee (any)|Perception| | K50: |Beat Blade|Distract|Feint|Step Aside| | L50: Your blade is an instrument of justice, bound by long tradition and employed with deadly precision. | M50: Melee (Any One) | N50: Dwarf, High Elf, Human | O50: 57 | P50: 1 | Q50: 2 | R50: 3 | T50: 1 | U50: 1 | X50: 4
A51: Duellist|2 | B51: Duellist | C51: 2 | D51: Courtier | E51: Duellist | F51: Silver 4 | G51: Entertain (Storytelling), Endurance, Intimidate, Melee (Any One), Ranged (Blackpowder), Trade (Gunsmith) | H51: Combat Reflexes, Dual Wielder, Etiquette (Any One), Fast Shot | I51: Main Gauche or Sword-breaker, Pistol with 10 Shots | J51: |Athletics|Charm|Cool|Dodge|Gamble|Heal|Intuition|Language (Classical)|Melee (any)|Perception|Entertain (Storytelling)|Endurance|Intimidate|Ranged (Blackpowder)|Trade (Gunsmith)| | K51: |Beat Blade|Distract|Feint|Step Aside|Combat Reflexes|Dual Wielder|Etiquette (any)|Fast Shot| | L51: Your blade is an instrument of justice, bound by long tradition and employed with deadly precision. | M51: Melee (Any One) | N51: Dwarf, High Elf, Human | O51: 57 | P51: 1 | Q51: 2 | R51: 3 | T51: 1 | U51: 1 | X51: 4
A52: Duellist|3 | B52: Duellist | C52: 3 | D52: Courtier | E52: Duelmaster | F52: Gold 1 | G52: Leadership, Lore (Warfare), Melee (Any One), Perform (Acrobatics) | H52: Ambidextrous, Disarm, Reversal, Riposte | I52: Hand Weapon, Quality Rapier, Trusty Second, 2 Wooden Training Swords | J52: |Athletics|Charm|Cool|Dodge|Gamble|Heal|Intuition|Language (Classical)|Melee (any)|Perception|Entertain (Storytelling)|Endurance|Intimidate|Ranged (Blackpowder)|Trade (Gunsmith)|Leadership|Lore (Warfare)|Perform (Acrobatics)| | K52: |Beat Blade|Distract|Feint|Step Aside|Combat Reflexes|Dual Wielder|Etiquette (any)|Fast Shot|Ambidextrous|Disarm|Reversal|Riposte| | L52: Your blade is an instrument of justice, bound by long tradition and employed with deadly precision. | M52: Melee (Any One) | N52: Dwarf, High Elf, Human | O52: 57 | P52: 1 | Q52: 2 | R52: 3 | T52: 1 | U52: 1 | X52: 4
A53: Duellist|4 | B53: Duellist | C53: 4 | D53: Courtier | E53: Judicial Champion | F53: Gold 2 | G53: Lore (Law), Melee (Any One) | H53: Combat Master, Menacing, Reaction Strike, Strike to Injure | I53: 2 Quality Weapons | J53: |Athletics|Charm|Cool|Dodge|Gamble|Heal|Intuition|Language (Classical)|Melee (any)|Perception|Entertain (Storytelling)|Endurance|Intimidate|Ranged (Blackpowder)|Trade (Gunsmith)|Leadership|Lore (Warfare)|Perform (Acrobatics)|Lore (Law)| | K53: |Beat Blade|Distract|Feint|Step Aside|Combat Reflexes|Dual Wielder|Etiquette (any)|Fast Shot|Ambidextrous|Disarm|Reversal|Riposte|Combat Master|Menacing|Reaction Strike|Strike to Injure| | L53: Your blade is an instrument of justice, bound by long tradition and employed with deadly precision. | M53: Melee (Any One) | N53: Dwarf, High Elf, Human | O53: 57 | P53: 1 | Q53: 2 | R53: 3 | T53: 1 | U53: 1 | X53: 4
A54: Engineer|1 | B54: Engineer | C54: 1 | D54: Academic | E54: Student Engineer | F54: Brass 4 | G54: Art (Drawing), Consume Alcohol, Cool, Endurance, Evaluate, Language (Classical), Lore (Engineering), Ranged (Engineering), Research, Trade (Engineer) | H54: Craftsman (Engineer), Read/Write, Tinker, Unshakeable | I54: Book (Engineer), Hammer and Spikes | J54: |Art (Drawing)|Consume Alcohol|Cool|Endurance|Evaluate|Language (Classical)|Lore (Engineering)|Ranged (Engineering)|Research|Trade (Engineer)| | K54: |Craftsman (Engineer)|Read/Write|Tinker|Unshakeable| | L54: You create machines and constructions both useful and bizarre, and occasionally downright deadly. | M54: Trade (Engineer) | N54: Dwarf, Halfling, Human | O54: 58 | Q54: 2 | R54: 1 | T54: 3 | V54: 1 | W54: 1 | X54: 4
A55: Engineer|2 | B55: Engineer | C55: 2 | D55: Academic | E55: Engineer | F55: Silver 3 | G55: Drive, Language (Guilder), Lore (Science), Navigation, Ride (Horse), Secret Signs (Guilder) | H55: Etiquette (Guilder), Etiquette (Scholars), Gunner, Marksman | I55: Guild Licence, Trade Tools (Engineer) | J55: |Art (Drawing)|Consume Alcohol|Cool|Endurance|Evaluate|Language (Classical)|Lore (Engineering)|Ranged (Engineering)|Research|Trade (Engineer)|Drive|Language (Guilder)|Lore (Science)|Navigation|Ride (Horse)|Secret Signs (Guilder)| | K55: |Craftsman (Engineer)|Read/Write|Tinker|Unshakeable|Etiquette (Guilder)|Etiquette (Scholars)|Gunner|Marksman| | L55: You create machines and constructions both useful and bizarre, and occasionally downright deadly. | M55: Trade (Engineer) | N55: Dwarf, Halfling, Human | O55: 58 | Q55: 2 | R55: 1 | T55: 3 | V55: 1 | W55: 1 | X55: 4
A56: Engineer|3 | B56: Engineer | C56: 3 | D56: Academic | E56: Master Engineer | F56: Silver 5 | G56: Animal Training (Pigeon), Dodge, Language (Khazalid), Leadership | H56: Master Tradesman (Engineer), Orientation, Sniper, Super Numerate | I56: Workshop (Engineer) | J56: |Art (Drawing)|Consume Alcohol|Cool|Endurance|Evaluate|Language (Classical)|Lore (Engineering)|Ranged (Engineering)|Research|Trade (Engineer)|Drive|Language (Guilder)|Lore (Science)|Navigation|Ride (Horse)|Secret Signs (Guilder)|Animal Training (Pigeon)|Dodge|Language (Khazalid)|Leadership| | K56: |Craftsman (Engineer)|Read/Write|Tinker|Unshakeable|Etiquette (Guilder)|Etiquette (Scholars)|Gunner|Marksman|Master Tradesman (Engineer)|Orientation|Sniper|Super Numerate| | L56: You create machines and constructions both useful and bizarre, and occasionally downright deadly. | M56: Trade (Engineer) | N56: Dwarf, Halfling, Human | O56: 58 | Q56: 2 | R56: 1 | T56: 3 | V56: 1 | W56: 1 | X56: 4
A57: Engineer|4 | B57: Engineer | C57: 4 | D57: Academic | E57: Chartered Engineer | F57: Gold 2 | G57: Language (Any One), Perception | H57: Embezzle, Magnum Opus, Rapid Reload, Savant (Engineering) | I57: Library (Engineering), Quality Trade Tools (Engineer), Large Workshop (Engineer) | J57: |Art (Drawing)|Consume Alcohol|Cool|Endurance|Evaluate|Language (Classical)|Lore (Engineering)|Ranged (Engineering)|Research|Trade (Engineer)|Drive|Language (Guilder)|Lore (Science)|Navigation|Ride (Horse)|Secret Signs (Guilder)|Animal Training (Pigeon)|Dodge|Language (Khazalid)|Leadership|Language (any)|Perception| | K57: |Craftsman (Engineer)|Read/Write|Tinker|Unshakeable|Etiquette (Guilder)|Etiquette (Scholars)|Gunner|Marksman|Master Tradesman (Engineer)|Orientation|Sniper|Super Numerate|Embezzle|Magnum Opus|Rapid Reload|Savant (Engineering)| | L57: You create machines and constructions both useful and bizarre, and occasionally downright deadly. | M57: Trade (Engineer) | N57: Dwarf, Halfling, Human | O57: 58 | Q57: 2 | R57: 1 | T57: 3 | V57: 1 | W57: 1 | X57: 4
A58: Entertainer|1 | B58: Entertainer | C58: 1 | D58: Ranger | E58: Busker | F58: Brass 3 | G58: Athletics, Charm, Consume Alcohol, Dodge, Entertain (Any One), Gossip, Haggle, Perform (Any One), Play (Any One), Sleight of Hand | H58: Attractive, Mimic, Perfect Pitch, Suave | I58: Bowl, Musical Instrument | J58: |Athletics|Charm|Consume Alcohol|Dodge|Entertain (any)|Gossip|Haggle|Perform (any)|Play (any)|Sleight of Hand| | K58: |Attractive|Mimic|Perfect Pitch|Suave| | L58: From the village green to the grandest theatre, you bring diversion and enjoyment to the people. | M58: Entertain (Any One) | N58: Dwarf, Halfling, High Elf, Human, Wood Elf | O58: 59 | P58: 2 | Q58: 3 | S58: 4 | U58: 1 | V58: 1 | Y58: 1
A59: Entertainer|2 | B59: Entertainer | C59: 2 | D59: Ranger | E59: Entertainer | F59: Brass 5 | G59: Entertain (Any One), Melee (Basic), Perform (Any One), Play (Any One), Ranged (Throwing), Ride (Any One) | H59: Contortionist, Jump Up, Sharpshooter, Trick Rider | I59: Costume, Instrument, 5 Throwing Knives | J59: |Athletics|Charm|Consume Alcohol|Dodge|Entertain (any)|Gossip|Haggle|Perform (any)|Play (any)|Sleight of Hand|Melee (Basic)|Ranged (Throwing)|Ride (any)| | K59: |Attractive|Mimic|Perfect Pitch|Suave|Contortionist|Jump Up|Sharpshooter|Trick Rider| | L59: From the village green to the grandest theatre, you bring diversion and enjoyment to the people. | M59: Entertain (Any One) | N59: Dwarf, Halfling, High Elf, Human, Wood Elf | O59: 59 | P59: 2 | Q59: 3 | S59: 4 | U59: 1 | V59: 1 | Y59: 1
A60: Entertainer|3 | B60: Entertainer | C60: 3 | D60: Ranger | E60: Troubadour | F60: Silver 3 | G60: Animal Care, Animal Training (Any One), Art (Writing), Language (Any One) | H60: Blather, Master of Disguise, Public Speaker, Read/Write | I60: Trained Animal, Writing Kit | J60: |Athletics|Charm|Consume Alcohol|Dodge|Entertain (any)|Gossip|Haggle|Perform (any)|Play (any)|Sleight of Hand|Melee (Basic)|Ranged (Throwing)|Ride (any)|Animal Care|Animal Training (any)|Art (Writing)|Language (any)| | K60: |Attractive|Mimic|Perfect Pitch|Suave|Contortionist|Jump Up|Sharpshooter|Trick Rider|Blather|Master of Disguise|Public Speaker|Read/Write| | L60: From the village green to the grandest theatre, you bring diversion and enjoyment to the people. | M60: Entertain (Any One) | N60: Dwarf, Halfling, High Elf, Human, Wood Elf | O60: 59 | P60: 2 | Q60: 3 | S60: 4 | U60: 1 | V60: 1 | Y60: 1
